Workbook
Name Print_Titles: SUM!$1:$7
Name Print_Titles: '2026'!$1:$7
Name Print_Titles: '2025'!$1:$7
Name Print_Titles: '2024'!$1:$7

Sheet SUM
C1: <- Click 1 for standard view, 2 for deep dive
C2: HOTEL MALURI PROFIT & LOSS STATEMENT
C4: SUMMARY | O4: YEAR 2024 | AH4: YEAR 2025 | BA4: YEAR 2026
D6: ACC CODE | E6: 46174 | F6: 45809 | G6: VAR | H6: Q2 2026 | I6: Q2 2025 | J6: VAR | K6: YTD 2026 | L6: YTD 2025 | M6: VAR | O6: 45292 | P6: 45323 | Q6: 45352 | R6: 45383 | S6: 45413 | T6: 45444 | U6: 45474 | V6: 45505 | W6: 45536 | X6: 45566 | Y6: 45597 | Z6: 45627 | AA6: TOTAL | AB6: Q1 2024 | AC6: Q2 2024 | AD6: Q3 2024 | AE6: Q4 2024 | AF6: TOTAL | AH6: 45658 | AI6: 45689 | AJ6: 45717 | AK6: 45748 | AL6: 45778 | AM6: 45809 | AN6: 45839 | AO6: 45870 | AP6: 45901 | AQ6: 45931 | AR6: 45962 | AS6: 45992 | AT6: TOTAL | AU6: Q1 2025 | AV6: Q2 2025 | AW6: Q3 2025 | AX6: Q4 2025 | AY6: TOTAL | BA6: 46023 | BB6: 46054 | BC6: 46082 | BD6: 46113 | BE6: 46143 | BF6: 46174 | BG6: 46204 | BH6: 46235 | BI6: 46266 | BJ6: 46296 | BK6: 46327 | BL6: 46357 | BM6: TOTAL | BN6: Q1 2026 | BO6: Q2 2026 | BP6: Q3 2026 | BQ6: Q4 2026 | BR6: TOTAL
C8: ROOM STATS
C10: ROOMS AVAILABLE | E10: =SUMIF($BA$6:$BL$6,$E$6,$BA10:$BL10) -> 4440 | F10: =SUMIF($AH$6:$AS$6,$F$6,$AH10:$AS10) -> 4440 | G10: =(E10-F10)/F10 -> 0 | H10: =SUMIF($BN$6:$BR$6,$H$6,$BN10:$BR10) -> 13468 | I10: =SUMIF($AU$6:$AY$6,$I$6,$AU10:$AY10) -> 17677 | J10: =(H10-I10)/I10 -> -0.23810601 | K10: =BM10 -> 26788 | L10: =SUM(AH10:AM10) -> 37207 | M10: =(K10-L10)/L10 -> -0.28002795 | O10: 6727 | P10: 6293 | Q10: 6727 | R10: 6510 | S10: 6727 | T10: 6510 | U10: 6727 | V10: 6727 | W10: 6510 | X10: 6727 | Y10: 6510 | Z10: 6727 | AA10: =SUM(O10:Z10) -> 79422 | AB10: =SUM(O10:Q10) -> 19747 | AC10: =SUM(R10:T10) -> 19747 | AD10: =SUM(U10:W10) -> 19964 | AE10: =SUM(X10:Z10) -> 19964 | AF10: =SUM(AB10:AE10) -> 79422 | AH10: 6727 | AI10: 6076 | AJ10: 6727 | AK10: 6510 | AL10: 6727 | AM10: 4440 | AN10: 4588 | AO10: 4588 | AP10: 4440 | AQ10: 4588 | AR10: 4440 | AS10: 1 | AT10: =SUM(AH10:AS10) -> 59852 | AU10: =SUM(AH10:AJ10) -> 19530 | AV10: =SUM(AK10:AM10) -> 17677 | AW10: =SUM(AN10:AP10) -> 13616 | AX10: =SUM(AQ10:AS10) -> 9029 | AY10: =SUM(AU10:AX10) -> 59852 | BA10: 4588 | BB10: 4144 | BC10: 4588 | BD10: ='2026'!H10 -> 4440 | BE10: ='2026'!I10 -> 4588 | BF10: ='2026'!J10 -> 4440 | BG10: ='2026'!K10 -> 0 | BH10: ='2026'!L10 -> 0 | BI10: ='2026'!M10 -> 0 | BJ10: ='2026'!N10 -> 0 | BK10: ='2026'!O10 -> 0 | BL10: ='2026'!P10 -> 0 | BM10: =SUM(BA10:BL10) -> 26788 | BN10: =SUM(BA10:BC10) -> 13320 | BO10: =SUM(BD10:BF10) -> 13468 | BP10: =SUM(BG10:BI10) -> 0 | BQ10: =SUM(BJ10:BL10) -> 0 | BR10: =SUM(BN10:BQ10) -> 26788
C11: ROOM SOLD | E11: =SUMIF($BA$6:$BL$6,$E$6,$BA11:$BL11) -> 2397 | F11: =SUMIF($AH$6:$AS$6,$F$6,$AH11:$AS11) -> 2193 | G11: =(E11-F11)/F11 -> 0.093023256 | H11: =SUMIF($BN$6:$BR$6,$H$6,$BN11:$BR11) -> 7284 | I11: =SUMIF($AU$6:$AY$6,$I$6,$AU11:$AY11) -> 6602 | J11: =(H11-I11)/I11 -> 0.10330203 | K11: =BM11 -> 14363 | L11: =SUM(AH11:AM11) -> 13295 | M11: =(K11-L11)/L11 -> 0.080330951 | O11: 1500 | P11: 2279 | Q11: 1846 | R11: 1665 | S11: 2319 | T11: 2266 | U11: 3006 | V11: 3005 | W11: 2535 | X11: 2460 | Y11: 2538 | Z11: 3117 | AA11: =SUM(O11:Z11) -> 28536 | AB11: =SUM(O11:Q11) -> 5625 | AC11: =SUM(R11:T11) -> 6250 | AD11: =SUM(U11:W11) -> 8546 | AE11: =SUM(X11:Z11) -> 8115 | AF11: =SUM(AB11:AE11) -> 28536 | AH11: 2536 | AI11: 2433 | AJ11: 1724 | AK11: 2143 | AL11: 2266 | AM11: 2193 | AN11: 2158 | AO11: 2340 | AP11: 2147 | AQ11: 1646 | AR11: 1746 | AS11: 1 | AT11: =SUM(AH11:AS11) -> 23333 | AU11: =SUM(AH11:AJ11) -> 6693 | AV11: =SUM(AK11:AM11) -> 6602 | AW11: =SUM(AN11:AP11) -> 6645 | AX11: =SUM(AQ11:AS11) -> 3393 | AY11: =SUM(AU11:AX11) -> 23333 | BA11: 2681 | BB11: 2313 | BC11: 2085 | BD11: ='2026'!H11 -> 2418 | BE11: ='2026'!I11 -> 2469 | BF11: ='2026'!J11 -> 2397 | BG11: ='2026'!K11 -> 0 | BH11: ='2026'!L11 -> 0 | BI11: ='2026'!M11 -> 0 | BJ11: ='2026'!N11 -> 0 | BK11: ='2026'!O11 -> 0 | BL11: ='2026'!P11 -> 0 | BM11: =SUM(BA11:BL11) -> 14363 | BN11: =SUM(BA11:BC11) -> 7079 | BO11: =SUM(BD11:BF11) -> 7284 | BP11: =SUM(BG11:BI11) -> 0 | BQ11: =SUM(BJ11:BL11) -> 0 | BR11: =SUM(BN11:BQ11) -> 14363
C12: OCCUPANCY % | E12: =SUMIF($BA$6:$BL$6,$E$6,$BA12:$BL12) -> 0.53986486 | F12: =SUMIF($AH$6:$AS$6,$F$6,$AH12:$AS12) -> 0.49391892 | G12: =(E12-F12)/F12 -> 0.093023256 | H12: =SUMIF($BN$6:$BR$6,$H$6,$BN12:$BR12) -> 0.54083754 | I12: =SUMIF($AU$6:$AY$6,$I$6,$AU12:$AY12) -> 0.37347966 | J12: =(H12-I12)/I12 -> 0.44810439 | K12: =BM12 -> 0.53617291 | L12: =L11/L10 -> 0.35732523 | M12: =(K12-L12)/L12 -> 0.50051791 | O12: =O11/O10 -> 0.22298201 | P12: =P11/P10 -> 0.36214842 | Q12: =Q11/Q10 -> 0.27441653 | R12: =R11/R10 -> 0.25576037 | S12: =S11/S10 -> 0.34473019 | T12: =T11/T10 -> 0.34807988 | U12: =U11/U10 -> 0.44685595 | V12: =V11/V10 -> 0.4467073 | ... Z12: =Z11/Z10 -> 0.46335662 | AA12: =SUM(O12:Z12) -> 4.3099904 | AB12: =AB11/AB10 -> 0.2848534 | AC12: =AC11/AC10 -> 0.31650377 | AD12: =AD11/AD10 -> 0.42807053 | AE12: =AE11/AE10 -> 0.40648167 | AF12: =AF11/AF10 -> 0.35929591 | AH12: =AH11/AH10 -> 0.37698826 | AI12: =AI11/AI10 -> 0.40042791 | AJ12: =AJ11/AJ10 -> 0.25628066 | AK12: =AK11/AK10 -> 0.32918587 | AL12: =AL11/AL10 -> 0.33685149 | AM12: =AM11/AM10 -> 0.49391892 | AN12: =AN11/AN10 -> 0.47035745 | AO12: =AO11/AO10 -> 0.51002616 | ... AS12: =AS11/AS10 -> 1 | AT12: =SUM(AH12:AS12) -> 5.4096005 | AU12: =AU11/AU10 -> 0.34270353 | AV12: =AV11/AV10 -> 0.37347966 | AW12: =AW11/AW10 -> 0.48802879 | AX12: =AX11/AX10 -> 0.37578912 | AY12: =AY11/AY10 -> 0.38984495 | BA12: =BA11/BA10 -> 0.58435048 | BB12: =BB11/BB10 -> 0.55815637 | BC12: =BC11/BC10 -> 0.45444638 | BD12: ='2026'!H12 -> 0.54459459 | BE12: ='2026'!I12 -> 0.53814298 | BF12: ='2026'!J12 -> 0.53986486 | BG12: ='2026'!K12 -> 0 | BH12: ='2026'!L12 -> 0 | BI12: ='2026'!M12 -> 0 | BJ12: ='2026'!N12 -> 0 | BK12: ='2026'!O12 -> 0 | BL12: ='2026'!P12 -> 0 | BM12: =BM11/BM10 -> 0.53617291 | BN12: =BN11/BN10 -> 0.53145646 | BO12: =BO11/BO10 -> 0.54083754 | BR12: =BR11/BR10 -> 0.53617291
C13: AVERAGE RATE | E13: =SUMIF($BA$6:$BL$6,$E$6,$BA13:$BL13) -> 153.36213 | F13: =SUMIF($AH$6:$AS$6,$F$6,$AH13:$AS13) -> 147.00023 | G13: =(E13-F13)/F13 -> 0.04327819 | H13: =SUMIF($BN$6:$BR$6,$H$6,$BN13:$BR13) -> 466.64773 | I13: =SUMIF($AU$6:$AY$6,$I$6,$AU13:$AY13) -> 440.69976 | J13: =(H13-I13)/I13 -> 0.058879016 | K13: =BM13 -> 938.38147 | L13: =SUM(AH13:AM13) -> 882.6377 | M13: =(K13-L13)/L13 -> 0.063155889 | O13: 132.20001 | P13: 135.93266 | Q13: 140.73536 | R13: 139.35417 | S13: 142.53889 | T13: 139.04339 | U13: 137.75687 | V13: 137.87402 | W13: 143.76785 | X13: 140.60951 | Y13: 140.50317 | Z13: 153.24232 | AA13: =SUM(O13:Z13) -> 1683.5582 | AB13: =SUM(O13:Q13) -> 408.86803 | AC13: =SUM(R13:T13) -> 420.93645 | AD13: =SUM(U13:W13) -> 419.39873 | AE13: =SUM(X13:Z13) -> 434.355 | AF13: =SUM(AB13:AE13) -> 1683.5582 | AH13: =SUM(AH28:AH29)/AH11 -> 148.26769 | AI13: =SUM(AI28:AI29)/AI11 -> 148.44627 | AJ13: =SUM(AJ28:AJ29)/AJ11 -> 145.22398 | AK13: =SUM(AK28:AK29)/AK11 -> 146.0393 | AL13: =SUM(AL28:AL29)/AL11 -> 147.66023 | AM13: =SUM(AM28:AM29)/AM11 -> 147.00023 | AN13: =SUM(AN28:AN29)/AN11 -> 144.92735 | AO13: =SUM(AO28:AO29)/AO11 -> 150.91782 | ... AS13: =SUM(AS28:AS29)/AS11 -> 460827.59 | AT13: =SUM(AH13:AS13) -> 462456.63 | AU13: =SUM(AH13:AJ13) -> 441.93794 | AV13: =SUM(AK13:AM13) -> 440.69976 | AW13: =SUM(AN13:AP13) -> 451.16672 | AX13: =SUM(AQ13:AS13) -> 461122.82 | AY13: =SUM(AU13:AX13) -> 462456.63 | BA13: =SUM(BA28:BA29)/BA11 -> 157.11885 | BB13: =SUM(BB28:BB29)/BB11 -> 160.27401 | BC13: =SUM(BC28:BC29)/BC11 -> 154.34088 | BD13: ='2026'!H13 -> 152.50555 | BE13: ='2026'!I13 -> 160.78005 | BF13: ='2026'!J13 -> 153.36213 | BG13: ='2026'!K13 -> 0 | BH13: ='2026'!L13 -> 0 | BI13: ='2026'!M13 -> 0 | BJ13: ='2026'!N13 -> 0 | BK13: ='2026'!O13 -> 0 | BL13: ='2026'!P13 -> 0 | BM13: =SUM(BA13:BL13) -> 938.38147 | BN13: =SUM(BA13:BC13) -> 471.73374 | BO13: =SUM(BD13:BF13) -> 466.64773 | BP13: =SUM(BG13:BI13) -> 0 | BQ13: =SUM(BJ13:BL13) -> 0 | BR13: =SUM(BN13:BQ13) -> 938.38147
C14: REV PAR | E14: =SUMIF($BA$6:$BL$6,$E$6,$BA14:$BL14) -> 82.794827 | F14: =SUMIF($AH$6:$AS$6,$F$6,$AH14:$AS14) -> 72.606194 | G14: =(E14-F14)/F14 -> 0.14032732 | H14: =SUMIF($BN$6:$BR$6,$H$6,$BN14:$BR14) -> 252.37118 | I14: =SUMIF($AU$6:$AY$6,$I$6,$AU14:$AY14) -> 170.41984 | J14: =(H14-I14)/I14 -> 0.48087912 | K14: =BM14 -> 503.78127 | L14: =SUM(AH14:AM14) -> 322.97514 | M14: =(K14-L14)/L14 -> 0.55981437 | O14: 29.478224 | P14: 49.227799 | Q14: 38.620109 | R14: 35.641275 | S14: 49.137458 | T14: 48.398206 | U14: 61.557477 | V14: 61.58933 | W14: 55.983332 | X14: 51.419563 | Y14: 54.776813 | Z14: 71.005844 | AA14: =SUM(O14:Z14) -> 606.83543 | AB14: =SUM(O14:Q14) -> 117.32613 | AC14: =SUM(R14:T14) -> 133.17694 | AD14: =SUM(U14:W14) -> 179.13014 | AE14: =SUM(X14:Z14) -> 177.20222 | AF14: =SUM(AB14:AE14) -> 606.83543 | AH14: =(AH11/AH10)*AH13 -> 55.895179 | AI14: =(AI11/AI10)*AI13 -> 59.442029 | AJ14: =(AJ11/AJ10)*AJ13 -> 37.218097 | AK14: =(AK11/AK10)*AK13 -> 48.074075 | AL14: =(AL11/AL10)*AL13 -> 49.739569 | AM14: =(AM11/AM10)*AM13 -> 72.606194 | AN14: =(AN11/AN10)*AN13 -> 68.167661 | AO14: =(AO11/AO10)*AO13 -> 76.972036 | ... AS14: =(AS11/AS10)*AS13 -> 460827.59 | AT14: =SUM(AH14:AS14) -> 461481.9 | AU14: =SUM(AH14:AJ14) -> 152.55531 | AV14: =SUM(AK14:AM14) -> 170.41984 | AW14: =SUM(AN14:AP14) -> 220.24676 | AX14: =SUM(AQ14:AS14) -> 460938.68 | AY14: =SUM(AU14:AX14) -> 461481.9 | BA14: =(BA11/BA10)*BA13 -> 91.812476 | BB14: =(BB11/BB10)*BB13 -> 89.457961 | BC14: =(BC11/BC10)*BC13 -> 70.139653 | BD14: ='2026'!H14 -> 83.053696 | BE14: ='2026'!I14 -> 86.522657 | BF14: ='2026'!J14 -> 82.794827 | BG14: ='2026'!K14 -> 0 | BH14: ='2026'!L14 -> 0 | BI14: ='2026'!M14 -> 0 | BJ14: ='2026'!N14 -> 0 | BK14: ='2026'!O14 -> 0 | BL14: ='2026'!P14 -> 0 | BM14: =SUM(BA14:BL14) -> 503.78127 | BN14: =SUM(BA14:BC14) -> 251.41009 | BO14: =SUM(BD14:BF14) -> 252.37118 | BP14: =SUM(BG14:BI14) -> 0 | BQ14: =SUM(BJ14:BL14) -> 0 | BR14: =SUM(BN14:BQ14) -> 503.78127
AB15: =SUM(O15:Q15) -> 0 | AC15: =SUM(R15:T15) -> 0 | AD15: =SUM(U15:W15) -> 0 | AE15: =SUM(X15:Z15) -> 0 | AU15: =SUM(AH15:AJ15) -> 0 | AV15: =SUM(AK15:AM15) -> 0 | AW15: =SUM(AN15:AP15) -> 0 | AX15: =SUM(AQ15:AS15) -> 0 | BN15: =SUM(BA15:BC15) -> 0 | BO15: =SUM(BD15:BF15) -> 0 | BP15: =SUM(BG15:BI15) -> 0 | BQ15: =SUM(BJ15:BL15) -> 0
C16: TOTAL COST | E16: =E108+E221 -> 587454.79 | F16: =F108+F221 -> 459903.73 | G16: =(E16-F16)/F16 -> 0.27734296 | H16: =H108+H221 -> 1747555 | I16: =I108+I221 -> 1431383.3 | J16: =(H16-I16)/I16 -> 0.22088541 | K16: =BM16 -> 3760105.2 | L16: =SUM(AH16:AM16) -> 3130998.7 | M16: =(K16-L16)/L16 -> 0.20092836 | O16: =O108+O221 -> 644636.49 | P16: =P108+P221 -> 483942.81 | Q16: =Q108+Q221 -> 586857.15 | R16: =R108+R221 -> 494401 | S16: =S108+S221 -> 563988.36 | T16: =T108+T221 -> 531323.95 | U16: =U108+U221 -> 767245.55 | V16: =V108+V221 -> 690800.38 | ... Z16: =Z108+Z221 -> 575262.78 | AA16: =SUM(O16:Z16) -> 6937772.6 | AB16: =SUM(O16:Q16) -> 1715436.4 | AC16: =SUM(R16:T16) -> 1589713.3 | AD16: =SUM(U16:W16) -> 1982141.9 | AE16: =SUM(X16:Z16) -> 1650481 | AF16: =SUM(AB16:AE16) -> 6937772.7 | AH16: =AH108+AH221 -> 682120.09 | AI16: =AI108+AI221 -> 513180.3 | AJ16: =AJ108+AJ221 -> 504315 | AK16: =AK108+AK221 -> 458222.32 | AL16: =AL108+AL221 -> 513257.28 | AM16: =AM108+AM221 -> 459903.73 | AN16: =AN108+AN221 -> 472504.77 | AO16: =AO108+AO221 -> 786386.7 | ... AS16: =AS108+AS221 -> 1638506.3 | AT16: =SUM(AH16:AS16) -> 7501944.3 | AU16: =SUM(AH16:AJ16) -> 1699615.4 | AV16: =SUM(AK16:AM16) -> 1431383.3 | AW16: =SUM(AN16:AP16) -> 1758521.9 | AX16: =SUM(AQ16:AS16) -> 2612423.7 | AY16: =SUM(AU16:AX16) -> 7501944.3 | BA16: =BA108+BA221 -> 704693.07 | BB16: =BB108+BB221 -> 642668.4 | BC16: =BC108+BC221 -> 665188.67 | BD16: =BD108+BD221 -> 572560.52 | BE16: =BE108+BE221 -> 587539.72 | BF16: =BF108+BF221 -> 587454.79 | BG16: =BG108+BG221 -> 0 | BH16: =BH108+BH221 -> 0 | ... BL16: =BL108+BL221 -> 0 | BM16: =SUM(BA16:BL16) -> 3760105.2 | BN16: =SUM(BA16:BC16) -> 2012550.1 | BO16: =SUM(BD16:BF16) -> 1747555 | BP16: =SUM(BG16:BI16) -> 0 | BQ16: =SUM(BJ16:BL16) -> 0 | BR16: =SUM(BN16:BQ16) -> 3760105.2
C17: AVERAGE COST | E17: =E16/1 -> 587454.79 | F17: =F16/1 -> 459903.73 | G17: =(E17-F17)/F17 -> 0.27734296 | H17: =H16/3 -> 582518.34 | I17: =I16/3 -> 477127.78 | J17: =(H17-I17)/I17 -> 0.22088541 | K17: =K16/MONTH(E$6) -> 626684.19 | L17: =L16/MONTH(E6) -> 521833.12 | M17: =(K17-L17)/L17 -> 0.20092836 | O17: =O16/1 -> 644636.49 | P17: =P16/1 -> 483942.81 | Q17: =Q16/1 -> 586857.15 | R17: =R16/1 -> 494401 | S17: =S16/1 -> 563988.36 | T17: =T16/1 -> 531323.95 | U17: =U16/1 -> 767245.55 | V17: =V16/1 -> 690800.38 | ... Z17: =Z16/1 -> 575262.78 | AA17: =SUM(O17:Z17) -> 6937772.6 | AB17: =SUM(O17:Q17) -> 1715436.4 | AC17: =SUM(R17:T17) -> 1589713.3 | AD17: =SUM(U17:W17) -> 1982141.9 | AE17: =SUM(X17:Z17) -> 1650481 | AF17: =SUM(AB17:AE17) -> 6937772.7 | AH17: =AH16/1 -> 682120.09 | AI17: =AI16/1 -> 513180.3 | AJ17: =AJ16/1 -> 504315 | AK17: =AK16/1 -> 458222.32 | AL17: =AL16/1 -> 513257.28 | AM17: =AM16/1 -> 459903.73 | AN17: =AN16/1 -> 472504.77 | AO17: =AO16/1 -> 786386.7 | ... AS17: =AS16/1 -> 1638506.3 | AT17: =SUM(AH17:AS17) -> 7501944.3 | AU17: =SUM(AH17:AJ17) -> 1699615.4 | AV17: =SUM(AK17:AM17) -> 1431383.3 | AW17: =SUM(AN17:AP17) -> 1758521.9 | AX17: =SUM(AQ17:AS17) -> 2612423.7 | AY17: =SUM(AU17:AX17) -> 7501944.3 | BA17: =BA16/1 -> 704693.07 | BB17: =BB16/1 -> 642668.4 | BC17: =BC16/1 -> 665188.67 | BD17: =BD16/1 -> 572560.52 | BE17: =BE16/1 -> 587539.72 | BF17: =BF16/1 -> 587454.79 | BG17: =BG16/1 -> 0 | BH17: =BH16/1 -> 0 | ... BL17: =BL16/1 -> 0 | BM17: =SUM(BA17:BL17) -> 3760105.2 | BN17: =SUM(BA17:BC17) -> 2012550.1 | BO17: =SUM(BD17:BF17) -> 1747555 | BP17: =SUM(BG17:BI17) -> 0 | BQ17: =SUM(BJ17:BL17) -> 0 | BR17: =SUM(BN17:BQ17) -> 3760105.2
C19: FOOD REVENUE & COST
C20: FOOD REVENUE * | E20: =E39+E41+E43+E47 -> 47107.01 | F20: =F39+F41+F43+F47 -> 12236.47 | G20: =(E20-F20)/F20 -> 2.8497222 | H20: =H39+H41+H43+H47 -> 125044.17 | I20: =I39+I41+I43+I47 -> 49885.46 | J20: =(H20-I20)/I20 -> 1.5066256 | K20: =K39+K41+K43+K47 -> 361852.24 | L20: =SUM(AH20:AM20) -> 245457.27 | M20: =(K20-L20)/L20 -> 0.47419647 | O20: =O39+O41+O43+O47 -> 25359.38 | P20: =P39+P41+P43+P47 -> 28424.25 | Q20: =Q39+Q41+Q43+Q47 -> 97945.96 | R20: =R39+R41+R43+R47 -> 70797.07 | S20: =S39+S41+S43+S47 -> 33305.83 | T20: =T39+T41+T43+T47 -> 29357.49 | U20: =U39+U41+U43+U47 -> 36166 | V20: =V39+V41+V43+V47 -> 33224.16 | ... Z20: =Z39+Z41+Z43+Z47 -> 19440.23 | AA20: =SUM(O20:Z20) -> 421190.4 | AB20: =SUM(O20:Q20) -> 151729.59 | AC20: =SUM(R20:T20) -> 133460.39 | AD20: =SUM(U20:W20) -> 89795.43 | AE20: =SUM(X20:Z20) -> 46204.99 | AF20: =SUM(AB20:AE20) -> 421190.4 | AH20: =AH39+AH41+AH43+AH47 -> 11237.62 | AI20: =AI39+AI41+AI43+AI47 -> 11051.17 | AJ20: =AJ39+AJ41+AJ43+AJ47 -> 173283.02 | AK20: =AK39+AK41+AK43+AK47 -> 22433.86 | AL20: =AL39+AL41+AL43+AL47 -> 15215.13 | AM20: =AM39+AM41+AM43+AM47 -> 12236.47 | AN20: =AN39+AN41+AN43+AN47 -> 13176.76 | AO20: =AO39+AO41+AO43+AO47 -> 12812.24 | ... AS20: =AS39+AS41+AS43+AS47 -> 15761.74 | AT20: =SUM(AH20:AS20) -> 322508.96 | AU20: =SUM(AH20:AJ20) -> 195571.81 | AV20: =SUM(AK20:AM20) -> 49885.46 | AW20: =SUM(AN20:AP20) -> 38989.86 | AX20: =SUM(AQ20:AS20) -> 38061.83 | AY20: =SUM(AU20:AX20) -> 322508.96 | BA20: =BA39+BA41+BA43+BA47 -> 42929.69 | BB20: =BB39+BB41+BB43+BB47 -> 48662.33 | BC20: =BC39+BC41+BC43+BC47 -> 145216.05 | BD20: =BD39+BD41+BD43+BD47 -> 45729.39 | BE20: =BE39+BE41+BE43+BE47 -> 32207.77 | BF20: =BF39+BF41+BF43+BF47 -> 47107.01 | BG20: =BG39+BG41+BG43+BG47 -> 0 | BH20: =BH39+BH41+BH43+BH47 -> 0 | ... BL20: =BL39+BL41+BL43+BL47 -> 0 | BM20: =SUM(BA20:BL20) -> 361852.24 | BN20: =SUM(BA20:BC20) -> 236808.07 | BO20: =SUM(BD20:BF20) -> 125044.17 | BP20: =SUM(BG20:BI20) -> 0 | BQ20: =SUM(BJ20:BL20) -> 0 | BR20: =SUM(BN20:BQ20) -> 361852.24
C21: FOOD COST ** | E21: =E83+E88+E89+E90+E91+E84 -> 28254.21 | F21: =F83+F88+F89+F90+F91+F84 -> 26128.44 | G21: =(E21-F21)/F21 -> 0.081358474 | H21: =H83+H88+H89+H90+H91+H84 -> 84029.9 | I21: =I83+I88+I89+I90+I91+I84 -> 109850.48 | J21: =(H21-I21)/I21 -> -0.23505205 | K21: =K83+K88+K89+K90+K91+K84 -> 221771.06 | L21: =SUM(AH21:AM21) -> 279534.67 | M21: =(K21-L21)/L21 -> -0.20664202 | O21: =O83+O88+O89+O90+O91+O84 -> 42651.26 | P21: =P83+P88+P89+P90+P91+P84 -> 46548.98 | Q21: =Q83+Q88+Q89+Q90+Q91+Q84 -> 80476.09 | R21: =R83+R88+R89+R90+R91+R84 -> 53120.16 | S21: =S83+S88+S89+S90+S91+S84 -> 53325.88 | T21: =T83+T88+T89+T90+T91+T84 -> 36857.89 | U21: =U83+U88+U89+U90+U91+U84 -> 36605.5 | V21: =V83+V88+V89+V90+V91+V84 -> 50435.96 | ... Z21: =Z83+Z88+Z89+Z90+Z91+Z84 -> 37793.32 | AA21: =SUM(O21:Z21) -> 572962.43 | AB21: =SUM(O21:Q21) -> 169676.33 | AC21: =SUM(R21:T21) -> 143303.93 | AD21: =SUM(U21:W21) -> 124790.29 | AE21: =SUM(X21:Z21) -> 135191.88 | AF21: =SUM(AB21:AE21) -> 572962.43 | AH21: =AH83+AH88+AH89+AH90+AH91+AH84 -> 52439.34 | AI21: =AI83+AI88+AI89+AI90+AI91+AI84 -> 32245.88 | AJ21: =AJ83+AJ88+AJ89+AJ90+AJ91+AJ84 -> 84998.97 | AK21: =AK83+AK88+AK89+AK90+AK91+AK84 -> 32431.83 | AL21: =AL83+AL88+AL89+AL90+AL91+AL84 -> 51290.21 | AM21: =AM83+AM88+AM89+AM90+AM91+AM84 -> 26128.44 | AN21: =AN83+AN88+AN89+AN90+AN91+AN84 -> 32072.54 | AO21: =AO83+AO88+AO89+AO90+AO91+AO84 -> 33955.25 | ... AS21: =AS83+AS88+AS89+AS90+AS91+AS84 -> 44903.05 | AT21: =SUM(AH21:AS21) -> 499535.26 | AU21: =SUM(AH21:AJ21) -> 169684.19 | AV21: =SUM(AK21:AM21) -> 109850.48 | AW21: =SUM(AN21:AP21) -> 107824.96 | AX21: =SUM(AQ21:AS21) -> 112175.63 | AY21: =SUM(AU21:AX21) -> 499535.26 | BA21: =BA83+BA88+BA89+BA90+BA91+BA84 -> 36014.3 | BB21: =BB83+BB88+BB89+BB90+BB91+BB84 -> 50142.15 | BC21: =BC83+BC88+BC89+BC90+BC91+BC84 -> 51584.71 | BD21: =BD83+BD88+BD89+BD90+BD91+BD84 -> 32936.58 | BE21: =BE83+BE88+BE89+BE90+BE91+BE84 -> 22839.11 | BF21: =BF83+BF88+BF89+BF90+BF91+BF84 -> 28254.21 | BG21: =BG83+BG88+BG89+BG90+BG91+BG84 -> 0 | BH21: =BH83+BH88+BH89+BH90+BH91+BH84 -> 0 | ... BL21: =BL83+BL88+BL89+BL90+BL91+BL84 -> 0 | BM21: =SUM(BA21:BL21) -> 221771.06 | BN21: =SUM(BA21:BC21) -> 137741.16 | BO21: =SUM(BD21:BF21) -> 84029.9 | BP21: =SUM(BG21:BI21) -> 0 | BQ21: =SUM(BJ21:BL21) -> 0 | BR21: =SUM(BN21:BQ21) -> 221771.06
C22: DIFFERENCE | E22: =E20-E21 -> 18852.8 | F22: =F20-F21 -> -13891.97 | G22: =(E22-F22)/F22 -> -2.3571005 | H22: =H20-H21 -> 41014.27 | I22: =I20-I21 -> -59965.02 | J22: =(H22-I22)/I22 -> -1.6839699 | K22: =K20-K21 -> 140081.18 | L22: =L20-L21 -> -34077.4 | M22: =(K22-L22)/L22 -> -5.1106769 | O22: =O20-O21 -> -17291.88 | P22: =P20-P21 -> -18124.73 | Q22: =Q20-Q21 -> 17469.87 | R22: =R20-R21 -> 17676.91 | S22: =S20-S21 -> -20020.05 | T22: =T20-T21 -> -7500.4 | U22: =U20-U21 -> -439.5 | V22: =V20-V21 -> -17211.8 | ... Z22: =Z20-Z21 -> -18353.09 | AA22: =SUM(O22:Z22) -> -151772.03 | AB22: =SUM(O22:Q22) -> -17946.74 | AC22: =SUM(R22:T22) -> -9843.54 | AD22: =SUM(U22:W22) -> -34994.86 | AE22: =SUM(X22:Z22) -> -88986.89 | AF22: =SUM(AB22:AE22) -> -151772.03 | AH22: =AH20-AH21 -> -41201.72 | AI22: =AI20-AI21 -> -21194.71 | AJ22: =AJ20-AJ21 -> 88284.05 | AK22: =AK20-AK21 -> -9997.97 | AL22: =AL20-AL21 -> -36075.08 | AM22: =AM20-AM21 -> -13891.97 | AN22: =AN20-AN21 -> -18895.78 | AO22: =AO20-AO21 -> -21143.01 | ... AS22: =AS20-AS21 -> -29141.31 | AT22: =SUM(AH22:AS22) -> -177026.3 | AU22: =SUM(AH22:AJ22) -> 25887.62 | AV22: =SUM(AK22:AM22) -> -59965.02 | AW22: =SUM(AN22:AP22) -> -68835.1 | AX22: =SUM(AQ22:AS22) -> -74113.8 | AY22: =SUM(AU22:AX22) -> -177026.3 | BA22: =BA20-BA21 -> 6915.39 | BB22: =BB20-BB21 -> -1479.82 | BC22: =BC20-BC21 -> 93631.34 | BD22: =BD20-BD21 -> 12792.81 | BE22: =BE20-BE21 -> 9368.66 | BF22: =BF20-BF21 -> 18852.8 | BG22: =BG20-BG21 -> 0 | BH22: =BH20-BH21 -> 0 | ... BL22: =BL20-BL21 -> 0 | BM22: =SUM(BA22:BL22) -> 140081.18 | BN22: =SUM(BA22:BC22) -> 99066.91 | BO22: =SUM(BD22:BF22) -> 41014.27 | BP22: =SUM(BG22:BI22) -> 0 | BQ22: =SUM(BJ22:BL22) -> 0 | BR22: =SUM(BN22:BQ22) -> 140081.18
C25: REVENUE | AB25: =SUM(O25:Q25) -> 0 | AC25: =SUM(R25:T25) -> 0 | AD25: =SUM(U25:W25) -> 0 | AE25: =SUM(X25:Z25) -> 0 | AU25: =SUM(AH25:AJ25) -> 0 | AV25: =SUM(AK25:AM25) -> 0 | AW25: =SUM(AN25:AP25) -> 0 | AX25: =SUM(AQ25:AS25) -> 0 | BN25: =SUM(BA25:BC25) -> 0 | BO25: =SUM(BD25:BF25) -> 0 | BP25: =SUM(BG25:BI25) -> 0 | BQ25: =SUM(BJ25:BL25) -> 0
AB26: =SUM(O26:Q26) -> 0 | AC26: =SUM(R26:T26) -> 0 | AD26: =SUM(U26:W26) -> 0 | AE26: =SUM(X26:Z26) -> 0 | AU26: =SUM(AH26:AJ26) -> 0 | AV26: =SUM(AK26:AM26) -> 0 | AW26: =SUM(AN26:AP26) -> 0 | AX26: =SUM(AQ26:AS26) -> 0 | BN26: =SUM(BA26:BC26) -> 0 | BO26: =SUM(BD26:BF26) -> 0 | BP26: =SUM(BG26:BI26) -> 0 | BQ26: =SUM(BJ26:BL26) -> 0
A27: ROOM | B27: 500-1000 | C27: ROOM | D27: 500-1000 | E27: =SUMIF($BA$6:$BL$6,$E$6,$BA27:$BL27) -> 380114.73 | F27: =SUMIF($AH$6:$AS$6,$F$6,$AH27:$AS27) -> 336619.46 | G27: =(E27-F27)/F27 -> 0.12921199 | H27: =SUMIF($BN$6:$BR$6,$H$6,$BN27:$BR27) -> 1171257.7 | I27: =SUMIF($AU$6:$AY$6,$I$6,$AU27:$AY27) -> 1014736.5 | J27: =(H27-I27)/I27 -> 0.15424812 | K27: =BM27 -> 2322249.5 | L27: =SUM(AH27:AM27) -> 2029522.1 | M27: =(K27-L27)/L27 -> 0.14423464 | O27: =SUMIF('2024 AC'!$B$3:$B$250,"*"&$D27&"*",'2024 AC'!C$3:C$250) -> 215086.38 | P27: =SUMIF('2024 AC'!$B$3:$B$250,"*"&$D27&"*",'2024 AC'!D$3:D$250) -> 330522.99 | Q27: =SUMIF('2024 AC'!$B$3:$B$250,"*"&$D27&"*",'2024 AC'!E$3:E$250) -> 267347.64 | R27: =SUMIF('2024 AC'!$B$3:$B$250,"*"&$D27&"*",'2024 AC'!F$3:F$250) -> 242849.09 | S27: =SUMIF('2024 AC'!$B$3:$B$250,"*"&$D27&"*",'2024 AC'!G$3:G$250) -> 349112.36 | T27: =SUMIF('2024 AC'!$B$3:$B$250,"*"&$D27&"*",'2024 AC'!H$3:H$250) -> 329037.23 | U27: =SUMIF('2024 AC'!$B$3:$B$250,"*"&$D27&"*",'2024 AC'!I$3:I$250) -> 430480.72 | V27: =SUMIF('2024 AC'!$B$3:$B$250,"*"&$D27&"*",'2024 AC'!J$3:J$250) -> 440278.28 | ... Z27: =SUMIF('2024 AC'!$B$3:$B$250,"*"&$D27&"*",'2024 AC'!N$3:N$250) -> 489138.54 | AA27: =SUM(O27:Z27) -> 4210071.2 | AB27: =SUM(O27:Q27) -> 812957.01 | AC27: =SUM(R27:T27) -> 920998.68 | AD27: =SUM(U27:W27) -> 1247848.6 | AE27: =SUM(X27:Z27) -> 1228266.9 | AF27: =SUM(AB27:AE27) -> 4210071.2 | AH27: =SUMIF('2025 AC'!$B$3:$B$250,"*"&$D27&"*",'2025 AC'!C$3:C$250) -> 387262.17 | AI27: =SUMIF('2025 AC'!$B$3:$B$250,"*"&$D27&"*",'2025 AC'!D$3:D$250) -> 370307.95 | AJ27: =SUMIF('2025 AC'!$B$3:$B$250,"*"&$D27&"*",'2025 AC'!E$3:E$250) -> 257215.41 | AK27: =SUMIF('2025 AC'!$B$3:$B$250,"*"&$D27&"*",'2025 AC'!F$3:F$250) -> 325707.83 | AL27: =SUMIF('2025 AC'!$B$3:$B$250,"*"&$D27&"*",'2025 AC'!G$3:G$250) -> 352409.25 | AM27: =SUMIF('2025 AC'!$B$3:$B$250,"*"&$D27&"*",'2025 AC'!H$3:H$250) -> 336619.46 | AN27: =SUMIF('2025 AC'!$B$3:$B$250,"*"&$D27&"*",'2025 AC'!I$3:I$250) -> 329009.54 | AO27: =SUMIF('2025 AC'!$B$3:$B$250,"*"&$D27&"*",'2025 AC'!J$3:J$250) -> 369440.7 | ... AS27: =SUMIF('2025 AC'!$B$3:$B$250,"*"&$D27&"*",'2025 AC'!N$3:N$250) -> 474032.84 | AT27: =SUM(AH27:AS27) -> 4083024 | AU27: =SUM(AH27:AJ27) -> 1014785.5 | AV27: =SUM(AK27:AM27) -> 1014736.5 | AW27: =SUM(AN27:AP27) -> 1051146.6 | AX27: =SUM(AQ27:AS27) -> 1002355.3 | AY27: =SUM(AU27:AX27) -> 4083024 | BA27: =SUMIF('2026 AC'!$B$3:$B$254,"*"&$D27&"*",'2026 AC'!C$3:C$254) -> 435957.26 | BB27: =SUMIF('2026 AC'!$B$3:$B$254,"*"&$D27&"*",'2026 AC'!D$3:D$254) -> 381267.35 | BC27: =SUMIF('2026 AC'!$B$3:$B$254,"*"&$D27&"*",'2026 AC'!E$3:E$254) -> 333767.1 | BD27: =SUMIF('2026 AC'!$B$3:$B$254,"*"&$D27&"*",'2026 AC'!F$3:F$254) -> 384752.75 | BE27: =SUMIF('2026 AC'!$B$3:$B$254,"*"&$D27&"*",'2026 AC'!G$3:G$254) -> 406390.26 | BF27: =SUMIF('2026 AC'!$B$3:$B$254,"*"&$D27&"*",'2026 AC'!H$3:H$254) -> 380114.73 | BG27: =SUMIF('2026 AC'!$B$3:$B$254,"*"&$D27&"*",'2026 AC'!I$3:I$254) -> 0 | BH27: =SUMIF('2026 AC'!$B$3:$B$254,"*"&$D27&"*",'2026 AC'!J$3:J$254) -> 0 | ... BL27: =SUMIF('2026 AC'!$B$3:$B$254,"*"&$D27&"*",'2026 AC'!N$3:N$254) -> 0 | BM27: =SUM(BA27:BL27) -> 2322249.5 | BN27: =SUM(BA27:BC27) -> 1150991.7 | BO27: =SUM(BD27:BF27) -> 1171257.7 | BP27: =SUM(BG27:BI27) -> 0 | BQ27: =SUM(BJ27:BL27) -> 0 | BR27: =SUM(BN27:BQ27) -> 2322249.5
A28: ROOM CHARGE (SC) | B28: 500-1001 | C28: ROOM CHARGE (SC) | D28: 500-1001 | E28: =SUMIF($BA$6:$BL$6,$E$6,$BA28:$BL28) -> 45375.88 | F28: =SUMIF($AH$6:$AS$6,$F$6,$AH28:$AS28) -> 56019.32 | G28: =(E28-F28)/F28 -> -0.18999588 | H28: =SUMIF($BN$6:$BR$6,$H$6,$BN28:$BR28) -> 150171.45 | I28: =SUMIF($AU$6:$AY$6,$I$6,$AU28:$AY28) -> 152422.71 | J28: =(H28-I28)/I28 -> -0.014769846 | K28: =BM28 -> 311649.44 | L28: =SUM(AH28:AM28) -> 274680.82 | M28: =(K28-L28)/L28 -> 0.13458756 | O28: =SUMIF('2024 AC'!$B$3:$B$250,"*"&$D28&"*",'2024 AC'!C$3:C$250) -> 91824.64 | P28: =SUMIF('2024 AC'!$B$3:$B$250,"*"&$D28&"*",'2024 AC'!D$3:D$250) -> 117113.12 | Q28: =SUMIF('2024 AC'!$B$3:$B$250,"*"&$D28&"*",'2024 AC'!E$3:E$250) -> 39065.6 | R28: =SUMIF('2024 AC'!$B$3:$B$250,"*"&$D28&"*",'2024 AC'!F$3:F$250) -> 49011.14 | S28: =SUMIF('2024 AC'!$B$3:$B$250,"*"&$D28&"*",'2024 AC'!G$3:G$250) -> 56140.47 | T28: =SUMIF('2024 AC'!$B$3:$B$250,"*"&$D28&"*",'2024 AC'!H$3:H$250) -> 53387.22 | U28: =SUMIF('2024 AC'!$B$3:$B$250,"*"&$D28&"*",'2024 AC'!I$3:I$250) -> 99876.81 | V28: =SUMIF('2024 AC'!$B$3:$B$250,"*"&$D28&"*",'2024 AC'!J$3:J$250) -> 94461.36 | ... Z28: =SUMIF('2024 AC'!$B$3:$B$250,"*"&$D28&"*",'2024 AC'!N$3:N$250) -> 41620.43 | AA28: =SUM(O28:Z28) -> 841352.73 | AB28: =SUM(O28:Q28) -> 248003.36 | AC28: =SUM(R28:T28) -> 158538.83 | AD28: =SUM(U28:W28) -> 249172.88 | AE28: =SUM(X28:Z28) -> 185637.66 | AF28: =SUM(AB28:AE28) -> 841352.73 | AH28: =SUMIF('2025 AC'!$B$3:$B$250,"*"&$D28&"*",'2025 AC'!C$3:C$250) -> 36556.07 | AI28: =SUMIF('2025 AC'!$B$3:$B$250,"*"&$D28&"*",'2025 AC'!D$3:D$250) -> 37009.27 | AJ28: =SUMIF('2025 AC'!$B$3:$B$250,"*"&$D28&"*",'2025 AC'!E$3:E$250) -> 48692.77 | AK28: =SUMIF('2025 AC'!$B$3:$B$250,"*"&$D28&"*",'2025 AC'!F$3:F$250) -> 52694.7 | AL28: =SUMIF('2025 AC'!$B$3:$B$250,"*"&$D28&"*",'2025 AC'!G$3:G$250) -> 43708.69 | AM28: =SUMIF('2025 AC'!$B$3:$B$250,"*"&$D28&"*",'2025 AC'!H$3:H$250) -> 56019.32 | AN28: =SUMIF('2025 AC'!$B$3:$B$250,"*"&$D28&"*",'2025 AC'!I$3:I$250) -> 55221.53 | AO28: =SUMIF('2025 AC'!$B$3:$B$250,"*"&$D28&"*",'2025 AC'!J$3:J$250) -> 42610.84 | ... AS28: =SUMIF('2025 AC'!$B$3:$B$250,"*"&$D28&"*",'2025 AC'!N$3:N$250) -> 48222.76 | AT28: =SUM(AH28:AS28) -> 533790.77 | AU28: =SUM(AH28:AJ28) -> 122258.11 | AV28: =SUM(AK28:AM28) -> 152422.71 | AW28: =SUM(AN28:AP28) -> 141207.78 | AX28: =SUM(AQ28:AS28) -> 117902.17 | AY28: =SUM(AU28:AX28) -> 533790.77 | BA28: =SUMIF('2026 AC'!$B$3:$B$254,"*"&$D28&"*",'2026 AC'!C$3:C$254) -> 72341.52 | BB28: =SUMIF('2026 AC'!$B$3:$B$254,"*"&$D28&"*",'2026 AC'!D$3:D$254) -> 41920.27 | BC28: =SUMIF('2026 AC'!$B$3:$B$254,"*"&$D28&"*",'2026 AC'!E$3:E$254) -> 47216.2 | BD28: =SUMIF('2026 AC'!$B$3:$B$254,"*"&$D28&"*",'2026 AC'!F$3:F$254) -> 64930.4 | BE28: =SUMIF('2026 AC'!$B$3:$B$254,"*"&$D28&"*",'2026 AC'!G$3:G$254) -> 39865.17 | BF28: =SUMIF('2026 AC'!$B$3:$B$254,"*"&$D28&"*",'2026 AC'!H$3:H$254) -> 45375.88 | BG28: =SUMIF('2026 AC'!$B$3:$B$254,"*"&$D28&"*",'2026 AC'!I$3:I$254) -> 0 | BH28: =SUMIF('2026 AC'!$B$3:$B$254,"*"&$D28&"*",'2026 AC'!J$3:J$254) -> 0 | ... BL28: =SUMIF('2026 AC'!$B$3:$B$254,"*"&$D28&"*",'2026 AC'!N$3:N$254) -> 0 | BM28: =SUM(BA28:BL28) -> 311649.44 | BN28: =SUM(BA28:BC28) -> 161477.99 | BO28: =SUM(BD28:BF28) -> 150171.45 | BP28: =SUM(BG28:BI28) -> 0 | BQ28: =SUM(BJ28:BL28) -> 0 | BR28: =SUM(BN28:BQ28) -> 311649.44
A29: ROOM CHARGE (NSC) | B29: 500-1002 | C29: ROOM CHARGE (NSC) | D29: 500-1002 | E29: =SUMIF($BA$6:$BL$6,$E$6,$BA29:$BL29) -> 322233.15 | F29: =SUMIF($AH$6:$AS$6,$F$6,$AH29:$AS29) -> 266352.18 | G29: =(E29-F29)/F29 -> 0.20980106 | H29: =SUMIF($BN$6:$BR$6,$H$6,$BN29:$BR29) -> 983161.94 | I29: =SUMIF($AU$6:$AY$6,$I$6,$AU29:$AY29) -> 817509.1 | J29: =(H29-I29)/I29 -> 0.20263119 | K29: =BM29 -> 1935434.1 | L29: =SUM(AH29:AM29) -> 1682793.8 | M29: =(K29-L29)/L29 -> 0.15013149 | O29: =SUMIF('2024 AC'!$B$3:$B$250,"*"&$D29&"*",'2024 AC'!C$3:C$250) -> 106475.37 | P29: =SUMIF('2024 AC'!$B$3:$B$250,"*"&$D29&"*",'2024 AC'!D$3:D$250) -> 192677.42 | Q29: =SUMIF('2024 AC'!$B$3:$B$250,"*"&$D29&"*",'2024 AC'!E$3:E$250) -> 220731.87 | R29: =SUMIF('2024 AC'!$B$3:$B$250,"*"&$D29&"*",'2024 AC'!F$3:F$250) -> 183013.56 | S29: =SUMIF('2024 AC'!$B$3:$B$250,"*"&$D29&"*",'2024 AC'!G$3:G$250) -> 274407.21 | T29: =SUMIF('2024 AC'!$B$3:$B$250,"*"&$D29&"*",'2024 AC'!H$3:H$250) -> 261685.1 | U29: =SUMIF('2024 AC'!$B$3:$B$250,"*"&$D29&"*",'2024 AC'!I$3:I$250) -> 314220.34 | V29: =SUMIF('2024 AC'!$B$3:$B$250,"*"&$D29&"*",'2024 AC'!J$3:J$250) -> 319850.06 | ... Z29: =SUMIF('2024 AC'!$B$3:$B$250,"*"&$D29&"*",'2024 AC'!N$3:N$250) -> 436035.88 | AA29: =SUM(O29:Z29) -> 3177192.8 | AB29: =SUM(O29:Q29) -> 519884.66 | AC29: =SUM(R29:T29) -> 719105.87 | AD29: =SUM(U29:W29) -> 943687.18 | AE29: =SUM(X29:Z29) -> 994515.1 | AF29: =SUM(AB29:AE29) -> 3177192.8 | AH29: =SUMIF('2025 AC'!$B$3:$B$250,"*"&$D29&"*",'2025 AC'!C$3:C$250) -> 339450.8 | AI29: =SUMIF('2025 AC'!$B$3:$B$250,"*"&$D29&"*",'2025 AC'!D$3:D$250) -> 324160.5 | AJ29: =SUMIF('2025 AC'!$B$3:$B$250,"*"&$D29&"*",'2025 AC'!E$3:E$250) -> 201673.37 | AK29: =SUMIF('2025 AC'!$B$3:$B$250,"*"&$D29&"*",'2025 AC'!F$3:F$250) -> 260267.53 | AL29: =SUMIF('2025 AC'!$B$3:$B$250,"*"&$D29&"*",'2025 AC'!G$3:G$250) -> 290889.39 | AM29: =SUMIF('2025 AC'!$B$3:$B$250,"*"&$D29&"*",'2025 AC'!H$3:H$250) -> 266352.18 | AN29: =SUMIF('2025 AC'!$B$3:$B$250,"*"&$D29&"*",'2025 AC'!I$3:I$250) -> 257531.7 | AO29: =SUMIF('2025 AC'!$B$3:$B$250,"*"&$D29&"*",'2025 AC'!J$3:J$250) -> 310536.86 | ... AS29: =SUMIF('2025 AC'!$B$3:$B$250,"*"&$D29&"*",'2025 AC'!N$3:N$250) -> 412604.83 | AT29: =SUM(AH29:AS29) -> 3384841.7 | AU29: =SUM(AH29:AJ29) -> 865284.67 | AV29: =SUM(AK29:AM29) -> 817509.1 | AW29: =SUM(AN29:AP29) -> 858168.51 | AX29: =SUM(AQ29:AS29) -> 843879.4 | AY29: =SUM(AU29:AX29) -> 3384841.7 | BA29: =SUMIF('2026 AC'!$B$3:$B$254,"*"&$D29&"*",'2026 AC'!C$3:C$254) -> 348894.12 | BB29: =SUMIF('2026 AC'!$B$3:$B$254,"*"&$D29&"*",'2026 AC'!D$3:D$254) -> 328793.52 | BC29: =SUMIF('2026 AC'!$B$3:$B$254,"*"&$D29&"*",'2026 AC'!E$3:E$254) -> 274584.53 | BD29: =SUMIF('2026 AC'!$B$3:$B$254,"*"&$D29&"*",'2026 AC'!F$3:F$254) -> 303828.01 | BE29: =SUMIF('2026 AC'!$B$3:$B$254,"*"&$D29&"*",'2026 AC'!G$3:G$254) -> 357100.78 | BF29: =SUMIF('2026 AC'!$B$3:$B$254,"*"&$D29&"*",'2026 AC'!H$3:H$254) -> 322233.15 | BG29: =SUMIF('2026 AC'!$B$3:$B$254,"*"&$D29&"*",'2026 AC'!I$3:I$254) -> 0 | BH29: =SUMIF('2026 AC'!$B$3:$B$254,"*"&$D29&"*",'2026 AC'!J$3:J$254) -> 0 | ... BL29: =SUMIF('2026 AC'!$B$3:$B$254,"*"&$D29&"*",'2026 AC'!N$3:N$254) -> 0 | BM29: =SUM(BA29:BL29) -> 1935434.1 | BN29: =SUM(BA29:BC29) -> 952272.17 | BO29: =SUM(BD29:BF29) -> 983161.94 | BP29: =SUM(BG29:BI29) -> 0 | BQ29: =SUM(BJ29:BL29) -> 0 | BR29: =SUM(BN29:BQ29) -> 1935434.1
A30: ROOM CHARGE - EXTENDED USE | B30: 500-1003 | C30: ROOM CHARGE - EXTRA CHARGES | D30: 500-1003 | E30: =SUMIF($BA$6:$BL$6,$E$6,$BA30:$BL30) -> 1881.4 | F30: =SUMIF($AH$6:$AS$6,$F$6,$AH30:$AS30) -> 0 | G30: =IFERROR((E30-F30)/F30,1) -> 1 | H30: =SUMIF($BN$6:$BR$6,$H$6,$BN30:$BR30) -> 5050.98 | I30: =SUMIF($AU$6:$AY$6,$I$6,$AU30:$AY30) -> 0 | J30: =IFERROR((H30-I30)/I30,1) -> 1 | K30: =BM30 -> 11106.24 | L30: =SUM(AH30:AM30) -> 0 | M30: =IFERROR((K30-L30)/L30,1) -> 1 | O30: =SUMIF('2024 AC'!$B$3:$B$250,"*"&$D30&"*",'2024 AC'!C$3:C$250) -> 0 | P30: =SUMIF('2024 AC'!$B$3:$B$250,"*"&$D30&"*",'2024 AC'!D$3:D$250) -> 0 | Q30: =SUMIF('2024 AC'!$B$3:$B$250,"*"&$D30&"*",'2024 AC'!E$3:E$250) -> 0 | R30: =SUMIF('2024 AC'!$B$3:$B$250,"*"&$D30&"*",'2024 AC'!F$3:F$250) -> 0 | S30: =SUMIF('2024 AC'!$B$3:$B$250,"*"&$D30&"*",'2024 AC'!G$3:G$250) -> 0 | T30: =SUMIF('2024 AC'!$B$3:$B$250,"*"&$D30&"*",'2024 AC'!H$3:H$250) -> 0 | U30: =SUMIF('2024 AC'!$B$3:$B$250,"*"&$D30&"*",'2024 AC'!I$3:I$250) -> 0 | V30: =SUMIF('2024 AC'!$B$3:$B$250,"*"&$D30&"*",'2024 AC'!J$3:J$250) -> 0 | ... Z30: =SUMIF('2024 AC'!$B$3:$B$250,"*"&$D30&"*",'2024 AC'!N$3:N$250) -> 0 | AA30: =SUM(O30:Z30) -> 0 | AB30: =SUM(O30:Q30) -> 0 | AC30: =SUM(R30:T30) -> 0 | AD30: =SUM(U30:W30) -> 0 | AE30: =SUM(X30:Z30) -> 0 | AF30: =SUM(AB30:AE30) -> 0 | AH30: =SUMIF('2025 AC'!$B$3:$B$250,"*"&$D30&"*",'2025 AC'!C$3:C$250) -> 0 | AI30: =SUMIF('2025 AC'!$B$3:$B$250,"*"&$D30&"*",'2025 AC'!D$3:D$250) -> 0 | AJ30: =SUMIF('2025 AC'!$B$3:$B$250,"*"&$D30&"*",'2025 AC'!E$3:E$250) -> 0 | AK30: =SUMIF('2025 AC'!$B$3:$B$250,"*"&$D30&"*",'2025 AC'!F$3:F$250) -> 0 | AL30: =SUMIF('2025 AC'!$B$3:$B$250,"*"&$D30&"*",'2025 AC'!G$3:G$250) -> 0 | AM30: =SUMIF('2025 AC'!$B$3:$B$250,"*"&$D30&"*",'2025 AC'!H$3:H$250) -> 0 | AN30: =SUMIF('2025 AC'!$B$3:$B$250,"*"&$D30&"*",'2025 AC'!I$3:I$250) -> 779.67 | AO30: =SUMIF('2025 AC'!$B$3:$B$250,"*"&$D30&"*",'2025 AC'!J$3:J$250) -> 1432.22 | ... AS30: =SUMIF('2025 AC'!$B$3:$B$250,"*"&$D30&"*",'2025 AC'!N$3:N$250) -> 1258.54 | AT30: =SUM(AH30:AS30) -> 5919.64 | AU30: =SUM(AH30:AJ30) -> 0 | AV30: =SUM(AK30:AM30) -> 0 | AW30: =SUM(AN30:AP30) -> 3211.92 | AX30: =SUM(AQ30:AS30) -> 2707.72 | AY30: =SUM(AU30:AX30) -> 5919.64 | BA30: =SUMIF('2026 AC'!$B$3:$B$254,"*"&$D30&"*",'2026 AC'!C$3:C$254) -> 2122.9 | BB30: =SUMIF('2026 AC'!$B$3:$B$254,"*"&$D30&"*",'2026 AC'!D$3:D$254) -> 1652.62 | BC30: =SUMIF('2026 AC'!$B$3:$B$254,"*"&$D30&"*",'2026 AC'!E$3:E$254) -> 2279.74 | BD30: =SUMIF('2026 AC'!$B$3:$B$254,"*"&$D30&"*",'2026 AC'!F$3:F$254) -> 1355.96 | BE30: =SUMIF('2026 AC'!$B$3:$B$254,"*"&$D30&"*",'2026 AC'!G$3:G$254) -> 1813.62 | BF30: =SUMIF('2026 AC'!$B$3:$B$254,"*"&$D30&"*",'2026 AC'!H$3:H$254) -> 1881.4 | BG30: =SUMIF('2026 AC'!$B$3:$B$254,"*"&$D30&"*",'2026 AC'!I$3:I$254) -> 0 | BH30: =SUMIF('2026 AC'!$B$3:$B$254,"*"&$D30&"*",'2026 AC'!J$3:J$254) -> 0 | ... BL30: =SUMIF('2026 AC'!$B$3:$B$254,"*"&$D30&"*",'2026 AC'!N$3:N$254) -> 0 | BM30: =SUM(BA30:BL30) -> 11106.24 | BN30: =SUM(BA30:BC30) -> 6055.26 | BO30: =SUM(BD30:BF30) -> 5050.98 | BP30: =SUM(BG30:BI30) -> 0 | BQ30: =SUM(BJ30:BL30) -> 0 | BR30: =SUM(BN30:BQ30) -> 11106.24
A31: GUEST SERVICES - LAUNDRY | B31: 500-1004 | C31: GUEST SERVICES - LAUNDRY | D31: 500-1004 | E31: =SUMIF($BA$6:$BL$6,$E$6,$BA31:$BL31) -> 123.01 | F31: =SUMIF($AH$6:$AS$6,$F$6,$AH31:$AS31) -> 0 | G31: =IFERROR((E31-F31)/F31,0) -> 0 | H31: =SUMIF($BN$6:$BR$6,$H$6,$BN31:$BR31) -> 326.82 | I31: =SUMIF($AU$6:$AY$6,$I$6,$AU31:$AY31) -> 108.57 | J31: =IFERROR((H31-I31)/I31,0) -> 2.0102238 | K31: =BM31 -> 813.81 | L31: =SUM(AH31:AM31) -> 108.57 | M31: =IFERROR((K31-L31)/L31,0) -> 6.495717 | O31: =SUMIF('2024 AC'!$B$3:$B$250,"*"&$D31&"*",'2024 AC'!C$3:C$250) -> 0 | P31: =SUMIF('2024 AC'!$B$3:$B$250,"*"&$D31&"*",'2024 AC'!D$3:D$250) -> 0 | Q31: =SUMIF('2024 AC'!$B$3:$B$250,"*"&$D31&"*",'2024 AC'!E$3:E$250) -> 0 | R31: =SUMIF('2024 AC'!$B$3:$B$250,"*"&$D31&"*",'2024 AC'!F$3:F$250) -> 0 | S31: =SUMIF('2024 AC'!$B$3:$B$250,"*"&$D31&"*",'2024 AC'!G$3:G$250) -> 0 | T31: =SUMIF('2024 AC'!$B$3:$B$250,"*"&$D31&"*",'2024 AC'!H$3:H$250) -> 0 | U31: =SUMIF('2024 AC'!$B$3:$B$250,"*"&$D31&"*",'2024 AC'!I$3:I$250) -> 0 | V31: =SUMIF('2024 AC'!$B$3:$B$250,"*"&$D31&"*",'2024 AC'!J$3:J$250) -> 0 | ... Z31: =SUMIF('2024 AC'!$B$3:$B$250,"*"&$D31&"*",'2024 AC'!N$3:N$250) -> 739.75 | AA31: =SUM(O31:Z31) -> 787.25 | AB31: =SUM(O31:Q31) -> 0 | AC31: =SUM(R31:T31) -> 0 | AD31: =SUM(U31:W31) -> 0 | AE31: =SUM(X31:Z31) -> 787.25 | AF31: =SUM(AB31:AE31) -> 787.25 | AH31: =SUMIF('2025 AC'!$B$3:$B$250,"*"&$D31&"*",'2025 AC'!C$3:C$250) -> 0 | AI31: =SUMIF('2025 AC'!$B$3:$B$250,"*"&$D31&"*",'2025 AC'!D$3:D$250) -> 0 | AJ31: =SUMIF('2025 AC'!$B$3:$B$250,"*"&$D31&"*",'2025 AC'!E$3:E$250) -> 0 | AK31: =SUMIF('2025 AC'!$B$3:$B$250,"*"&$D31&"*",'2025 AC'!F$3:F$250) -> 72.04 | AL31: =SUMIF('2025 AC'!$B$3:$B$250,"*"&$D31&"*",'2025 AC'!G$3:G$250) -> 36.53 | AM31: =SUMIF('2025 AC'!$B$3:$B$250,"*"&$D31&"*",'2025 AC'!H$3:H$250) -> 0 | AN31: =SUMIF('2025 AC'!$B$3:$B$250,"*"&$D31&"*",'2025 AC'!I$3:I$250) -> 0 | AO31: =SUMIF('2025 AC'!$B$3:$B$250,"*"&$D31&"*",'2025 AC'!J$3:J$250) -> 142.08 | ... AS31: =SUMIF('2025 AC'!$B$3:$B$250,"*"&$D31&"*",'2025 AC'!N$3:N$250) -> 0 | AT31: =SUM(AH31:AS31) -> 421.67 | AU31: =SUM(AH31:AJ31) -> 0 | AV31: =SUM(AK31:AM31) -> 108.57 | AW31: =SUM(AN31:AP31) -> 266.57 | AX31: =SUM(AQ31:AS31) -> 46.53 | AY31: =SUM(AU31:AX31) -> 421.67 | BA31: =SUMIF('2026 AC'!$B$3:$B$254,"*"&$D31&"*",'2026 AC'!C$3:C$254) -> 308.01 | BB31: =SUMIF('2026 AC'!$B$3:$B$254,"*"&$D31&"*",'2026 AC'!D$3:D$254) -> 178.98 | BC31: =SUMIF('2026 AC'!$B$3:$B$254,"*"&$D31&"*",'2026 AC'!E$3:E$254) -> 0 | BD31: =SUMIF('2026 AC'!$B$3:$B$254,"*"&$D31&"*",'2026 AC'!F$3:F$254) -> 56.82 | BE31: =SUMIF('2026 AC'!$B$3:$B$254,"*"&$D31&"*",'2026 AC'!G$3:G$254) -> 146.99 | BF31: =SUMIF('2026 AC'!$B$3:$B$254,"*"&$D31&"*",'2026 AC'!H$3:H$254) -> 123.01 | BG31: =SUMIF('2026 AC'!$B$3:$B$254,"*"&$D31&"*",'2026 AC'!I$3:I$254) -> 0 | BH31: =SUMIF('2026 AC'!$B$3:$B$254,"*"&$D31&"*",'2026 AC'!J$3:J$254) -> 0 | ... BL31: =SUMIF('2026 AC'!$B$3:$B$254,"*"&$D31&"*",'2026 AC'!N$3:N$254) -> 0 | BM31: =SUM(BA31:BL31) -> 813.81 | BN31: =SUM(BA31:BC31) -> 486.99 | BO31: =SUM(BD31:BF31) -> 326.82 | BP31: =SUM(BG31:BI31) -> 0 | BQ31: =SUM(BJ31:BL31) -> 0 | BR31: =SUM(BN31:BQ31) -> 813.81
A32: GUEST SERVICES - BC / CONVENIENCE STORE | B32: 500-1005 | C32: GUEST SERVICES - BC / CONVENIENCE STORE | D32: 500-1005 | E32: =SUMIF($BA$6:$BL$6,$E$6,$BA32:$BL32) -> 0 | F32: =SUMIF($AH$6:$AS$6,$F$6,$AH32:$AS32) -> 0 | G32: =IFERROR((E32-F32)/F32,0) -> 0 | H32: =SUMIF($BN$6:$BR$6,$H$6,$BN32:$BR32) -> 0 | I32: =SUMIF($AU$6:$AY$6,$I$6,$AU32:$AY32) -> 0 | J32: =IFERROR((H32-I32)/I32,0) -> 0 | K32: =BM32 -> 0 | L32: =SUM(AH32:AM32) -> 0 | M32: =IFERROR((K32-L32)/L32,0) -> 0 | O32: =SUMIF('2024 AC'!$B$3:$B$250,"*"&$D32&"*",'2024 AC'!C$3:C$250) -> 0 | P32: =SUMIF('2024 AC'!$B$3:$B$250,"*"&$D32&"*",'2024 AC'!D$3:D$250) -> 0 | Q32: =SUMIF('2024 AC'!$B$3:$B$250,"*"&$D32&"*",'2024 AC'!E$3:E$250) -> 0 | R32: =SUMIF('2024 AC'!$B$3:$B$250,"*"&$D32&"*",'2024 AC'!F$3:F$250) -> 0 | S32: =SUMIF('2024 AC'!$B$3:$B$250,"*"&$D32&"*",'2024 AC'!G$3:G$250) -> 416.67 | T32: =SUMIF('2024 AC'!$B$3:$B$250,"*"&$D32&"*",'2024 AC'!H$3:H$250) -> 0 | U32: =SUMIF('2024 AC'!$B$3:$B$250,"*"&$D32&"*",'2024 AC'!I$3:I$250) -> 127.12 | V32: =SUMIF('2024 AC'!$B$3:$B$250,"*"&$D32&"*",'2024 AC'!J$3:J$250) -> 127.12 | ... Z32: =SUMIF('2024 AC'!$B$3:$B$250,"*"&$D32&"*",'2024 AC'!N$3:N$250) -> 260.62 | AA32: =SUM(O32:Z32) -> 1061.2 | AB32: =SUM(O32:Q32) -> 0 | AC32: =SUM(R32:T32) -> 416.67 | AD32: =SUM(U32:W32) -> 383.91 | AE32: =SUM(X32:Z32) -> 260.62 | AF32: =SUM(AB32:AE32) -> 1061.2 | AH32: =SUMIF('2025 AC'!$B$3:$B$250,"*"&$D32&"*",'2025 AC'!C$3:C$250) -> 0 | AI32: =SUMIF('2025 AC'!$B$3:$B$250,"*"&$D32&"*",'2025 AC'!D$3:D$250) -> 0 | AJ32: =SUMIF('2025 AC'!$B$3:$B$250,"*"&$D32&"*",'2025 AC'!E$3:E$250) -> 0 | AK32: =SUMIF('2025 AC'!$B$3:$B$250,"*"&$D32&"*",'2025 AC'!F$3:F$250) -> 0 | AL32: =SUMIF('2025 AC'!$B$3:$B$250,"*"&$D32&"*",'2025 AC'!G$3:G$250) -> 0 | AM32: =SUMIF('2025 AC'!$B$3:$B$250,"*"&$D32&"*",'2025 AC'!H$3:H$250) -> 0 | AN32: =SUMIF('2025 AC'!$B$3:$B$250,"*"&$D32&"*",'2025 AC'!I$3:I$250) -> 0 | AO32: =SUMIF('2025 AC'!$B$3:$B$250,"*"&$D32&"*",'2025 AC'!J$3:J$250) -> 0 | ... AS32: =SUMIF('2025 AC'!$B$3:$B$250,"*"&$D32&"*",'2025 AC'!N$3:N$250) -> 0 | AT32: =SUM(AH32:AS32) -> 0 | AU32: =SUM(AH32:AJ32) -> 0 | AV32: =SUM(AK32:AM32) -> 0 | AW32: =SUM(AN32:AP32) -> 0 | AX32: =SUM(AQ32:AS32) -> 0 | AY32: =SUM(AU32:AX32) -> 0 | BA32: =SUMIF('2026 AC'!$B$3:$B$254,"*"&$D32&"*",'2026 AC'!C$3:C$254) -> 0 | BB32: =SUMIF('2026 AC'!$B$3:$B$254,"*"&$D32&"*",'2026 AC'!D$3:D$254) -> 0 | BC32: =SUMIF('2026 AC'!$B$3:$B$254,"*"&$D32&"*",'2026 AC'!E$3:E$254) -> 0 | BD32: =SUMIF('2026 AC'!$B$3:$B$254,"*"&$D32&"*",'2026 AC'!F$3:F$254) -> 0 | BE32: =SUMIF('2026 AC'!$B$3:$B$254,"*"&$D32&"*",'2026 AC'!G$3:G$254) -> 0 | BF32: =SUMIF('2026 AC'!$B$3:$B$254,"*"&$D32&"*",'2026 AC'!H$3:H$254) -> 0 | BG32: =SUMIF('2026 AC'!$B$3:$B$254,"*"&$D32&"*",'2026 AC'!I$3:I$254) -> 0 | BH32: =SUMIF('2026 AC'!$B$3:$B$254,"*"&$D32&"*",'2026 AC'!J$3:J$254) -> 0 | ... BL32: =SUMIF('2026 AC'!$B$3:$B$254,"*"&$D32&"*",'2026 AC'!N$3:N$254) -> 0 | BM32: =SUM(BA32:BL32) -> 0 | BN32: =SUM(BA32:BC32) -> 0 | BO32: =SUM(BD32:BF32) -> 0 | BP32: =SUM(BG32:BI32) -> 0 | BQ32: =SUM(BJ32:BL32) -> 0 | BR32: =SUM(BN32:BQ32) -> 0
A33: GUEST SERVICES - FLOWER / DECORATION | B33: 500-1006 | C33: GUEST SERVICES - FLOWER | D33: 500-1006 | E33: =SUMIF($BA$6:$BL$6,$E$6,$BA33:$BL33) -> 0 | F33: =SUMIF($AH$6:$AS$6,$F$6,$AH33:$AS33) -> 0 | G33: =IFERROR((E33-F33)/F33,0) -> 0 | H33: =SUMIF($BN$6:$BR$6,$H$6,$BN33:$BR33) -> 0 | I33: =SUMIF($AU$6:$AY$6,$I$6,$AU33:$AY33) -> 0 | J33: =IFERROR((H33-I33)/I33,1) -> 1 | K33: =BM33 -> 42.37 | L33: =SUM(AH33:AM33) -> 0 | M33: =IFERROR((K33-L33)/L33,1) -> 1 | O33: =SUMIF('2024 AC'!$B$3:$B$250,"*"&$D33&"*",'2024 AC'!C$3:C$250) -> 232.75 | P33: =SUMIF('2024 AC'!$B$3:$B$250,"*"&$D33&"*",'2024 AC'!D$3:D$250) -> 0 | Q33: =SUMIF('2024 AC'!$B$3:$B$250,"*"&$D33&"*",'2024 AC'!E$3:E$250) -> 0 | R33: =SUMIF('2024 AC'!$B$3:$B$250,"*"&$D33&"*",'2024 AC'!F$3:F$250) -> 0 | S33: =SUMIF('2024 AC'!$B$3:$B$250,"*"&$D33&"*",'2024 AC'!G$3:G$250) -> 0 | T33: =SUMIF('2024 AC'!$B$3:$B$250,"*"&$D33&"*",'2024 AC'!H$3:H$250) -> 0 | U33: =SUMIF('2024 AC'!$B$3:$B$250,"*"&$D33&"*",'2024 AC'!I$3:I$250) -> 0 | V33: =SUMIF('2024 AC'!$B$3:$B$250,"*"&$D33&"*",'2024 AC'!J$3:J$250) -> 0 | ... Z33: =SUMIF('2024 AC'!$B$3:$B$250,"*"&$D33&"*",'2024 AC'!N$3:N$250) -> 0 | AA33: =SUM(O33:Z33) -> 232.75 | AB33: =SUM(O33:Q33) -> 232.75 | AC33: =SUM(R33:T33) -> 0 | AD33: =SUM(U33:W33) -> 0 | AE33: =SUM(X33:Z33) -> 0 | AF33: =SUM(AB33:AE33) -> 232.75 | AH33: =SUMIF('2025 AC'!$B$3:$B$250,"*"&$D33&"*",'2025 AC'!C$3:C$250) -> 0 | AI33: =SUMIF('2025 AC'!$B$3:$B$250,"*"&$D33&"*",'2025 AC'!D$3:D$250) -> 0 | AJ33: =SUMIF('2025 AC'!$B$3:$B$250,"*"&$D33&"*",'2025 AC'!E$3:E$250) -> 0 | AK33: =SUMIF('2025 AC'!$B$3:$B$250,"*"&$D33&"*",'2025 AC'!F$3:F$250) -> 0 | AL33: =SUMIF('2025 AC'!$B$3:$B$250,"*"&$D33&"*",'2025 AC'!G$3:G$250) -> 0 | AM33: =SUMIF('2025 AC'!$B$3:$B$250,"*"&$D33&"*",'2025 AC'!H$3:H$250) -> 0 | AN33: =SUMIF('2025 AC'!$B$3:$B$250,"*"&$D33&"*",'2025 AC'!I$3:I$250) -> 42.37 | AO33: =SUMIF('2025 AC'!$B$3:$B$250,"*"&$D33&"*",'2025 AC'!J$3:J$250) -> 42.37 | ... AS33: =SUMIF('2025 AC'!$B$3:$B$250,"*"&$D33&"*",'2025 AC'!N$3:N$250) -> 0 | AT33: =SUM(AH33:AS33) -> 279.66 | AU33: =SUM(AH33:AJ33) -> 0 | AV33: =SUM(AK33:AM33) -> 0 | AW33: =SUM(AN33:AP33) -> 262.71 | AX33: =SUM(AQ33:AS33) -> 16.95 | AY33: =SUM(AU33:AX33) -> 279.66 | BA33: =SUMIF('2026 AC'!$B$3:$B$254,"*"&$D33&"*",'2026 AC'!C$3:C$254) -> 0 | BB33: =SUMIF('2026 AC'!$B$3:$B$254,"*"&$D33&"*",'2026 AC'!D$3:D$254) -> 42.37 | BC33: =SUMIF('2026 AC'!$B$3:$B$254,"*"&$D33&"*",'2026 AC'!E$3:E$254) -> 0 | BD33: =SUMIF('2026 AC'!$B$3:$B$254,"*"&$D33&"*",'2026 AC'!F$3:F$254) -> 0 | BE33: =SUMIF('2026 AC'!$B$3:$B$254,"*"&$D33&"*",'2026 AC'!G$3:G$254) -> 0 | BF33: =SUMIF('2026 AC'!$B$3:$B$254,"*"&$D33&"*",'2026 AC'!H$3:H$254) -> 0 | BG33: =SUMIF('2026 AC'!$B$3:$B$254,"*"&$D33&"*",'2026 AC'!I$3:I$254) -> 0 | BH33: =SUMIF('2026 AC'!$B$3:$B$254,"*"&$D33&"*",'2026 AC'!J$3:J$254) -> 0 | ... BL33: =SUMIF('2026 AC'!$B$3:$B$254,"*"&$D33&"*",'2026 AC'!N$3:N$254) -> 0 | BM33: =SUM(BA33:BL33) -> 42.37 | BN33: =SUM(BA33:BC33) -> 42.37 | BO33: =SUM(BD33:BF33) -> 0 | BP33: =SUM(BG33:BI33) -> 0 | BQ33: =SUM(BJ33:BL33) -> 0 | BR33: =SUM(BN33:BQ33) -> 42.37
A34: GUEST SERVICES - TELEPHONE | B34: 500-1007 | C34: GUEST SERVICES - TELEPHONE | D34: 500-1007 | E34: =SUMIF($BA$6:$BL$6,$E$6,$BA34:$BL34) -> 0 | F34: =SUMIF($AH$6:$AS$6,$F$6,$AH34:$AS34) -> 0 | G34: =IFERROR((E34-F34)/F34,0) -> 0 | H34: =SUMIF($BN$6:$BR$6,$H$6,$BN34:$BR34) -> 0 | I34: =SUMIF($AU$6:$AY$6,$I$6,$AU34:$AY34) -> 0 | J34: =IFERROR((H34-I34)/I34,0) -> 0 | K34: =BM34 -> 0 | L34: =SUM(AH34:AM34) -> 0 | M34: =IFERROR((K34-L34)/L34,0) -> 0 | O34: =SUMIF('2024 AC'!$B$3:$B$250,"*"&$D34&"*",'2024 AC'!C$3:C$250) -> 0 | P34: =SUMIF('2024 AC'!$B$3:$B$250,"*"&$D34&"*",'2024 AC'!D$3:D$250) -> 0 | Q34: =SUMIF('2024 AC'!$B$3:$B$250,"*"&$D34&"*",'2024 AC'!E$3:E$250) -> 0 | R34: =SUMIF('2024 AC'!$B$3:$B$250,"*"&$D34&"*",'2024 AC'!F$3:F$250) -> 0 | S34: =SUMIF('2024 AC'!$B$3:$B$250,"*"&$D34&"*",'2024 AC'!G$3:G$250) -> 0 | T34: =SUMIF('2024 AC'!$B$3:$B$250,"*"&$D34&"*",'2024 AC'!H$3:H$250) -> 0 | U34: =SUMIF('2024 AC'!$B$3:$B$250,"*"&$D34&"*",'2024 AC'!I$3:I$250) -> 0 | V34: =SUMIF('2024 AC'!$B$3:$B$250,"*"&$D34&"*",'2024 AC'!J$3:J$250) -> 0 | ... Z34: =SUMIF('2024 AC'!$B$3:$B$250,"*"&$D34&"*",'2024 AC'!N$3:N$250) -> 0 | AA34: =SUM(O34:Z34) -> 0 | AB34: =SUM(O34:Q34) -> 0 | AC34: =SUM(R34:T34) -> 0 | AD34: =SUM(U34:W34) -> 0 | AE34: =SUM(X34:Z34) -> 0 | AF34: =SUM(AB34:AE34) -> 0 | AH34: =SUMIF('2025 AC'!$B$3:$B$250,"*"&$D34&"*",'2025 AC'!C$3:C$250) -> 0 | AI34: =SUMIF('2025 AC'!$B$3:$B$250,"*"&$D34&"*",'2025 AC'!D$3:D$250) -> 0 | AJ34: =SUMIF('2025 AC'!$B$3:$B$250,"*"&$D34&"*",'2025 AC'!E$3:E$250) -> 0 | AK34: =SUMIF('2025 AC'!$B$3:$B$250,"*"&$D34&"*",'2025 AC'!F$3:F$250) -> 0 | AL34: =SUMIF('2025 AC'!$B$3:$B$250,"*"&$D34&"*",'2025 AC'!G$3:G$250) -> 0 | AM34: =SUMIF('2025 AC'!$B$3:$B$250,"*"&$D34&"*",'2025 AC'!H$3:H$250) -> 0 | AN34: =SUMIF('2025 AC'!$B$3:$B$250,"*"&$D34&"*",'2025 AC'!I$3:I$250) -> 0 | AO34: =SUMIF('2025 AC'!$B$3:$B$250,"*"&$D34&"*",'2025 AC'!J$3:J$250) -> 0 | ... AS34: =SUMIF('2025 AC'!$B$3:$B$250,"*"&$D34&"*",'2025 AC'!N$3:N$250) -> 0 | AT34: =SUM(AH34:AS34) -> 0 | AU34: =SUM(AH34:AJ34) -> 0 | AV34: =SUM(AK34:AM34) -> 0 | AW34: =SUM(AN34:AP34) -> 0 | AX34: =SUM(AQ34:AS34) -> 0 | AY34: =SUM(AU34:AX34) -> 0 | BA34: =SUMIF('2026 AC'!$B$3:$B$254,"*"&$D34&"*",'2026 AC'!C$3:C$254) -> 0 | BB34: =SUMIF('2026 AC'!$B$3:$B$254,"*"&$D34&"*",'2026 AC'!D$3:D$254) -> 0 | BC34: =SUMIF('2026 AC'!$B$3:$B$254,"*"&$D34&"*",'2026 AC'!E$3:E$254) -> 0 | BD34: =SUMIF('2026 AC'!$B$3:$B$254,"*"&$D34&"*",'2026 AC'!F$3:F$254) -> 0 | BE34: =SUMIF('2026 AC'!$B$3:$B$254,"*"&$D34&"*",'2026 AC'!G$3:G$254) -> 0 | BF34: =SUMIF('2026 AC'!$B$3:$B$254,"*"&$D34&"*",'2026 AC'!H$3:H$254) -> 0 | BG34: =SUMIF('2026 AC'!$B$3:$B$254,"*"&$D34&"*",'2026 AC'!I$3:I$254) -> 0 | BH34: =SUMIF('2026 AC'!$B$3:$B$254,"*"&$D34&"*",'2026 AC'!J$3:J$254) -> 0 | ... BL34: =SUMIF('2026 AC'!$B$3:$B$254,"*"&$D34&"*",'2026 AC'!N$3:N$254) -> 0 | BM34: =SUM(BA34:BL34) -> 0 | BN34: =SUM(BA34:BC34) -> 0 | BO34: =SUM(BD34:BF34) -> 0 | BP34: =SUM(BG34:BI34) -> 0 | BQ34: =SUM(BJ34:BL34) -> 0 | BR34: =SUM(BN34:BQ34) -> 0
A35: GUEST SERVICES - TRANSPORTATION | B35: 500-1008 | C35: GUEST SERVICES - TRANSPORTATION | D35: 500-1008 | E35: =SUMIF($BA$6:$BL$6,$E$6,$BA35:$BL35) -> 0 | F35: =SUMIF($AH$6:$AS$6,$F$6,$AH35:$AS35) -> 275.08 | G35: =IFERROR((E35-F35)/F35,0) -> -1 | H35: =SUMIF($BN$6:$BR$6,$H$6,$BN35:$BR35) -> 0 | I35: =SUMIF($AU$6:$AY$6,$I$6,$AU35:$AY35) -> 616.77 | J35: =(H35-I35)/I35 -> -1 | K35: =BM35 -> 254.25 | L35: =SUM(AH35:AM35) -> 676.26 | M35: =(K35-L35)/L35 -> -0.62403513 | O35: =SUMIF('2024 AC'!$B$3:$B$250,"*"&$D35&"*",'2024 AC'!C$3:C$250) -> 0 | P35: =SUMIF('2024 AC'!$B$3:$B$250,"*"&$D35&"*",'2024 AC'!D$3:D$250) -> 172.42 | Q35: =SUMIF('2024 AC'!$B$3:$B$250,"*"&$D35&"*",'2024 AC'!E$3:E$250) -> 0 | R35: =SUMIF('2024 AC'!$B$3:$B$250,"*"&$D35&"*",'2024 AC'!F$3:F$250) -> 84.75 | S35: =SUMIF('2024 AC'!$B$3:$B$250,"*"&$D35&"*",'2024 AC'!G$3:G$250) -> 338.99 | T35: =SUMIF('2024 AC'!$B$3:$B$250,"*"&$D35&"*",'2024 AC'!H$3:H$250) -> 169.5 | U35: =SUMIF('2024 AC'!$B$3:$B$250,"*"&$D35&"*",'2024 AC'!I$3:I$250) -> 0 | V35: =SUMIF('2024 AC'!$B$3:$B$250,"*"&$D35&"*",'2024 AC'!J$3:J$250) -> 169.5 | ... Z35: =SUMIF('2024 AC'!$B$3:$B$250,"*"&$D35&"*",'2024 AC'!N$3:N$250) -> 292.38 | AA35: =SUM(O35:Z35) -> 1464.16 | AB35: =SUM(O35:Q35) -> 172.42 | AC35: =SUM(R35:T35) -> 593.24 | AD35: =SUM(U35:W35) -> 254.25 | AE35: =SUM(X35:Z35) -> 444.25 | AF35: =SUM(AB35:AE35) -> 1464.16 | AH35: =SUMIF('2025 AC'!$B$3:$B$250,"*"&$D35&"*",'2025 AC'!C$3:C$250) -> 8.65 | AI35: =SUMIF('2025 AC'!$B$3:$B$250,"*"&$D35&"*",'2025 AC'!D$3:D$250) -> 50.84 | AJ35: =SUMIF('2025 AC'!$B$3:$B$250,"*"&$D35&"*",'2025 AC'!E$3:E$250) -> 0 | AK35: =SUMIF('2025 AC'!$B$3:$B$250,"*"&$D35&"*",'2025 AC'!F$3:F$250) -> 0 | AL35: =SUMIF('2025 AC'!$B$3:$B$250,"*"&$D35&"*",'2025 AC'!G$3:G$250) -> 341.69 | AM35: =SUMIF('2025 AC'!$B$3:$B$250,"*"&$D35&"*",'2025 AC'!H$3:H$250) -> 275.08 | AN35: =SUMIF('2025 AC'!$B$3:$B$250,"*"&$D35&"*",'2025 AC'!I$3:I$250) -> 121.53 | AO35: =SUMIF('2025 AC'!$B$3:$B$250,"*"&$D35&"*",'2025 AC'!J$3:J$250) -> 169.5 | ... AS35: =SUMIF('2025 AC'!$B$3:$B$250,"*"&$D35&"*",'2025 AC'!N$3:N$250) -> 0 | AT35: =SUM(AH35:AS35) -> 967.29 | AU35: =SUM(AH35:AJ35) -> 59.49 | AV35: =SUM(AK35:AM35) -> 616.77 | AW35: =SUM(AN35:AP35) -> 291.03 | AX35: =SUM(AQ35:AS35) -> 0 | AY35: =SUM(AU35:AX35) -> 967.29 | BA35: =SUMIF('2026 AC'!$B$3:$B$254,"*"&$D35&"*",'2026 AC'!C$3:C$254) -> 254.25 | BB35: =SUMIF('2026 AC'!$B$3:$B$254,"*"&$D35&"*",'2026 AC'!D$3:D$254) -> 0 | BC35: =SUMIF('2026 AC'!$B$3:$B$254,"*"&$D35&"*",'2026 AC'!E$3:E$254) -> 0 | BD35: =SUMIF('2026 AC'!$B$3:$B$254,"*"&$D35&"*",'2026 AC'!F$3:F$254) -> 0 | BE35: =SUMIF('2026 AC'!$B$3:$B$254,"*"&$D35&"*",'2026 AC'!G$3:G$254) -> 0 | BF35: =SUMIF('2026 AC'!$B$3:$B$254,"*"&$D35&"*",'2026 AC'!H$3:H$254) -> 0 | BG35: =SUMIF('2026 AC'!$B$3:$B$254,"*"&$D35&"*",'2026 AC'!I$3:I$254) -> 0 | BH35: =SUMIF('2026 AC'!$B$3:$B$254,"*"&$D35&"*",'2026 AC'!J$3:J$254) -> 0 | ... BL35: =SUMIF('2026 AC'!$B$3:$B$254,"*"&$D35&"*",'2026 AC'!N$3:N$254) -> 0 | BM35: =SUM(BA35:BL35) -> 254.25 | BN35: =SUM(BA35:BC35) -> 254.25 | BO35: =SUM(BD35:BF35) -> 0 | BP35: =SUM(BG35:BI35) -> 0 | BQ35: =SUM(BJ35:BL35) -> 0 | BR35: =SUM(BN35:BQ35) -> 254.25
A36: GUEST SERVICES - ROOM KEY CARD | B36: 500-1009 | C36: GUEST SERVICES - ROOM KEY CARD | D36: 500-1009 | E36: =SUMIF($BA$6:$BL$6,$E$6,$BA36:$BL36) -> 0 | F36: =SUMIF($AH$6:$AS$6,$F$6,$AH36:$AS36) -> 0 | G36: =IFERROR((E36-F36)/F36,0) -> 0 | H36: =SUMIF($BN$6:$BR$6,$H$6,$BN36:$BR36) -> 10 | I36: =SUMIF($AU$6:$AY$6,$I$6,$AU36:$AY36) -> 0 | J36: =IFERROR((H36-I36)/I36,1) -> 1 | K36: =BM36 -> 10 | L36: =SUM(AH36:AM36) -> 0 | M36: =IFERROR((K36-L36)/L36,1) -> 1 | O36: =SUMIF('2024 AC'!$B$3:$B$250,"*"&$D36&"*",'2024 AC'!C$3:C$250) -> 0 | P36: =SUMIF('2024 AC'!$B$3:$B$250,"*"&$D36&"*",'2024 AC'!D$3:D$250) -> 0 | Q36: =SUMIF('2024 AC'!$B$3:$B$250,"*"&$D36&"*",'2024 AC'!E$3:E$250) -> 0 | R36: =SUMIF('2024 AC'!$B$3:$B$250,"*"&$D36&"*",'2024 AC'!F$3:F$250) -> 0 | S36: =SUMIF('2024 AC'!$B$3:$B$250,"*"&$D36&"*",'2024 AC'!G$3:G$250) -> 0 | T36: =SUMIF('2024 AC'!$B$3:$B$250,"*"&$D36&"*",'2024 AC'!H$3:H$250) -> 0 | U36: =SUMIF('2024 AC'!$B$3:$B$250,"*"&$D36&"*",'2024 AC'!I$3:I$250) -> 0 | V36: =SUMIF('2024 AC'!$B$3:$B$250,"*"&$D36&"*",'2024 AC'!J$3:J$250) -> 0 | ... Z36: =SUMIF('2024 AC'!$B$3:$B$250,"*"&$D36&"*",'2024 AC'!N$3:N$250) -> 0 | AA36: =SUM(O36:Z36) -> 20 | AB36: =SUM(O36:Q36) -> 0 | AC36: =SUM(R36:T36) -> 0 | AD36: =SUM(U36:W36) -> 10 | AE36: =SUM(X36:Z36) -> 10 | AF36: =SUM(AB36:AE36) -> 20 | AH36: =SUMIF('2025 AC'!$B$3:$B$250,"*"&$D36&"*",'2025 AC'!C$3:C$250) -> 0 | AI36: =SUMIF('2025 AC'!$B$3:$B$250,"*"&$D36&"*",'2025 AC'!D$3:D$250) -> 0 | AJ36: =SUMIF('2025 AC'!$B$3:$B$250,"*"&$D36&"*",'2025 AC'!E$3:E$250) -> 0 | AK36: =SUMIF('2025 AC'!$B$3:$B$250,"*"&$D36&"*",'2025 AC'!F$3:F$250) -> 0 | AL36: =SUMIF('2025 AC'!$B$3:$B$250,"*"&$D36&"*",'2025 AC'!G$3:G$250) -> 0 | AM36: =SUMIF('2025 AC'!$B$3:$B$250,"*"&$D36&"*",'2025 AC'!H$3:H$250) -> 0 | AN36: =SUMIF('2025 AC'!$B$3:$B$250,"*"&$D36&"*",'2025 AC'!I$3:I$250) -> 0 | AO36: =SUMIF('2025 AC'!$B$3:$B$250,"*"&$D36&"*",'2025 AC'!J$3:J$250) -> 0 | ... AS36: =SUMIF('2025 AC'!$B$3:$B$250,"*"&$D36&"*",'2025 AC'!N$3:N$250) -> 9.18 | AT36: =SUM(AH36:AS36) -> 9.18 | AU36: =SUM(AH36:AJ36) -> 0 | AV36: =SUM(AK36:AM36) -> 0 | AW36: =SUM(AN36:AP36) -> 0 | AX36: =SUM(AQ36:AS36) -> 9.18 | AY36: =SUM(AU36:AX36) -> 9.18 | BA36: =SUMIF('2026 AC'!$B$3:$B$254,"*"&$D36&"*",'2026 AC'!C$3:C$254) -> 0 | BB36: =SUMIF('2026 AC'!$B$3:$B$254,"*"&$D36&"*",'2026 AC'!D$3:D$254) -> 0 | BC36: =SUMIF('2026 AC'!$B$3:$B$254,"*"&$D36&"*",'2026 AC'!E$3:E$254) -> 0 | BD36: =SUMIF('2026 AC'!$B$3:$B$254,"*"&$D36&"*",'2026 AC'!F$3:F$254) -> 0 | BE36: =SUMIF('2026 AC'!$B$3:$B$254,"*"&$D36&"*",'2026 AC'!G$3:G$254) -> 10 | BF36: =SUMIF('2026 AC'!$B$3:$B$254,"*"&$D36&"*",'2026 AC'!H$3:H$254) -> 0 | BG36: =SUMIF('2026 AC'!$B$3:$B$254,"*"&$D36&"*",'2026 AC'!I$3:I$254) -> 0 | BH36: =SUMIF('2026 AC'!$B$3:$B$254,"*"&$D36&"*",'2026 AC'!J$3:J$254) -> 0 | ... BL36: =SUMIF('2026 AC'!$B$3:$B$254,"*"&$D36&"*",'2026 AC'!N$3:N$254) -> 0 | BM36: =SUM(BA36:BL36) -> 10 | BN36: =SUM(BA36:BC36) -> 0 | BO36: =SUM(BD36:BF36) -> 10 | BP36: =SUM(BG36:BI36) -> 0 | BQ36: =SUM(BJ36:BL36) -> 0 | BR36: =SUM(BN36:BQ36) -> 10
A37: ROOM SERVICE CHARGE | B37: 500-RMSC | C37: ROOM SERVICE CHARGE | D37: 500-RMSC | E37: =SUMIF($BA$6:$BL$6,$E$6,$BA37:$BL37) -> 10501.29 | F37: =SUMIF($AH$6:$AS$6,$F$6,$AH37:$AS37) -> 13972.88 | G37: =(E37-F37)/F37 -> -0.248452 | H37: =SUMIF($BN$6:$BR$6,$H$6,$BN37:$BR37) -> 32536.55 | I37: =SUMIF($AU$6:$AY$6,$I$6,$AU37:$AY37) -> 44079.39 | J37: =(H37-I37)/I37 -> -0.26186479 | K37: =BM37 -> 62939.23 | L37: =SUM(AH37:AM37) -> 71262.65 | M37: =(K37-L37)/L37 -> -0.11679919 | O37: =SUMIF('2024 AC'!$B$3:$B$250,"*"&$D37&"*",'2024 AC'!C$3:C$250) -> 16553.62 | P37: =SUMIF('2024 AC'!$B$3:$B$250,"*"&$D37&"*",'2024 AC'!D$3:D$250) -> 20560.03 | Q37: =SUMIF('2024 AC'!$B$3:$B$250,"*"&$D37&"*",'2024 AC'!E$3:E$250) -> 7550.17 | R37: =SUMIF('2024 AC'!$B$3:$B$250,"*"&$D37&"*",'2024 AC'!F$3:F$250) -> 10739.64 | S37: =SUMIF('2024 AC'!$B$3:$B$250,"*"&$D37&"*",'2024 AC'!G$3:G$250) -> 17809.02 | T37: =SUMIF('2024 AC'!$B$3:$B$250,"*"&$D37&"*",'2024 AC'!H$3:H$250) -> 13795.41 | U37: =SUMIF('2024 AC'!$B$3:$B$250,"*"&$D37&"*",'2024 AC'!I$3:I$250) -> 16256.45 | V37: =SUMIF('2024 AC'!$B$3:$B$250,"*"&$D37&"*",'2024 AC'!J$3:J$250) -> 25670.24 | ... Z37: =SUMIF('2024 AC'!$B$3:$B$250,"*"&$D37&"*",'2024 AC'!N$3:N$250) -> 10189.48 | AA37: =SUM(O37:Z37) -> 187960.29 | AB37: =SUM(O37:Q37) -> 44663.82 | AC37: =SUM(R37:T37) -> 42344.07 | AD37: =SUM(U37:W37) -> 54340.43 | AE37: =SUM(X37:Z37) -> 46611.97 | AF37: =SUM(AB37:AE37) -> 187960.29 | AH37: =SUMIF('2025 AC'!$B$3:$B$250,"*"&$D37&"*",'2025 AC'!C$3:C$250) -> 11246.65 | AI37: =SUMIF('2025 AC'!$B$3:$B$250,"*"&$D37&"*",'2025 AC'!D$3:D$250) -> 9087.34 | AJ37: =SUMIF('2025 AC'!$B$3:$B$250,"*"&$D37&"*",'2025 AC'!E$3:E$250) -> 6849.27 | AK37: =SUMIF('2025 AC'!$B$3:$B$250,"*"&$D37&"*",'2025 AC'!F$3:F$250) -> 12673.56 | AL37: =SUMIF('2025 AC'!$B$3:$B$250,"*"&$D37&"*",'2025 AC'!G$3:G$250) -> 17432.95 | AM37: =SUMIF('2025 AC'!$B$3:$B$250,"*"&$D37&"*",'2025 AC'!H$3:H$250) -> 13972.88 | AN37: =SUMIF('2025 AC'!$B$3:$B$250,"*"&$D37&"*",'2025 AC'!I$3:I$250) -> 15312.74 | AO37: =SUMIF('2025 AC'!$B$3:$B$250,"*"&$D37&"*",'2025 AC'!J$3:J$250) -> 14506.83 | ... AS37: =SUMIF('2025 AC'!$B$3:$B$250,"*"&$D37&"*",'2025 AC'!N$3:N$250) -> 11937.53 | AT37: =SUM(AH37:AS37) -> 156794.07 | AU37: =SUM(AH37:AJ37) -> 27183.26 | AV37: =SUM(AK37:AM37) -> 44079.39 | AW37: =SUM(AN37:AP37) -> 47738.03 | AX37: =SUM(AQ37:AS37) -> 37793.39 | AY37: =SUM(AU37:AX37) -> 156794.07 | BA37: =SUMIF('2026 AC'!$B$3:$B$254,"*"&$D37&"*",'2026 AC'!C$3:C$254) -> 12036.46 | BB37: =SUMIF('2026 AC'!$B$3:$B$254,"*"&$D37&"*",'2026 AC'!D$3:D$254) -> 8679.59 | BC37: =SUMIF('2026 AC'!$B$3:$B$254,"*"&$D37&"*",'2026 AC'!E$3:E$254) -> 9686.63 | BD37: =SUMIF('2026 AC'!$B$3:$B$254,"*"&$D37&"*",'2026 AC'!F$3:F$254) -> 14581.56 | BE37: =SUMIF('2026 AC'!$B$3:$B$254,"*"&$D37&"*",'2026 AC'!G$3:G$254) -> 7453.7 | BF37: =SUMIF('2026 AC'!$B$3:$B$254,"*"&$D37&"*",'2026 AC'!H$3:H$254) -> 10501.29 | BG37: =SUMIF('2026 AC'!$B$3:$B$254,"*"&$D37&"*",'2026 AC'!I$3:I$254) -> 0 | BH37: =SUMIF('2026 AC'!$B$3:$B$254,"*"&$D37&"*",'2026 AC'!J$3:J$254) -> 0 | ... BL37: =SUMIF('2026 AC'!$B$3:$B$254,"*"&$D37&"*",'2026 AC'!N$3:N$254) -> 0 | BM37: =SUM(BA37:BL37) -> 62939.23 | BN37: =SUM(BA37:BC37) -> 30402.68 | BO37: =SUM(BD37:BF37) -> 32536.55 | BP37: =SUM(BG37:BI37) -> 0 | BQ37: =SUM(BJ37:BL37) -> 0 | BR37: =SUM(BN37:BQ37) -> 62939.23
A38: F&B REVENUE | B38: 500-2000 | C38: F&B REVENUE | D38: 500-2000 | E38: =SUMIF($BA$6:$BL$6,$E$6,$BA38:$BL38) -> 17895.14 | F38: =SUMIF($AH$6:$AS$6,$F$6,$AH38:$AS38) -> 12236.47 | G38: =(E38-F38)/F38 -> 0.46244301 | H38: =SUMIF($BN$6:$BR$6,$H$6,$BN38:$BR38) -> 38463.62 | I38: =SUMIF($AU$6:$AY$6,$I$6,$AU38:$AY38) -> 49885.46 | J38: =(H38-I38)/I38 -> -0.2289613 | K38: =BM38 -> 194334.4 | L38: =SUM(AH38:AM38) -> 245457.27 | M38: =(K38-L38)/L38 -> -0.20827605 | O38: =SUMIF('2024 AC'!$B$3:$B$250,"*"&$D38&"*",'2024 AC'!C$3:C$250) -> 25359.38 | P38: =SUMIF('2024 AC'!$B$3:$B$250,"*"&$D38&"*",'2024 AC'!D$3:D$250) -> 28424.25 | Q38: =SUMIF('2024 AC'!$B$3:$B$250,"*"&$D38&"*",'2024 AC'!E$3:E$250) -> 97945.96 | R38: =SUMIF('2024 AC'!$B$3:$B$250,"*"&$D38&"*",'2024 AC'!F$3:F$250) -> 70797.07 | S38: =SUMIF('2024 AC'!$B$3:$B$250,"*"&$D38&"*",'2024 AC'!G$3:G$250) -> 33305.83 | T38: =SUMIF('2024 AC'!$B$3:$B$250,"*"&$D38&"*",'2024 AC'!H$3:H$250) -> 29357.49 | U38: =SUMIF('2024 AC'!$B$3:$B$250,"*"&$D38&"*",'2024 AC'!I$3:I$250) -> 36166 | V38: =SUMIF('2024 AC'!$B$3:$B$250,"*"&$D38&"*",'2024 AC'!J$3:J$250) -> 33224.16 | ... Z38: =SUMIF('2024 AC'!$B$3:$B$250,"*"&$D38&"*",'2024 AC'!N$3:N$250) -> 19440.23 | AA38: =SUM(O38:Z38) -> 421190.4 | AB38: =SUM(O38:Q38) -> 151729.59 | AC38: =SUM(R38:T38) -> 133460.39 | AD38: =SUM(U38:W38) -> 89795.43 | AE38: =SUM(X38:Z38) -> 46204.99 | AF38: =SUM(AB38:AE38) -> 421190.4 | AH38: =SUMIF('2025 AC'!$B$3:$B$250,"*"&$D38&"*",'2025 AC'!C$3:C$250) -> 11237.62 | AI38: =SUMIF('2025 AC'!$B$3:$B$250,"*"&$D38&"*",'2025 AC'!D$3:D$250) -> 11051.17 | AJ38: =SUMIF('2025 AC'!$B$3:$B$250,"*"&$D38&"*",'2025 AC'!E$3:E$250) -> 173283.02 | AK38: =SUMIF('2025 AC'!$B$3:$B$250,"*"&$D38&"*",'2025 AC'!F$3:F$250) -> 22433.86 | AL38: =SUMIF('2025 AC'!$B$3:$B$250,"*"&$D38&"*",'2025 AC'!G$3:G$250) -> 15215.13 | AM38: =SUMIF('2025 AC'!$B$3:$B$250,"*"&$D38&"*",'2025 AC'!H$3:H$250) -> 12236.47 | AN38: =SUMIF('2025 AC'!$B$3:$B$250,"*"&$D38&"*",'2025 AC'!I$3:I$250) -> 13176.76 | AO38: =SUMIF('2025 AC'!$B$3:$B$250,"*"&$D38&"*",'2025 AC'!J$3:J$250) -> 12812.24 | ... AS38: =SUMIF('2025 AC'!$B$3:$B$250,"*"&$D38&"*",'2025 AC'!N$3:N$250) -> 15761.74 | AT38: =SUM(AH38:AS38) -> 322508.96 | AU38: =SUM(AH38:AJ38) -> 195571.81 | AV38: =SUM(AK38:AM38) -> 49885.46 | AW38: =SUM(AN38:AP38) -> 38989.86 | AX38: =SUM(AQ38:AS38) -> 38061.83 | AY38: =SUM(AU38:AX38) -> 322508.96 | BA38: =SUMIF('2026 AC'!$B$3:$B$254,"*"&$D38&"*",'2026 AC'!C$3:C$254) -> 18794.09 | BB38: =SUMIF('2026 AC'!$B$3:$B$254,"*"&$D38&"*",'2026 AC'!D$3:D$254) -> 27030.97 | BC38: =SUMIF('2026 AC'!$B$3:$B$254,"*"&$D38&"*",'2026 AC'!E$3:E$254) -> 110045.72 | BD38: =SUMIF('2026 AC'!$B$3:$B$254,"*"&$D38&"*",'2026 AC'!F$3:F$254) -> 10962.42 | BE38: =SUMIF('2026 AC'!$B$3:$B$254,"*"&$D38&"*",'2026 AC'!G$3:G$254) -> 9606.06 | BF38: =SUMIF('2026 AC'!$B$3:$B$254,"*"&$D38&"*",'2026 AC'!H$3:H$254) -> 17895.14 | BG38: =SUMIF('2026 AC'!$B$3:$B$254,"*"&$D38&"*",'2026 AC'!I$3:I$254) -> 0 | BH38: =SUMIF('2026 AC'!$B$3:$B$254,"*"&$D38&"*",'2026 AC'!J$3:J$254) -> 0 | ... BL38: =SUMIF('2026 AC'!$B$3:$B$254,"*"&$D38&"*",'2026 AC'!N$3:N$254) -> 0 | BM38: =SUM(BA38:BL38) -> 194334.4 | BN38: =SUM(BA38:BC38) -> 155870.78 | BO38: =SUM(BD38:BF38) -> 38463.62 | BP38: =SUM(BG38:BI38) -> 0 | BQ38: =SUM(BJ38:BL38) -> 0 | BR38: =SUM(BN38:BQ38) -> 194334.4
A39: BREAKFAST PACKAGE (FO) | B39: 500-BF01 | C39: BREAKFAST PACKAGE (FO)* | D39: 500-BF01 | E39: =SUMIF($BA$6:$BL$6,$E$6,$BA39:$BL39) -> 9060.81 | F39: =SUMIF($AH$6:$AS$6,$F$6,$AH39:$AS39) -> 10241.5 | G39: =(E39-F39)/F39 -> -0.11528487 | H39: =SUMIF($BN$6:$BR$6,$H$6,$BN39:$BR39) -> 19107.67 | I39: =SUMIF($AU$6:$AY$6,$I$6,$AU39:$AY39) -> 37373.76 | J39: =(H39-I39)/I39 -> -0.48874103 | K39: =BM39 -> 40321.85 | L39: =SUM(AH39:AM39) -> 70646.19 | M39: =(K39-L39)/L39 -> -0.4292424 | O39: =SUMIF('2024 AC'!$B$3:$B$250,"*"&$D39&"*",'2024 AC'!C$3:C$250) -> 1164.19 | P39: =SUMIF('2024 AC'!$B$3:$B$250,"*"&$D39&"*",'2024 AC'!D$3:D$250) -> 978.68 | Q39: =SUMIF('2024 AC'!$B$3:$B$250,"*"&$D39&"*",'2024 AC'!E$3:E$250) -> 3076.37 | R39: =SUMIF('2024 AC'!$B$3:$B$250,"*"&$D39&"*",'2024 AC'!F$3:F$250) -> 2724.56 | S39: =SUMIF('2024 AC'!$B$3:$B$250,"*"&$D39&"*",'2024 AC'!G$3:G$250) -> 1949.11 | T39: =SUMIF('2024 AC'!$B$3:$B$250,"*"&$D39&"*",'2024 AC'!H$3:H$250) -> 3364.7 | U39: =SUMIF('2024 AC'!$B$3:$B$250,"*"&$D39&"*",'2024 AC'!I$3:I$250) -> 14121.59 | V39: =SUMIF('2024 AC'!$B$3:$B$250,"*"&$D39&"*",'2024 AC'!J$3:J$250) -> 4190.85 | ... Z39: =SUMIF('2024 AC'!$B$3:$B$250,"*"&$D39&"*",'2024 AC'!N$3:N$250) -> 13585.1 | AA39: =SUM(O39:Z39) -> 83171.21 | AB39: =SUM(O39:Q39) -> 5219.24 | AC39: =SUM(R39:T39) -> 8038.37 | AD39: =SUM(U39:W39) -> 29563.74 | AE39: =SUM(X39:Z39) -> 40349.86 | AF39: =SUM(AB39:AE39) -> 83171.21 | AH39: =SUMIF('2025 AC'!$B$3:$B$250,"*"&$D39&"*",'2025 AC'!C$3:C$250) -> 11237.62 | AI39: =SUMIF('2025 AC'!$B$3:$B$250,"*"&$D39&"*",'2025 AC'!D$3:D$250) -> 9051.17 | AJ39: =SUMIF('2025 AC'!$B$3:$B$250,"*"&$D39&"*",'2025 AC'!E$3:E$250) -> 12983.64 | AK39: =SUMIF('2025 AC'!$B$3:$B$250,"*"&$D39&"*",'2025 AC'!F$3:F$250) -> 14924.2 | AL39: =SUMIF('2025 AC'!$B$3:$B$250,"*"&$D39&"*",'2025 AC'!G$3:G$250) -> 12208.06 | AM39: =SUMIF('2025 AC'!$B$3:$B$250,"*"&$D39&"*",'2025 AC'!H$3:H$250) -> 10241.5 | AN39: =SUMIF('2025 AC'!$B$3:$B$250,"*"&$D39&"*",'2025 AC'!I$3:I$250) -> 10898.86 | AO39: =SUMIF('2025 AC'!$B$3:$B$250,"*"&$D39&"*",'2025 AC'!J$3:J$250) -> 8072.39 | ... AS39: =SUMIF('2025 AC'!$B$3:$B$250,"*"&$D39&"*",'2025 AC'!N$3:N$250) -> 7502.84 | AT39: =SUM(AH39:AS39) -> 116773.76 | AU39: =SUM(AH39:AJ39) -> 33272.43 | AV39: =SUM(AK39:AM39) -> 37373.76 | AW39: =SUM(AN39:AP39) -> 23738.39 | AX39: =SUM(AQ39:AS39) -> 22389.18 | AY39: =SUM(AU39:AX39) -> 116773.76 | BA39: =SUMIF('2026 AC'!$B$3:$B$254,"*"&$D39&"*",'2026 AC'!C$3:C$254) -> 6606.96 | BB39: =SUMIF('2026 AC'!$B$3:$B$254,"*"&$D39&"*",'2026 AC'!D$3:D$254) -> 6051.21 | BC39: =SUMIF('2026 AC'!$B$3:$B$254,"*"&$D39&"*",'2026 AC'!E$3:E$254) -> 8556.01 | BD39: =SUMIF('2026 AC'!$B$3:$B$254,"*"&$D39&"*",'2026 AC'!F$3:F$254) -> 6467.97 | BE39: =SUMIF('2026 AC'!$B$3:$B$254,"*"&$D39&"*",'2026 AC'!G$3:G$254) -> 3578.89 | BF39: =SUMIF('2026 AC'!$B$3:$B$254,"*"&$D39&"*",'2026 AC'!H$3:H$254) -> 9060.81 | BG39: =SUMIF('2026 AC'!$B$3:$B$254,"*"&$D39&"*",'2026 AC'!I$3:I$254) -> 0 | BH39: =SUMIF('2026 AC'!$B$3:$B$254,"*"&$D39&"*",'2026 AC'!J$3:J$254) -> 0 | ... BL39: =SUMIF('2026 AC'!$B$3:$B$254,"*"&$D39&"*",'2026 AC'!N$3:N$254) -> 0 | BM39: =SUM(BA39:BL39) -> 40321.85 | BN39: =SUM(BA39:BC39) -> 21214.18 | BO39: =SUM(BD39:BF39) -> 19107.67 | BP39: =SUM(BG39:BI39) -> 0 | BQ39: =SUM(BJ39:BL39) -> 0 | BR39: =SUM(BN39:BQ39) -> 40321.85
A40: BREAKFAST SERVICE CHARGE | B40: 500-BFSC | C40: BREAKFAST SERVICE CHARGE | D40: 500-BFSC | E40: =SUMIF($BA$6:$BL$6,$E$6,$BA40:$BL40) -> 0 | F40: =SUMIF($AH$6:$AS$6,$F$6,$AH40:$AS40) -> 0 | G40: =IFERROR((E40-F40)/F40,0) -> 0 | H40: =SUMIF($BN$6:$BR$6,$H$6,$BN40:$BR40) -> 0 | I40: =SUMIF($AU$6:$AY$6,$I$6,$AU40:$AY40) -> 0 | J40: =IFERROR((H40-I40)/I40,0) -> 0 | K40: =BM40 -> 0 | L40: =SUM(AH40:AM40) -> 0 | M40: =IFERROR((K40-L40)/L40,0) -> 0 | O40: =SUMIF('2024 AC'!$B$3:$B$250,"*"&$D40&"*",'2024 AC'!C$3:C$250) -> 0 | P40: =SUMIF('2024 AC'!$B$3:$B$250,"*"&$D40&"*",'2024 AC'!D$3:D$250) -> 0 | Q40: =SUMIF('2024 AC'!$B$3:$B$250,"*"&$D40&"*",'2024 AC'!E$3:E$250) -> 0 | R40: =SUMIF('2024 AC'!$B$3:$B$250,"*"&$D40&"*",'2024 AC'!F$3:F$250) -> 0 | S40: =SUMIF('2024 AC'!$B$3:$B$250,"*"&$D40&"*",'2024 AC'!G$3:G$250) -> 0 | T40: =SUMIF('2024 AC'!$B$3:$B$250,"*"&$D40&"*",'2024 AC'!H$3:H$250) -> 0 | U40: =SUMIF('2024 AC'!$B$3:$B$250,"*"&$D40&"*",'2024 AC'!I$3:I$250) -> 0 | V40: =SUMIF('2024 AC'!$B$3:$B$250,"*"&$D40&"*",'2024 AC'!J$3:J$250) -> 0 | ... Z40: =SUMIF('2024 AC'!$B$3:$B$250,"*"&$D40&"*",'2024 AC'!N$3:N$250) -> 0 | AA40: =SUM(O40:Z40) -> 0 | AB40: =SUM(O40:Q40) -> 0 | AC40: =SUM(R40:T40) -> 0 | AD40: =SUM(U40:W40) -> 0 | AE40: =SUM(X40:Z40) -> 0 | AF40: =SUM(AB40:AE40) -> 0 | AH40: =SUMIF('2025 AC'!$B$3:$B$250,"*"&$D40&"*",'2025 AC'!C$3:C$250) -> 0 | AI40: =SUMIF('2025 AC'!$B$3:$B$250,"*"&$D40&"*",'2025 AC'!D$3:D$250) -> 0 | AJ40: =SUMIF('2025 AC'!$B$3:$B$250,"*"&$D40&"*",'2025 AC'!E$3:E$250) -> 0 | AK40: =SUMIF('2025 AC'!$B$3:$B$250,"*"&$D40&"*",'2025 AC'!F$3:F$250) -> 0 | AL40: =SUMIF('2025 AC'!$B$3:$B$250,"*"&$D40&"*",'2025 AC'!G$3:G$250) -> 0 | AM40: =SUMIF('2025 AC'!$B$3:$B$250,"*"&$D40&"*",'2025 AC'!H$3:H$250) -> 0 | AN40: =SUMIF('2025 AC'!$B$3:$B$250,"*"&$D40&"*",'2025 AC'!I$3:I$250) -> 0 | AO40: =SUMIF('2025 AC'!$B$3:$B$250,"*"&$D40&"*",'2025 AC'!J$3:J$250) -> 0 | ... AS40: =SUMIF('2025 AC'!$B$3:$B$250,"*"&$D40&"*",'2025 AC'!N$3:N$250) -> 0 | AT40: =SUM(AH40:AS40) -> 0 | AU40: =SUM(AH40:AJ40) -> 0 | AV40: =SUM(AK40:AM40) -> 0 | AW40: =SUM(AN40:AP40) -> 0 | AX40: =SUM(AQ40:AS40) -> 0 | AY40: =SUM(AU40:AX40) -> 0 | BA40: =SUMIF('2026 AC'!$B$3:$B$254,"*"&$D40&"*",'2026 AC'!C$3:C$254) -> 0 | BB40: =SUMIF('2026 AC'!$B$3:$B$254,"*"&$D40&"*",'2026 AC'!D$3:D$254) -> 0 | BC40: =SUMIF('2026 AC'!$B$3:$B$254,"*"&$D40&"*",'2026 AC'!E$3:E$254) -> 0 | BD40: =SUMIF('2026 AC'!$B$3:$B$254,"*"&$D40&"*",'2026 AC'!F$3:F$254) -> 0 | BE40: =SUMIF('2026 AC'!$B$3:$B$254,"*"&$D40&"*",'2026 AC'!G$3:G$254) -> 0 | BF40: =SUMIF('2026 AC'!$B$3:$B$254,"*"&$D40&"*",'2026 AC'!H$3:H$254) -> 0 | BG40: =SUMIF('2026 AC'!$B$3:$B$254,"*"&$D40&"*",'2026 AC'!I$3:I$254) -> 0 | BH40: =SUMIF('2026 AC'!$B$3:$B$254,"*"&$D40&"*",'2026 AC'!J$3:J$254) -> 0 | ... BL40: =SUMIF('2026 AC'!$B$3:$B$254,"*"&$D40&"*",'2026 AC'!N$3:N$254) -> 0 | BM40: =SUM(BA40:BL40) -> 0 | BN40: =SUM(BA40:BC40) -> 0 | BO40: =SUM(BD40:BF40) -> 0 | BP40: =SUM(BG40:BI40) -> 0 | BQ40: =SUM(BJ40:BL40) -> 0 | BR40: =SUM(BN40:BQ40) -> 0
A41: G3 F&B | B41: 500-G301 | C41: G3 F&B* | D41: 500-G301 | E41: =SUMIF($BA$6:$BL$6,$E$6,$BA41:$BL41) -> 0 | F41: =SUMIF($AH$6:$AS$6,$F$6,$AH41:$AS41) -> 0 | G41: =IFERROR((E41-F41)/F41,0) -> 0 | H41: =SUMIF($BN$6:$BR$6,$H$6,$BN41:$BR41) -> 0 | I41: =SUMIF($AU$6:$AY$6,$I$6,$AU41:$AY41) -> 0 | J41: =IFERROR((H41-I41)/I41,0) -> 0 | K41: =BM41 -> 0 | L41: =SUM(AH41:AM41) -> 0 | M41: =IFERROR((K41-L41)/L41,0) -> 0 | O41: =SUMIF('2024 AC'!$B$3:$B$250,"*"&$D41&"*",'2024 AC'!C$3:C$250) -> 23782.01 | P41: =SUMIF('2024 AC'!$B$3:$B$250,"*"&$D41&"*",'2024 AC'!D$3:D$250) -> 27010.69 | Q41: =SUMIF('2024 AC'!$B$3:$B$250,"*"&$D41&"*",'2024 AC'!E$3:E$250) -> 23209.67 | R41: =SUMIF('2024 AC'!$B$3:$B$250,"*"&$D41&"*",'2024 AC'!F$3:F$250) -> 25166.68 | S41: =SUMIF('2024 AC'!$B$3:$B$250,"*"&$D41&"*",'2024 AC'!G$3:G$250) -> 30536.72 | T41: =SUMIF('2024 AC'!$B$3:$B$250,"*"&$D41&"*",'2024 AC'!H$3:H$250) -> 23923.83 | U41: =SUMIF('2024 AC'!$B$3:$B$250,"*"&$D41&"*",'2024 AC'!I$3:I$250) -> 21747.26 | V41: =SUMIF('2024 AC'!$B$3:$B$250,"*"&$D41&"*",'2024 AC'!J$3:J$250) -> 28948.41 | ... Z41: =SUMIF('2024 AC'!$B$3:$B$250,"*"&$D41&"*",'2024 AC'!N$3:N$250) -> 0 | AA41: =SUM(O41:Z41) -> 213460.37 | AB41: =SUM(O41:Q41) -> 74002.37 | AC41: =SUM(R41:T41) -> 79627.23 | AD41: =SUM(U41:W41) -> 59830.77 | AE41: =SUM(X41:Z41) -> 0 | AF41: =SUM(AB41:AE41) -> 213460.37 | AH41: =SUMIF('2025 AC'!$B$3:$B$250,"*"&$D41&"*",'2025 AC'!C$3:C$250) -> 0 | AI41: =SUMIF('2025 AC'!$B$3:$B$250,"*"&$D41&"*",'2025 AC'!D$3:D$250) -> 0 | AJ41: =SUMIF('2025 AC'!$B$3:$B$250,"*"&$D41&"*",'2025 AC'!E$3:E$250) -> 0 | AK41: =SUMIF('2025 AC'!$B$3:$B$250,"*"&$D41&"*",'2025 AC'!F$3:F$250) -> 0 | AL41: =SUMIF('2025 AC'!$B$3:$B$250,"*"&$D41&"*",'2025 AC'!G$3:G$250) -> 0 | AM41: =SUMIF('2025 AC'!$B$3:$B$250,"*"&$D41&"*",'2025 AC'!H$3:H$250) -> 0 | AN41: =SUMIF('2025 AC'!$B$3:$B$250,"*"&$D41&"*",'2025 AC'!I$3:I$250) -> 0 | AO41: =SUMIF('2025 AC'!$B$3:$B$250,"*"&$D41&"*",'2025 AC'!J$3:J$250) -> 0 | ... AS41: =SUMIF('2025 AC'!$B$3:$B$250,"*"&$D41&"*",'2025 AC'!N$3:N$250) -> 0 | AT41: =SUM(AH41:AS41) -> 0 | AU41: =SUM(AH41:AJ41) -> 0 | AV41: =SUM(AK41:AM41) -> 0 | AW41: =SUM(AN41:AP41) -> 0 | AX41: =SUM(AQ41:AS41) -> 0 | AY41: =SUM(AU41:AX41) -> 0 | BA41: =SUMIF('2026 AC'!$B$3:$B$254,"*"&$D41&"*",'2026 AC'!C$3:C$254) -> 0 | BB41: =SUMIF('2026 AC'!$B$3:$B$254,"*"&$D41&"*",'2026 AC'!D$3:D$254) -> 0 | BC41: =SUMIF('2026 AC'!$B$3:$B$254,"*"&$D41&"*",'2026 AC'!E$3:E$254) -> 0 | BD41: =SUMIF('2026 AC'!$B$3:$B$254,"*"&$D41&"*",'2026 AC'!F$3:F$254) -> 0 | BE41: =SUMIF('2026 AC'!$B$3:$B$254,"*"&$D41&"*",'2026 AC'!G$3:G$254) -> 0 | BF41: =SUMIF('2026 AC'!$B$3:$B$254,"*"&$D41&"*",'2026 AC'!H$3:H$254) -> 0 | BG41: =SUMIF('2026 AC'!$B$3:$B$254,"*"&$D41&"*",'2026 AC'!I$3:I$254) -> 0 | BH41: =SUMIF('2026 AC'!$B$3:$B$254,"*"&$D41&"*",'2026 AC'!J$3:J$254) -> 0 | ... BL41: =SUMIF('2026 AC'!$B$3:$B$254,"*"&$D41&"*",'2026 AC'!N$3:N$254) -> 0 | BM41: =SUM(BA41:BL41) -> 0 | BN41: =SUM(BA41:BC41) -> 0 | BO41: =SUM(BD41:BF41) -> 0 | BP41: =SUM(BG41:BI41) -> 0 | BQ41: =SUM(BJ41:BL41) -> 0 | BR41: =SUM(BN41:BQ41) -> 0
A42: G3 SERVICE CHARGE | B42: 500-G3SC | C42: G3 SERVICE CHARGE | D42: 500-G3SC | E42: =SUMIF($BA$6:$BL$6,$E$6,$BA42:$BL42) -> 0 | F42: =SUMIF($AH$6:$AS$6,$F$6,$AH42:$AS42) -> 0 | G42: =IFERROR((E42-F42)/F42,0) -> 0 | H42: =SUMIF($BN$6:$BR$6,$H$6,$BN42:$BR42) -> 0 | I42: =SUMIF($AU$6:$AY$6,$I$6,$AU42:$AY42) -> 0 | J42: =IFERROR((H42-I42)/I42,0) -> 0 | K42: =BM42 -> 0 | L42: =SUM(AH42:AM42) -> 0 | M42: =IFERROR((K42-L42)/L42,0) -> 0 | O42: =SUMIF('2024 AC'!$B$3:$B$250,"*"&$D42&"*",'2024 AC'!C$3:C$250) -> 0 | P42: =SUMIF('2024 AC'!$B$3:$B$250,"*"&$D42&"*",'2024 AC'!D$3:D$250) -> 0 | Q42: =SUMIF('2024 AC'!$B$3:$B$250,"*"&$D42&"*",'2024 AC'!E$3:E$250) -> 0 | R42: =SUMIF('2024 AC'!$B$3:$B$250,"*"&$D42&"*",'2024 AC'!F$3:F$250) -> 0 | S42: =SUMIF('2024 AC'!$B$3:$B$250,"*"&$D42&"*",'2024 AC'!G$3:G$250) -> 0 | T42: =SUMIF('2024 AC'!$B$3:$B$250,"*"&$D42&"*",'2024 AC'!H$3:H$250) -> 0 | U42: =SUMIF('2024 AC'!$B$3:$B$250,"*"&$D42&"*",'2024 AC'!I$3:I$250) -> 0 | V42: =SUMIF('2024 AC'!$B$3:$B$250,"*"&$D42&"*",'2024 AC'!J$3:J$250) -> 0 | ... Z42: =SUMIF('2024 AC'!$B$3:$B$250,"*"&$D42&"*",'2024 AC'!N$3:N$250) -> 0 | AA42: =SUM(O42:Z42) -> 0 | AB42: =SUM(O42:Q42) -> 0 | AC42: =SUM(R42:T42) -> 0 | AD42: =SUM(U42:W42) -> 0 | AE42: =SUM(X42:Z42) -> 0 | AF42: =SUM(AB42:AE42) -> 0 | AH42: =SUMIF('2025 AC'!$B$3:$B$250,"*"&$D42&"*",'2025 AC'!C$3:C$250) -> 0 | AI42: =SUMIF('2025 AC'!$B$3:$B$250,"*"&$D42&"*",'2025 AC'!D$3:D$250) -> 0 | AJ42: =SUMIF('2025 AC'!$B$3:$B$250,"*"&$D42&"*",'2025 AC'!E$3:E$250) -> 0 | AK42: =SUMIF('2025 AC'!$B$3:$B$250,"*"&$D42&"*",'2025 AC'!F$3:F$250) -> 0 | AL42: =SUMIF('2025 AC'!$B$3:$B$250,"*"&$D42&"*",'2025 AC'!G$3:G$250) -> 0 | AM42: =SUMIF('2025 AC'!$B$3:$B$250,"*"&$D42&"*",'2025 AC'!H$3:H$250) -> 0 | AN42: =SUMIF('2025 AC'!$B$3:$B$250,"*"&$D42&"*",'2025 AC'!I$3:I$250) -> 0 | AO42: =SUMIF('2025 AC'!$B$3:$B$250,"*"&$D42&"*",'2025 AC'!J$3:J$250) -> 0 | ... AS42: =SUMIF('2025 AC'!$B$3:$B$250,"*"&$D42&"*",'2025 AC'!N$3:N$250) -> 0 | AT42: =SUM(AH42:AS42) -> 0 | AU42: =SUM(AH42:AJ42) -> 0 | AV42: =SUM(AK42:AM42) -> 0 | AW42: =SUM(AN42:AP42) -> 0 | AX42: =SUM(AQ42:AS42) -> 0 | AY42: =SUM(AU42:AX42) -> 0 | BA42: =SUMIF('2026 AC'!$B$3:$B$254,"*"&$D42&"*",'2026 AC'!C$3:C$254) -> 0 | BB42: =SUMIF('2026 AC'!$B$3:$B$254,"*"&$D42&"*",'2026 AC'!D$3:D$254) -> 0 | BC42: =SUMIF('2026 AC'!$B$3:$B$254,"*"&$D42&"*",'2026 AC'!E$3:E$254) -> 0 | BD42: =SUMIF('2026 AC'!$B$3:$B$254,"*"&$D42&"*",'2026 AC'!F$3:F$254) -> 0 | BE42: =SUMIF('2026 AC'!$B$3:$B$254,"*"&$D42&"*",'2026 AC'!G$3:G$254) -> 0 | BF42: =SUMIF('2026 AC'!$B$3:$B$254,"*"&$D42&"*",'2026 AC'!H$3:H$254) -> 0 | BG42: =SUMIF('2026 AC'!$B$3:$B$254,"*"&$D42&"*",'2026 AC'!I$3:I$254) -> 0 | BH42: =SUMIF('2026 AC'!$B$3:$B$254,"*"&$D42&"*",'2026 AC'!J$3:J$254) -> 0 | ... BL42: =SUMIF('2026 AC'!$B$3:$B$254,"*"&$D42&"*",'2026 AC'!N$3:N$254) -> 0 | BM42: =SUM(BA42:BL42) -> 0 | BN42: =SUM(BA42:BC42) -> 0 | BO42: =SUM(BD42:BF42) -> 0 | BP42: =SUM(BG42:BI42) -> 0 | BQ42: =SUM(BJ42:BL42) -> 0 | BR42: =SUM(BN42:BQ42) -> 0
A43: SR F&B | B43: 500-SR01 | C43: SR F&B* | D43: 500-SR01 | E43: =SUMIF($BA$6:$BL$6,$E$6,$BA43:$BL43) -> 8834.33 | F43: =SUMIF($AH$6:$AS$6,$F$6,$AH43:$AS43) -> 1994.97 | G43: =(E43-F43)/F43 -> 3.4283022 | H43: =SUMIF($BN$6:$BR$6,$H$6,$BN43:$BR43) -> 19355.95 | I43: =SUMIF($AU$6:$AY$6,$I$6,$AU43:$AY43) -> 12511.7 | J43: =(H43-I43)/I43 -> 0.54702798 | K43: =BM43 -> 154012.55 | L43: =SUM(AH43:AM43) -> 174811.08 | M43: =(K43-L43)/L43 -> -0.11897718 | O43: =SUMIF('2024 AC'!$B$3:$B$250,"*"&$D43&"*",'2024 AC'!C$3:C$250) -> 413.18 | P43: =SUMIF('2024 AC'!$B$3:$B$250,"*"&$D43&"*",'2024 AC'!D$3:D$250) -> 434.88 | Q43: =SUMIF('2024 AC'!$B$3:$B$250,"*"&$D43&"*",'2024 AC'!E$3:E$250) -> 71659.92 | R43: =SUMIF('2024 AC'!$B$3:$B$250,"*"&$D43&"*",'2024 AC'!F$3:F$250) -> 42905.83 | S43: =SUMIF('2024 AC'!$B$3:$B$250,"*"&$D43&"*",'2024 AC'!G$3:G$250) -> 820 | T43: =SUMIF('2024 AC'!$B$3:$B$250,"*"&$D43&"*",'2024 AC'!H$3:H$250) -> 2068.96 | U43: =SUMIF('2024 AC'!$B$3:$B$250,"*"&$D43&"*",'2024 AC'!I$3:I$250) -> 297.15 | V43: =SUMIF('2024 AC'!$B$3:$B$250,"*"&$D43&"*",'2024 AC'!J$3:J$250) -> 84.9 | ... Z43: =SUMIF('2024 AC'!$B$3:$B$250,"*"&$D43&"*",'2024 AC'!N$3:N$250) -> 5855.13 | AA43: =SUM(O43:Z43) -> 124558.82 | AB43: =SUM(O43:Q43) -> 72507.98 | AC43: =SUM(R43:T43) -> 45794.79 | AD43: =SUM(U43:W43) -> 400.92 | AE43: =SUM(X43:Z43) -> 5855.13 | AF43: =SUM(AB43:AE43) -> 124558.82 | AH43: =SUMIF('2025 AC'!$B$3:$B$250,"*"&$D43&"*",'2025 AC'!C$3:C$250) -> 0 | AI43: =SUMIF('2025 AC'!$B$3:$B$250,"*"&$D43&"*",'2025 AC'!D$3:D$250) -> 2000 | AJ43: =SUMIF('2025 AC'!$B$3:$B$250,"*"&$D43&"*",'2025 AC'!E$3:E$250) -> 160299.38 | AK43: =SUMIF('2025 AC'!$B$3:$B$250,"*"&$D43&"*",'2025 AC'!F$3:F$250) -> 7509.66 | AL43: =SUMIF('2025 AC'!$B$3:$B$250,"*"&$D43&"*",'2025 AC'!G$3:G$250) -> 3007.07 | AM43: =SUMIF('2025 AC'!$B$3:$B$250,"*"&$D43&"*",'2025 AC'!H$3:H$250) -> 1994.97 | AN43: =SUMIF('2025 AC'!$B$3:$B$250,"*"&$D43&"*",'2025 AC'!I$3:I$250) -> 2277.9 | AO43: =SUMIF('2025 AC'!$B$3:$B$250,"*"&$D43&"*",'2025 AC'!J$3:J$250) -> 4739.85 | ... AS43: =SUMIF('2025 AC'!$B$3:$B$250,"*"&$D43&"*",'2025 AC'!N$3:N$250) -> 8258.9 | AT43: =SUM(AH43:AS43) -> 205735.2 | AU43: =SUM(AH43:AJ43) -> 162299.38 | AV43: =SUM(AK43:AM43) -> 12511.7 | AW43: =SUM(AN43:AP43) -> 15251.47 | AX43: =SUM(AQ43:AS43) -> 15672.65 | AY43: =SUM(AU43:AX43) -> 205735.2 | BA43: =SUMIF('2026 AC'!$B$3:$B$254,"*"&$D43&"*",'2026 AC'!C$3:C$254) -> 12187.13 | BB43: =SUMIF('2026 AC'!$B$3:$B$254,"*"&$D43&"*",'2026 AC'!D$3:D$254) -> 20979.76 | BC43: =SUMIF('2026 AC'!$B$3:$B$254,"*"&$D43&"*",'2026 AC'!E$3:E$254) -> 101489.71 | BD43: =SUMIF('2026 AC'!$B$3:$B$254,"*"&$D43&"*",'2026 AC'!F$3:F$254) -> 4494.45 | BE43: =SUMIF('2026 AC'!$B$3:$B$254,"*"&$D43&"*",'2026 AC'!G$3:G$254) -> 6027.17 | BF43: =SUMIF('2026 AC'!$B$3:$B$254,"*"&$D43&"*",'2026 AC'!H$3:H$254) -> 8834.33 | BG43: =SUMIF('2026 AC'!$B$3:$B$254,"*"&$D43&"*",'2026 AC'!I$3:I$254) -> 0 | BH43: =SUMIF('2026 AC'!$B$3:$B$254,"*"&$D43&"*",'2026 AC'!J$3:J$254) -> 0 | ... BL43: =SUMIF('2026 AC'!$B$3:$B$254,"*"&$D43&"*",'2026 AC'!N$3:N$254) -> 0 | BM43: =SUM(BA43:BL43) -> 154012.55 | BN43: =SUM(BA43:BC43) -> 134656.6 | BO43: =SUM(BD43:BF43) -> 19355.95 | BP43: =SUM(BG43:BI43) -> 0 | BQ43: =SUM(BJ43:BL43) -> 0 | BR43: =SUM(BN43:BQ43) -> 154012.55
A44: SR SERVICE CHARGE | B44: 500-SRSC | C44: SR SERVICE CHARGE | D44: 500-SRSC | E44: =SUMIF($BA$6:$BL$6,$E$6,$BA44:$BL44) -> 0 | F44: =SUMIF($AH$6:$AS$6,$F$6,$AH44:$AS44) -> 0 | G44: =IFERROR((E44-F44)/F44,0) -> 0 | H44: =SUMIF($BN$6:$BR$6,$H$6,$BN44:$BR44) -> 0 | I44: =SUMIF($AU$6:$AY$6,$I$6,$AU44:$AY44) -> 0 | J44: =IFERROR((H44-I44)/I44,0) -> 0 | K44: =BM44 -> 0 | L44: =SUM(AH44:AM44) -> 0 | M44: =IFERROR((K44-L44)/L44,0) -> 0 | O44: =SUMIF('2024 AC'!$B$3:$B$250,"*"&$D44&"*",'2024 AC'!C$3:C$250) -> 0 | P44: =SUMIF('2024 AC'!$B$3:$B$250,"*"&$D44&"*",'2024 AC'!D$3:D$250) -> 0 | Q44: =SUMIF('2024 AC'!$B$3:$B$250,"*"&$D44&"*",'2024 AC'!E$3:E$250) -> 0 | R44: =SUMIF('2024 AC'!$B$3:$B$250,"*"&$D44&"*",'2024 AC'!F$3:F$250) -> 0 | S44: =SUMIF('2024 AC'!$B$3:$B$250,"*"&$D44&"*",'2024 AC'!G$3:G$250) -> 0 | T44: =SUMIF('2024 AC'!$B$3:$B$250,"*"&$D44&"*",'2024 AC'!H$3:H$250) -> 0 | U44: =SUMIF('2024 AC'!$B$3:$B$250,"*"&$D44&"*",'2024 AC'!I$3:I$250) -> 0 | V44: =SUMIF('2024 AC'!$B$3:$B$250,"*"&$D44&"*",'2024 AC'!J$3:J$250) -> 0 | ... Z44: =SUMIF('2024 AC'!$B$3:$B$250,"*"&$D44&"*",'2024 AC'!N$3:N$250) -> 0 | AA44: =SUM(O44:Z44) -> 0 | AB44: =SUM(O44:Q44) -> 0 | AC44: =SUM(R44:T44) -> 0 | AD44: =SUM(U44:W44) -> 0 | AE44: =SUM(X44:Z44) -> 0 | AF44: =SUM(AB44:AE44) -> 0 | AH44: =SUMIF('2025 AC'!$B$3:$B$250,"*"&$D44&"*",'2025 AC'!C$3:C$250) -> 0 | AI44: =SUMIF('2025 AC'!$B$3:$B$250,"*"&$D44&"*",'2025 AC'!D$3:D$250) -> 0 | AJ44: =SUMIF('2025 AC'!$B$3:$B$250,"*"&$D44&"*",'2025 AC'!E$3:E$250) -> 0 | AK44: =SUMIF('2025 AC'!$B$3:$B$250,"*"&$D44&"*",'2025 AC'!F$3:F$250) -> 0 | AL44: =SUMIF('2025 AC'!$B$3:$B$250,"*"&$D44&"*",'2025 AC'!G$3:G$250) -> 0 | AM44: =SUMIF('2025 AC'!$B$3:$B$250,"*"&$D44&"*",'2025 AC'!H$3:H$250) -> 0 | AN44: =SUMIF('2025 AC'!$B$3:$B$250,"*"&$D44&"*",'2025 AC'!I$3:I$250) -> 0 | AO44: =SUMIF('2025 AC'!$B$3:$B$250,"*"&$D44&"*",'2025 AC'!J$3:J$250) -> 0 | ... AS44: =SUMIF('2025 AC'!$B$3:$B$250,"*"&$D44&"*",'2025 AC'!N$3:N$250) -> 0 | AT44: =SUM(AH44:AS44) -> 0 | AU44: =SUM(AH44:AJ44) -> 0 | AV44: =SUM(AK44:AM44) -> 0 | AW44: =SUM(AN44:AP44) -> 0 | AX44: =SUM(AQ44:AS44) -> 0 | AY44: =SUM(AU44:AX44) -> 0 | BA44: =SUMIF('2026 AC'!$B$3:$B$254,"*"&$D44&"*",'2026 AC'!C$3:C$254) -> 0 | BB44: =SUMIF('2026 AC'!$B$3:$B$254,"*"&$D44&"*",'2026 AC'!D$3:D$254) -> 0 | BC44: =SUMIF('2026 AC'!$B$3:$B$254,"*"&$D44&"*",'2026 AC'!E$3:E$254) -> 0 | BD44: =SUMIF('2026 AC'!$B$3:$B$254,"*"&$D44&"*",'2026 AC'!F$3:F$254) -> 0 | BE44: =SUMIF('2026 AC'!$B$3:$B$254,"*"&$D44&"*",'2026 AC'!G$3:G$254) -> 0 | BF44: =SUMIF('2026 AC'!$B$3:$B$254,"*"&$D44&"*",'2026 AC'!H$3:H$254) -> 0 | BG44: =SUMIF('2026 AC'!$B$3:$B$254,"*"&$D44&"*",'2026 AC'!I$3:I$254) -> 0 | BH44: =SUMIF('2026 AC'!$B$3:$B$254,"*"&$D44&"*",'2026 AC'!J$3:J$254) -> 0 | ... BL44: =SUMIF('2026 AC'!$B$3:$B$254,"*"&$D44&"*",'2026 AC'!N$3:N$254) -> 0 | BM44: =SUM(BA44:BL44) -> 0 | BN44: =SUM(BA44:BC44) -> 0 | BO44: =SUM(BD44:BF44) -> 0 | BP44: =SUM(BG44:BI44) -> 0 | BQ44: =SUM(BJ44:BL44) -> 0 | BR44: =SUM(BN44:BQ44) -> 0
A45: BANQUET CHARGE | B45: 500-3000 | C45: BANQUET CHARGE | D45: 500-3000 | E45: =SUMIF($BA$6:$BL$6,$E$6,$BA45:$BL45) -> 57628.85 | F45: =SUMIF($AH$6:$AS$6,$F$6,$AH45:$AS45) -> 73202.38 | G45: =(E45-F45)/F45 -> -0.21274622 | H45: =SUMIF($BN$6:$BR$6,$H$6,$BN45:$BR45) -> 169802.74 | I45: =SUMIF($AU$6:$AY$6,$I$6,$AU45:$AY45) -> 242502.59 | J45: =(H45-I45)/I45 -> -0.29978999 | K45: =BM45 -> 305507.04 | L45: =SUM(AH45:AM45) -> 358765.43 | M45: =(K45-L45)/L45 -> -0.14844906 | O45: =SUMIF('2024 AC'!$B$3:$B$250,"*"&$D45&"*",'2024 AC'!C$3:C$250) -> 71987.21 | P45: =SUMIF('2024 AC'!$B$3:$B$250,"*"&$D45&"*",'2024 AC'!D$3:D$250) -> 87343.13 | Q45: =SUMIF('2024 AC'!$B$3:$B$250,"*"&$D45&"*",'2024 AC'!E$3:E$250) -> 32957.64 | R45: =SUMIF('2024 AC'!$B$3:$B$250,"*"&$D45&"*",'2024 AC'!F$3:F$250) -> 55593.21 | S45: =SUMIF('2024 AC'!$B$3:$B$250,"*"&$D45&"*",'2024 AC'!G$3:G$250) -> 119618.68 | T45: =SUMIF('2024 AC'!$B$3:$B$250,"*"&$D45&"*",'2024 AC'!H$3:H$250) -> 78987.38 | U45: =SUMIF('2024 AC'!$B$3:$B$250,"*"&$D45&"*",'2024 AC'!I$3:I$250) -> 48453.39 | V45: =SUMIF('2024 AC'!$B$3:$B$250,"*"&$D45&"*",'2024 AC'!J$3:J$250) -> 157775.54 | ... Z45: =SUMIF('2024 AC'!$B$3:$B$250,"*"&$D45&"*",'2024 AC'!N$3:N$250) -> 45184.38 | AA45: =SUM(O45:Z45) -> 949040.62 | AB45: =SUM(O45:Q45) -> 192287.98 | AC45: =SUM(R45:T45) -> 254199.27 | AD45: =SUM(U45:W45) -> 264084.94 | AE45: =SUM(X45:Z45) -> 238468.43 | AF45: =SUM(AB45:AE45) -> 949040.62 | AH45: =SUMIF('2025 AC'!$B$3:$B$250,"*"&$D45&"*",'2025 AC'!C$3:C$250) -> 64669.56 | AI45: =SUMIF('2025 AC'!$B$3:$B$250,"*"&$D45&"*",'2025 AC'!D$3:D$250) -> 44771.24 | AJ45: =SUMIF('2025 AC'!$B$3:$B$250,"*"&$D45&"*",'2025 AC'!E$3:E$250) -> 6822.04 | AK45: =SUMIF('2025 AC'!$B$3:$B$250,"*"&$D45&"*",'2025 AC'!F$3:F$250) -> 51250.08 | AL45: =SUMIF('2025 AC'!$B$3:$B$250,"*"&$D45&"*",'2025 AC'!G$3:G$250) -> 118050.13 | AM45: =SUMIF('2025 AC'!$B$3:$B$250,"*"&$D45&"*",'2025 AC'!H$3:H$250) -> 73202.38 | AN45: =SUMIF('2025 AC'!$B$3:$B$250,"*"&$D45&"*",'2025 AC'!I$3:I$250) -> 86079.94 | AO45: =SUMIF('2025 AC'!$B$3:$B$250,"*"&$D45&"*",'2025 AC'!J$3:J$250) -> 92604.25 | ... AS45: =SUMIF('2025 AC'!$B$3:$B$250,"*"&$D45&"*",'2025 AC'!N$3:N$250) -> 67672.14 | AT45: =SUM(AH45:AS45) -> 903959.3 | AU45: =SUM(AH45:AJ45) -> 116262.84 | AV45: =SUM(AK45:AM45) -> 242502.59 | AW45: =SUM(AN45:AP45) -> 305014.84 | AX45: =SUM(AQ45:AS45) -> 240179.03 | AY45: =SUM(AU45:AX45) -> 903959.3 | BA45: =SUMIF('2026 AC'!$B$3:$B$254,"*"&$D45&"*",'2026 AC'!C$3:C$254) -> 45334.79 | BB45: =SUMIF('2026 AC'!$B$3:$B$254,"*"&$D45&"*",'2026 AC'!D$3:D$254) -> 43000.03 | BC45: =SUMIF('2026 AC'!$B$3:$B$254,"*"&$D45&"*",'2026 AC'!E$3:E$254) -> 47369.48 | BD45: =SUMIF('2026 AC'!$B$3:$B$254,"*"&$D45&"*",'2026 AC'!F$3:F$254) -> 79461.97 | BE45: =SUMIF('2026 AC'!$B$3:$B$254,"*"&$D45&"*",'2026 AC'!G$3:G$254) -> 32711.92 | BF45: =SUMIF('2026 AC'!$B$3:$B$254,"*"&$D45&"*",'2026 AC'!H$3:H$254) -> 57628.85 | BG45: =SUMIF('2026 AC'!$B$3:$B$254,"*"&$D45&"*",'2026 AC'!I$3:I$254) -> 0 | BH45: =SUMIF('2026 AC'!$B$3:$B$254,"*"&$D45&"*",'2026 AC'!J$3:J$254) -> 0 | ... BL45: =SUMIF('2026 AC'!$B$3:$B$254,"*"&$D45&"*",'2026 AC'!N$3:N$254) -> 0 | BM45: =SUM(BA45:BL45) -> 305507.04 | BN45: =SUM(BA45:BC45) -> 135704.3 | BO45: =SUM(BD45:BF45) -> 169802.74 | BP45: =SUM(BG45:BI45) -> 0 | BQ45: =SUM(BJ45:BL45) -> 0 | BR45: =SUM(BN45:BQ45) -> 305507.04
A46: BANQUET CHARGE | B46: 500-BQ01 | C46: BANQUET CHARGE | D46: 500-BQ01 | E46: =SUMIF($BA$6:$BL$6,$E$6,$BA46:$BL46) -> 0 | F46: =SUMIF($AH$6:$AS$6,$F$6,$AH46:$AS46) -> 73202.38 | G46: =(E46-F46)/F46 -> -1 | H46: =SUMIF($BN$6:$BR$6,$H$6,$BN46:$BR46) -> 0 | I46: =SUMIF($AU$6:$AY$6,$I$6,$AU46:$AY46) -> 242502.59 | J46: =(H46-I46)/I46 -> -1 | K46: =BM46 -> 0 | L46: =SUM(AH46:AM46) -> 358765.43 | M46: =(K46-L46)/L46 -> -1 | O46: =SUMIF('2024 AC'!$B$3:$B$250,"*"&$D46&"*",'2024 AC'!C$3:C$250) -> 71987.21 | P46: =SUMIF('2024 AC'!$B$3:$B$250,"*"&$D46&"*",'2024 AC'!D$3:D$250) -> 87343.13 | Q46: =SUMIF('2024 AC'!$B$3:$B$250,"*"&$D46&"*",'2024 AC'!E$3:E$250) -> 32957.64 | R46: =SUMIF('2024 AC'!$B$3:$B$250,"*"&$D46&"*",'2024 AC'!F$3:F$250) -> 55593.21 | S46: =SUMIF('2024 AC'!$B$3:$B$250,"*"&$D46&"*",'2024 AC'!G$3:G$250) -> 119618.68 | T46: =SUMIF('2024 AC'!$B$3:$B$250,"*"&$D46&"*",'2024 AC'!H$3:H$250) -> 78987.38 | U46: =SUMIF('2024 AC'!$B$3:$B$250,"*"&$D46&"*",'2024 AC'!I$3:I$250) -> 48453.39 | V46: =SUMIF('2024 AC'!$B$3:$B$250,"*"&$D46&"*",'2024 AC'!J$3:J$250) -> 157775.54 | ... Z46: =SUMIF('2024 AC'!$B$3:$B$250,"*"&$D46&"*",'2024 AC'!N$3:N$250) -> 45184.38 | AA46: =SUM(O46:Z46) -> 949040.62 | AB46: =SUM(O46:Q46) -> 192287.98 | AC46: =SUM(R46:T46) -> 254199.27 | AD46: =SUM(U46:W46) -> 264084.94 | AE46: =SUM(X46:Z46) -> 238468.43 | AF46: =SUM(AB46:AE46) -> 949040.62 | AH46: =SUMIF('2025 AC'!$B$3:$B$250,"*"&$D46&"*",'2025 AC'!C$3:C$250) -> 64669.56 | AI46: =SUMIF('2025 AC'!$B$3:$B$250,"*"&$D46&"*",'2025 AC'!D$3:D$250) -> 44771.24 | AJ46: =SUMIF('2025 AC'!$B$3:$B$250,"*"&$D46&"*",'2025 AC'!E$3:E$250) -> 6822.04 | AK46: =SUMIF('2025 AC'!$B$3:$B$250,"*"&$D46&"*",'2025 AC'!F$3:F$250) -> 51250.08 | AL46: =SUMIF('2025 AC'!$B$3:$B$250,"*"&$D46&"*",'2025 AC'!G$3:G$250) -> 118050.13 | AM46: =SUMIF('2025 AC'!$B$3:$B$250,"*"&$D46&"*",'2025 AC'!H$3:H$250) -> 73202.38 | AN46: =SUMIF('2025 AC'!$B$3:$B$250,"*"&$D46&"*",'2025 AC'!I$3:I$250) -> 86079.94 | AO46: =SUMIF('2025 AC'!$B$3:$B$250,"*"&$D46&"*",'2025 AC'!J$3:J$250) -> 92604.25 | ... AS46: =SUMIF('2025 AC'!$B$3:$B$250,"*"&$D46&"*",'2025 AC'!N$3:N$250) -> 67672.14 | AT46: =SUM(AH46:AS46) -> 903959.3 | AU46: =SUM(AH46:AJ46) -> 116262.84 | AV46: =SUM(AK46:AM46) -> 242502.59 | AW46: =SUM(AN46:AP46) -> 305014.84 | AX46: =SUM(AQ46:AS46) -> 240179.03 | AY46: =SUM(AU46:AX46) -> 903959.3 | BA46: =SUMIF('2026 AC'!$B$3:$B$254,"*"&$D46&"*",'2026 AC'!C$3:C$254) -> 0 | BB46: =SUMIF('2026 AC'!$B$3:$B$254,"*"&$D46&"*",'2026 AC'!D$3:D$254) -> 0 | BC46: =SUMIF('2026 AC'!$B$3:$B$254,"*"&$D46&"*",'2026 AC'!E$3:E$254) -> 0 | BD46: =SUMIF('2026 AC'!$B$3:$B$254,"*"&$D46&"*",'2026 AC'!F$3:F$254) -> 0 | BE46: =SUMIF('2026 AC'!$B$3:$B$254,"*"&$D46&"*",'2026 AC'!G$3:G$254) -> 0 | BF46: =SUMIF('2026 AC'!$B$3:$B$254,"*"&$D46&"*",'2026 AC'!H$3:H$254) -> 0 | BG46: =SUMIF('2026 AC'!$B$3:$B$254,"*"&$D46&"*",'2026 AC'!I$3:I$254) -> 0 | BH46: =SUMIF('2026 AC'!$B$3:$B$254,"*"&$D46&"*",'2026 AC'!J$3:J$254) -> 0 | ... BL46: =SUMIF('2026 AC'!$B$3:$B$254,"*"&$D46&"*",'2026 AC'!N$3:N$254) -> 0 | BM46: =SUM(BA46:BL46) -> 0 | BN46: =SUM(BA46:BC46) -> 0 | BO46: =SUM(BD46:BF46) -> 0 | BP46: =SUM(BG46:BI46) -> 0 | BQ46: =SUM(BJ46:BL46) -> 0 | BR46: =SUM(BN46:BQ46) -> 0
A47: BANQUET SERVICE CHARGE | B47: 500-BQSC | C47: BANQUET FOOD & BEV (PACKAGE)* | D47: 500-BQ02 | E47: =SUMIF($BA$6:$BL$6,$E$6,$BA47:$BL47) -> 29211.87 | F47: =SUMIF($AH$6:$AS$6,$F$6,$AH47:$AS47) -> 0 | G47: =IFERROR((E47-F47)/F47,0) -> 0 | H47: =SUMIF($BN$6:$BR$6,$H$6,$BN47:$BR47) -> 86580.55 | I47: =SUMIF($AU$6:$AY$6,$I$6,$AU47:$AY47) -> 0 | J47: =IFERROR((H47-I47)/I47,0) -> 0 | K47: =BM47 -> 167517.84 | L47: =SUM(AH47:AM47) -> 0 | M47: =IFERROR((K47-L47)/L47,0) -> 0 | O47: =SUMIF('2024 AC'!$B$3:$B$250,"*"&$D47&"*",'2024 AC'!C$3:C$250) -> 0 | P47: =SUMIF('2024 AC'!$B$3:$B$250,"*"&$D47&"*",'2024 AC'!D$3:D$250) -> 0 | Q47: =SUMIF('2024 AC'!$B$3:$B$250,"*"&$D47&"*",'2024 AC'!E$3:E$250) -> 0 | R47: =SUMIF('2024 AC'!$B$3:$B$250,"*"&$D47&"*",'2024 AC'!F$3:F$250) -> 0 | S47: =SUMIF('2024 AC'!$B$3:$B$250,"*"&$D47&"*",'2024 AC'!G$3:G$250) -> 0 | T47: =SUMIF('2024 AC'!$B$3:$B$250,"*"&$D47&"*",'2024 AC'!H$3:H$250) -> 0 | U47: =SUMIF('2024 AC'!$B$3:$B$250,"*"&$D47&"*",'2024 AC'!I$3:I$250) -> 0 | V47: =SUMIF('2024 AC'!$B$3:$B$250,"*"&$D47&"*",'2024 AC'!J$3:J$250) -> 0 | ... Z47: =SUMIF('2024 AC'!$B$3:$B$250,"*"&$D47&"*",'2024 AC'!N$3:N$250) -> 0 | AA47: =SUM(O47:Z47) -> 0 | AB47: =SUM(O47:Q47) -> 0 | AC47: =SUM(R47:T47) -> 0 | AD47: =SUM(U47:W47) -> 0 | AE47: =SUM(X47:Z47) -> 0 | AF47: =SUM(AB47:AE47) -> 0 | AH47: =SUMIF('2025 AC'!$B$3:$B$250,"*"&$D47&"*",'2025 AC'!C$3:C$250) -> 0 | AI47: =SUMIF('2025 AC'!$B$3:$B$250,"*"&$D47&"*",'2025 AC'!D$3:D$250) -> 0 | AJ47: =SUMIF('2025 AC'!$B$3:$B$250,"*"&$D47&"*",'2025 AC'!E$3:E$250) -> 0 | AK47: =SUMIF('2025 AC'!$B$3:$B$250,"*"&$D47&"*",'2025 AC'!F$3:F$250) -> 0 | AL47: =SUMIF('2025 AC'!$B$3:$B$250,"*"&$D47&"*",'2025 AC'!G$3:G$250) -> 0 | AM47: =SUMIF('2025 AC'!$B$3:$B$250,"*"&$D47&"*",'2025 AC'!H$3:H$250) -> 0 | AN47: =SUMIF('2025 AC'!$B$3:$B$250,"*"&$D47&"*",'2025 AC'!I$3:I$250) -> 0 | AO47: =SUMIF('2025 AC'!$B$3:$B$250,"*"&$D47&"*",'2025 AC'!J$3:J$250) -> 0 | ... AS47: =SUMIF('2025 AC'!$B$3:$B$250,"*"&$D47&"*",'2025 AC'!N$3:N$250) -> 0 | AT47: =SUM(AH47:AS47) -> 0 | AU47: =SUM(AH47:AJ47) -> 0 | AV47: =SUM(AK47:AM47) -> 0 | AW47: =SUM(AN47:AP47) -> 0 | AX47: =SUM(AQ47:AS47) -> 0 | AY47: =SUM(AU47:AX47) -> 0 | BA47: =SUMIF('2026 AC'!$B$3:$B$254,"*"&$D47&"*",'2026 AC'!C$3:C$254) -> 24135.6 | BB47: =SUMIF('2026 AC'!$B$3:$B$254,"*"&$D47&"*",'2026 AC'!D$3:D$254) -> 21631.36 | BC47: =SUMIF('2026 AC'!$B$3:$B$254,"*"&$D47&"*",'2026 AC'!E$3:E$254) -> 35170.33 | BD47: =SUMIF('2026 AC'!$B$3:$B$254,"*"&$D47&"*",'2026 AC'!F$3:F$254) -> 34766.97 | BE47: =SUMIF('2026 AC'!$B$3:$B$254,"*"&$D47&"*",'2026 AC'!G$3:G$254) -> 22601.71 | BF47: =SUMIF('2026 AC'!$B$3:$B$254,"*"&$D47&"*",'2026 AC'!H$3:H$254) -> 29211.87 | BG47: =SUMIF('2026 AC'!$B$3:$B$254,"*"&$D47&"*",'2026 AC'!I$3:I$254) -> 0 | BH47: =SUMIF('2026 AC'!$B$3:$B$254,"*"&$D47&"*",'2026 AC'!J$3:J$254) -> 0 | ... BL47: =SUMIF('2026 AC'!$B$3:$B$254,"*"&$D47&"*",'2026 AC'!N$3:N$254) -> 0 | BM47: =SUM(BA47:BL47) -> 167517.84 | BN47: =SUM(BA47:BC47) -> 80937.29 | BO47: =SUM(BD47:BF47) -> 86580.55 | BP47: =SUM(BG47:BI47) -> 0 | BQ47: =SUM(BJ47:BL47) -> 0 | BR47: =SUM(BN47:BQ47) -> 167517.84
A48: BANQUET SERVICE CHARGE | B48: 500-BQSC | C48: BANQUET EQUIPMENT RENTAL | D48: 500-BQ03 | E48: =SUMIF($BA$6:$BL$6,$E$6,$BA48:$BL48) -> 1271.23 | F48: =SUMIF($AH$6:$AS$6,$F$6,$AH48:$AS48) -> 0 | G48: =IFERROR((E48-F48)/F48,0) -> 0 | H48: =SUMIF($BN$6:$BR$6,$H$6,$BN48:$BR48) -> 3856.09 | I48: =SUMIF($AU$6:$AY$6,$I$6,$AU48:$AY48) -> 0 | J48: =IFERROR((H48-I48)/I48,0) -> 0 | K48: =BM48 -> 6101.94 | L48: =SUM(AH48:AM48) -> 0 | M48: =IFERROR((K48-L48)/L48,0) -> 0 | O48: =SUMIF('2024 AC'!$B$3:$B$250,"*"&$D48&"*",'2024 AC'!C$3:C$250) -> 0 | P48: =SUMIF('2024 AC'!$B$3:$B$250,"*"&$D48&"*",'2024 AC'!D$3:D$250) -> 0 | Q48: =SUMIF('2024 AC'!$B$3:$B$250,"*"&$D48&"*",'2024 AC'!E$3:E$250) -> 0 | R48: =SUMIF('2024 AC'!$B$3:$B$250,"*"&$D48&"*",'2024 AC'!F$3:F$250) -> 0 | S48: =SUMIF('2024 AC'!$B$3:$B$250,"*"&$D48&"*",'2024 AC'!G$3:G$250) -> 0 | T48: =SUMIF('2024 AC'!$B$3:$B$250,"*"&$D48&"*",'2024 AC'!H$3:H$250) -> 0 | U48: =SUMIF('2024 AC'!$B$3:$B$250,"*"&$D48&"*",'2024 AC'!I$3:I$250) -> 0 | V48: =SUMIF('2024 AC'!$B$3:$B$250,"*"&$D48&"*",'2024 AC'!J$3:J$250) -> 0 | ... Z48: =SUMIF('2024 AC'!$B$3:$B$250,"*"&$D48&"*",'2024 AC'!N$3:N$250) -> 0 | AA48: =SUM(O48:Z48) -> 0 | AB48: =SUM(O48:Q48) -> 0 | AC48: =SUM(R48:T48) -> 0 | AD48: =SUM(U48:W48) -> 0 | AE48: =SUM(X48:Z48) -> 0 | AF48: =SUM(AB48:AE48) -> 0 | AH48: =SUMIF('2025 AC'!$B$3:$B$250,"*"&$D48&"*",'2025 AC'!C$3:C$250) -> 0 | AI48: =SUMIF('2025 AC'!$B$3:$B$250,"*"&$D48&"*",'2025 AC'!D$3:D$250) -> 0 | AJ48: =SUMIF('2025 AC'!$B$3:$B$250,"*"&$D48&"*",'2025 AC'!E$3:E$250) -> 0 | AK48: =SUMIF('2025 AC'!$B$3:$B$250,"*"&$D48&"*",'2025 AC'!F$3:F$250) -> 0 | AL48: =SUMIF('2025 AC'!$B$3:$B$250,"*"&$D48&"*",'2025 AC'!G$3:G$250) -> 0 | AM48: =SUMIF('2025 AC'!$B$3:$B$250,"*"&$D48&"*",'2025 AC'!H$3:H$250) -> 0 | AN48: =SUMIF('2025 AC'!$B$3:$B$250,"*"&$D48&"*",'2025 AC'!I$3:I$250) -> 0 | AO48: =SUMIF('2025 AC'!$B$3:$B$250,"*"&$D48&"*",'2025 AC'!J$3:J$250) -> 0 | ... AS48: =SUMIF('2025 AC'!$B$3:$B$250,"*"&$D48&"*",'2025 AC'!N$3:N$250) -> 0 | AT48: =SUM(AH48:AS48) -> 0 | AU48: =SUM(AH48:AJ48) -> 0 | AV48: =SUM(AK48:AM48) -> 0 | AW48: =SUM(AN48:AP48) -> 0 | AX48: =SUM(AQ48:AS48) -> 0 | AY48: =SUM(AU48:AX48) -> 0 | BA48: =SUMIF('2026 AC'!$B$3:$B$254,"*"&$D48&"*",'2026 AC'!C$3:C$254) -> 1059.36 | BB48: =SUMIF('2026 AC'!$B$3:$B$254,"*"&$D48&"*",'2026 AC'!D$3:D$254) -> 635.62 | BC48: =SUMIF('2026 AC'!$B$3:$B$254,"*"&$D48&"*",'2026 AC'!E$3:E$254) -> 550.87 | BD48: =SUMIF('2026 AC'!$B$3:$B$254,"*"&$D48&"*",'2026 AC'!F$3:F$254) -> 1864.49 | BE48: =SUMIF('2026 AC'!$B$3:$B$254,"*"&$D48&"*",'2026 AC'!G$3:G$254) -> 720.37 | BF48: =SUMIF('2026 AC'!$B$3:$B$254,"*"&$D48&"*",'2026 AC'!H$3:H$254) -> 1271.23 | BG48: =SUMIF('2026 AC'!$B$3:$B$254,"*"&$D48&"*",'2026 AC'!I$3:I$254) -> 0 | BH48: =SUMIF('2026 AC'!$B$3:$B$254,"*"&$D48&"*",'2026 AC'!J$3:J$254) -> 0 | ... BL48: =SUMIF('2026 AC'!$B$3:$B$254,"*"&$D48&"*",'2026 AC'!N$3:N$254) -> 0 | BM48: =SUM(BA48:BL48) -> 6101.94 | BN48: =SUM(BA48:BC48) -> 2245.85 | BO48: =SUM(BD48:BF48) -> 3856.09 | BP48: =SUM(BG48:BI48) -> 0 | BQ48: =SUM(BJ48:BL48) -> 0 | BR48: =SUM(BN48:BQ48) -> 6101.94
A49: BANQUET SERVICE CHARGE | B49: 500-BQSC | C49: BANQUET HALL RENTAL | D49: 500-BQ04 | E49: =SUMIF($BA$6:$BL$6,$E$6,$BA49:$BL49) -> 27145.75 | F49: =SUMIF($AH$6:$AS$6,$F$6,$AH49:$AS49) -> 0 | G49: =IFERROR((E49-F49)/F49,0) -> 0 | H49: =SUMIF($BN$6:$BR$6,$H$6,$BN49:$BR49) -> 79366.1 | I49: =SUMIF($AU$6:$AY$6,$I$6,$AU49:$AY49) -> 0 | J49: =IFERROR((H49-I49)/I49,0) -> 0 | K49: =BM49 -> 131442.34 | L49: =SUM(AH49:AM49) -> 0 | M49: =IFERROR((K49-L49)/L49,0) -> 0 | O49: =SUMIF('2024 AC'!$B$3:$B$250,"*"&$D49&"*",'2024 AC'!C$3:C$250) -> 0 | P49: =SUMIF('2024 AC'!$B$3:$B$250,"*"&$D49&"*",'2024 AC'!D$3:D$250) -> 0 | Q49: =SUMIF('2024 AC'!$B$3:$B$250,"*"&$D49&"*",'2024 AC'!E$3:E$250) -> 0 | R49: =SUMIF('2024 AC'!$B$3:$B$250,"*"&$D49&"*",'2024 AC'!F$3:F$250) -> 0 | S49: =SUMIF('2024 AC'!$B$3:$B$250,"*"&$D49&"*",'2024 AC'!G$3:G$250) -> 0 | T49: =SUMIF('2024 AC'!$B$3:$B$250,"*"&$D49&"*",'2024 AC'!H$3:H$250) -> 0 | U49: =SUMIF('2024 AC'!$B$3:$B$250,"*"&$D49&"*",'2024 AC'!I$3:I$250) -> 0 | V49: =SUMIF('2024 AC'!$B$3:$B$250,"*"&$D49&"*",'2024 AC'!J$3:J$250) -> 0 | ... Z49: =SUMIF('2024 AC'!$B$3:$B$250,"*"&$D49&"*",'2024 AC'!N$3:N$250) -> 0 | AA49: =SUM(O49:Z49) -> 0 | AB49: =SUM(O49:Q49) -> 0 | AC49: =SUM(R49:T49) -> 0 | AD49: =SUM(U49:W49) -> 0 | AE49: =SUM(X49:Z49) -> 0 | AF49: =SUM(AB49:AE49) -> 0 | AH49: =SUMIF('2025 AC'!$B$3:$B$250,"*"&$D49&"*",'2025 AC'!C$3:C$250) -> 0 | AI49: =SUMIF('2025 AC'!$B$3:$B$250,"*"&$D49&"*",'2025 AC'!D$3:D$250) -> 0 | AJ49: =SUMIF('2025 AC'!$B$3:$B$250,"*"&$D49&"*",'2025 AC'!E$3:E$250) -> 0 | AK49: =SUMIF('2025 AC'!$B$3:$B$250,"*"&$D49&"*",'2025 AC'!F$3:F$250) -> 0 | AL49: =SUMIF('2025 AC'!$B$3:$B$250,"*"&$D49&"*",'2025 AC'!G$3:G$250) -> 0 | AM49: =SUMIF('2025 AC'!$B$3:$B$250,"*"&$D49&"*",'2025 AC'!H$3:H$250) -> 0 | AN49: =SUMIF('2025 AC'!$B$3:$B$250,"*"&$D49&"*",'2025 AC'!I$3:I$250) -> 0 | AO49: =SUMIF('2025 AC'!$B$3:$B$250,"*"&$D49&"*",'2025 AC'!J$3:J$250) -> 0 | ... AS49: =SUMIF('2025 AC'!$B$3:$B$250,"*"&$D49&"*",'2025 AC'!N$3:N$250) -> 0 | AT49: =SUM(AH49:AS49) -> 0 | AU49: =SUM(AH49:AJ49) -> 0 | AV49: =SUM(AK49:AM49) -> 0 | AW49: =SUM(AN49:AP49) -> 0 | AX49: =SUM(AQ49:AS49) -> 0 | AY49: =SUM(AU49:AX49) -> 0 | BA49: =SUMIF('2026 AC'!$B$3:$B$254,"*"&$D49&"*",'2026 AC'!C$3:C$254) -> 20139.83 | BB49: =SUMIF('2026 AC'!$B$3:$B$254,"*"&$D49&"*",'2026 AC'!D$3:D$254) -> 20733.05 | BC49: =SUMIF('2026 AC'!$B$3:$B$254,"*"&$D49&"*",'2026 AC'!E$3:E$254) -> 11203.36 | BD49: =SUMIF('2026 AC'!$B$3:$B$254,"*"&$D49&"*",'2026 AC'!F$3:F$254) -> 42830.51 | BE49: =SUMIF('2026 AC'!$B$3:$B$254,"*"&$D49&"*",'2026 AC'!G$3:G$254) -> 9389.84 | BF49: =SUMIF('2026 AC'!$B$3:$B$254,"*"&$D49&"*",'2026 AC'!H$3:H$254) -> 27145.75 | BG49: =SUMIF('2026 AC'!$B$3:$B$254,"*"&$D49&"*",'2026 AC'!I$3:I$254) -> 0 | BH49: =SUMIF('2026 AC'!$B$3:$B$254,"*"&$D49&"*",'2026 AC'!J$3:J$254) -> 0 | ... BL49: =SUMIF('2026 AC'!$B$3:$B$254,"*"&$D49&"*",'2026 AC'!N$3:N$254) -> 0 | BM49: =SUM(BA49:BL49) -> 131442.34 | BN49: =SUM(BA49:BC49) -> 52076.24 | BO49: =SUM(BD49:BF49) -> 79366.1 | BP49: =SUM(BG49:BI49) -> 0 | BQ49: =SUM(BJ49:BL49) -> 0 | BR49: =SUM(BN49:BQ49) -> 131442.34
A50: BANQUET SERVICE CHARGE | B50: 500-BQSC | C50: BANQUET OTHER REVENUE | D50: 500-BQ05 | E50: =SUMIF($BA$6:$BL$6,$E$6,$BA50:$BL50) -> 0 | F50: =SUMIF($AH$6:$AS$6,$F$6,$AH50:$AS50) -> 0 | G50: =IFERROR((E50-F50)/F50,0) -> 0 | H50: =SUMIF($BN$6:$BR$6,$H$6,$BN50:$BR50) -> 0 | I50: =SUMIF($AU$6:$AY$6,$I$6,$AU50:$AY50) -> 0 | J50: =IFERROR((H50-I50)/I50,0) -> 0 | K50: =BM50 -> 444.92 | L50: =SUM(AH50:AM50) -> 0 | M50: =IFERROR((K50-L50)/L50,0) -> 0 | O50: =SUMIF('2024 AC'!$B$3:$B$250,"*"&$D50&"*",'2024 AC'!C$3:C$250) -> 0 | P50: =SUMIF('2024 AC'!$B$3:$B$250,"*"&$D50&"*",'2024 AC'!D$3:D$250) -> 0 | Q50: =SUMIF('2024 AC'!$B$3:$B$250,"*"&$D50&"*",'2024 AC'!E$3:E$250) -> 0 | R50: =SUMIF('2024 AC'!$B$3:$B$250,"*"&$D50&"*",'2024 AC'!F$3:F$250) -> 0 | S50: =SUMIF('2024 AC'!$B$3:$B$250,"*"&$D50&"*",'2024 AC'!G$3:G$250) -> 0 | T50: =SUMIF('2024 AC'!$B$3:$B$250,"*"&$D50&"*",'2024 AC'!H$3:H$250) -> 0 | U50: =SUMIF('2024 AC'!$B$3:$B$250,"*"&$D50&"*",'2024 AC'!I$3:I$250) -> 0 | V50: =SUMIF('2024 AC'!$B$3:$B$250,"*"&$D50&"*",'2024 AC'!J$3:J$250) -> 0 | ... Z50: =SUMIF('2024 AC'!$B$3:$B$250,"*"&$D50&"*",'2024 AC'!N$3:N$250) -> 0 | AA50: =SUM(O50:Z50) -> 0 | AB50: =SUM(O50:Q50) -> 0 | AC50: =SUM(R50:T50) -> 0 | AD50: =SUM(U50:W50) -> 0 | AE50: =SUM(X50:Z50) -> 0 | AF50: =SUM(AB50:AE50) -> 0 | AH50: =SUMIF('2025 AC'!$B$3:$B$250,"*"&$D50&"*",'2025 AC'!C$3:C$250) -> 0 | AI50: =SUMIF('2025 AC'!$B$3:$B$250,"*"&$D50&"*",'2025 AC'!D$3:D$250) -> 0 | AJ50: =SUMIF('2025 AC'!$B$3:$B$250,"*"&$D50&"*",'2025 AC'!E$3:E$250) -> 0 | AK50: =SUMIF('2025 AC'!$B$3:$B$250,"*"&$D50&"*",'2025 AC'!F$3:F$250) -> 0 | AL50: =SUMIF('2025 AC'!$B$3:$B$250,"*"&$D50&"*",'2025 AC'!G$3:G$250) -> 0 | AM50: =SUMIF('2025 AC'!$B$3:$B$250,"*"&$D50&"*",'2025 AC'!H$3:H$250) -> 0 | AN50: =SUMIF('2025 AC'!$B$3:$B$250,"*"&$D50&"*",'2025 AC'!I$3:I$250) -> 0 | AO50: =SUMIF('2025 AC'!$B$3:$B$250,"*"&$D50&"*",'2025 AC'!J$3:J$250) -> 0 | ... AS50: =SUMIF('2025 AC'!$B$3:$B$250,"*"&$D50&"*",'2025 AC'!N$3:N$250) -> 0 | AT50: =SUM(AH50:AS50) -> 0 | AU50: =SUM(AH50:AJ50) -> 0 | AV50: =SUM(AK50:AM50) -> 0 | AW50: =SUM(AN50:AP50) -> 0 | AX50: =SUM(AQ50:AS50) -> 0 | AY50: =SUM(AU50:AX50) -> 0 | BA50: =SUMIF('2026 AC'!$B$3:$B$254,"*"&$D50&"*",'2026 AC'!C$3:C$254) -> 0 | BB50: =SUMIF('2026 AC'!$B$3:$B$254,"*"&$D50&"*",'2026 AC'!D$3:D$254) -> 0 | BC50: =SUMIF('2026 AC'!$B$3:$B$254,"*"&$D50&"*",'2026 AC'!E$3:E$254) -> 444.92 | BD50: =SUMIF('2026 AC'!$B$3:$B$254,"*"&$D50&"*",'2026 AC'!F$3:F$254) -> 0 | BE50: =SUMIF('2026 AC'!$B$3:$B$254,"*"&$D50&"*",'2026 AC'!G$3:G$254) -> 0 | BF50: =SUMIF('2026 AC'!$B$3:$B$254,"*"&$D50&"*",'2026 AC'!H$3:H$254) -> 0 | BG50: =SUMIF('2026 AC'!$B$3:$B$254,"*"&$D50&"*",'2026 AC'!I$3:I$254) -> 0 | BH50: =SUMIF('2026 AC'!$B$3:$B$254,"*"&$D50&"*",'2026 AC'!J$3:J$254) -> 0 | ... BL50: =SUMIF('2026 AC'!$B$3:$B$254,"*"&$D50&"*",'2026 AC'!N$3:N$254) -> 0 | BM50: =SUM(BA50:BL50) -> 444.92 | BN50: =SUM(BA50:BC50) -> 444.92 | BO50: =SUM(BD50:BF50) -> 0 | BP50: =SUM(BG50:BI50) -> 0 | BQ50: =SUM(BJ50:BL50) -> 0 | BR50: =SUM(BN50:BQ50) -> 444.92
A51: BANQUET SERVICE CHARGE | B51: 500-BQSC | C51: BANQUET SERVICE CHARGE | D51: 500-BQSC | E51: =SUMIF($BA$6:$BL$6,$E$6,$BA51:$BL51) -> 0 | F51: =SUMIF($AH$6:$AS$6,$F$6,$AH51:$AS51) -> 0 | G51: =IFERROR((E51-F51)/F51,0) -> 0 | H51: =SUMIF($BN$6:$BR$6,$H$6,$BN51:$BR51) -> 0 | I51: =SUMIF($AU$6:$AY$6,$I$6,$AU51:$AY51) -> 0 | J51: =IFERROR((H51-I51)/I51,0) -> 0 | K51: =BM51 -> 0 | L51: =SUM(AH51:AM51) -> 0 | M51: =IFERROR((K51-L51)/L51,0) -> 0 | O51: =SUMIF('2024 AC'!$B$3:$B$250,"*"&$D51&"*",'2024 AC'!C$3:C$250) -> 0 | P51: =SUMIF('2024 AC'!$B$3:$B$250,"*"&$D51&"*",'2024 AC'!D$3:D$250) -> 0 | Q51: =SUMIF('2024 AC'!$B$3:$B$250,"*"&$D51&"*",'2024 AC'!E$3:E$250) -> 0 | R51: =SUMIF('2024 AC'!$B$3:$B$250,"*"&$D51&"*",'2024 AC'!F$3:F$250) -> 0 | S51: =SUMIF('2024 AC'!$B$3:$B$250,"*"&$D51&"*",'2024 AC'!G$3:G$250) -> 0 | T51: =SUMIF('2024 AC'!$B$3:$B$250,"*"&$D51&"*",'2024 AC'!H$3:H$250) -> 0 | U51: =SUMIF('2024 AC'!$B$3:$B$250,"*"&$D51&"*",'2024 AC'!I$3:I$250) -> 0 | V51: =SUMIF('2024 AC'!$B$3:$B$250,"*"&$D51&"*",'2024 AC'!J$3:J$250) -> 0 | ... Z51: =SUMIF('2024 AC'!$B$3:$B$250,"*"&$D51&"*",'2024 AC'!N$3:N$250) -> 0 | AA51: =SUM(O51:Z51) -> 0 | AB51: =SUM(O51:Q51) -> 0 | AC51: =SUM(R51:T51) -> 0 | AD51: =SUM(U51:W51) -> 0 | AE51: =SUM(X51:Z51) -> 0 | AF51: =SUM(AB51:AE51) -> 0 | AH51: =SUMIF('2025 AC'!$B$3:$B$250,"*"&$D51&"*",'2025 AC'!C$3:C$250) -> 0 | AI51: =SUMIF('2025 AC'!$B$3:$B$250,"*"&$D51&"*",'2025 AC'!D$3:D$250) -> 0 | AJ51: =SUMIF('2025 AC'!$B$3:$B$250,"*"&$D51&"*",'2025 AC'!E$3:E$250) -> 0 | AK51: =SUMIF('2025 AC'!$B$3:$B$250,"*"&$D51&"*",'2025 AC'!F$3:F$250) -> 0 | AL51: =SUMIF('2025 AC'!$B$3:$B$250,"*"&$D51&"*",'2025 AC'!G$3:G$250) -> 0 | AM51: =SUMIF('2025 AC'!$B$3:$B$250,"*"&$D51&"*",'2025 AC'!H$3:H$250) -> 0 | AN51: =SUMIF('2025 AC'!$B$3:$B$250,"*"&$D51&"*",'2025 AC'!I$3:I$250) -> 0 | AO51: =SUMIF('2025 AC'!$B$3:$B$250,"*"&$D51&"*",'2025 AC'!J$3:J$250) -> 0 | ... AS51: =SUMIF('2025 AC'!$B$3:$B$250,"*"&$D51&"*",'2025 AC'!N$3:N$250) -> 0 | AT51: =SUM(AH51:AS51) -> 0 | AU51: =SUM(AH51:AJ51) -> 0 | AV51: =SUM(AK51:AM51) -> 0 | AW51: =SUM(AN51:AP51) -> 0 | AX51: =SUM(AQ51:AS51) -> 0 | AY51: =SUM(AU51:AX51) -> 0 | BA51: =SUMIF('2026 AC'!$B$3:$B$254,"*"&$D51&"*",'2026 AC'!C$3:C$254) -> 0 | BB51: =SUMIF('2026 AC'!$B$3:$B$254,"*"&$D51&"*",'2026 AC'!D$3:D$254) -> 0 | BC51: =SUMIF('2026 AC'!$B$3:$B$254,"*"&$D51&"*",'2026 AC'!E$3:E$254) -> 0 | BD51: =SUMIF('2026 AC'!$B$3:$B$254,"*"&$D51&"*",'2026 AC'!F$3:F$254) -> 0 | BE51: =SUMIF('2026 AC'!$B$3:$B$254,"*"&$D51&"*",'2026 AC'!G$3:G$254) -> 0 | BF51: =SUMIF('2026 AC'!$B$3:$B$254,"*"&$D51&"*",'2026 AC'!H$3:H$254) -> 0 | BG51: =SUMIF('2026 AC'!$B$3:$B$254,"*"&$D51&"*",'2026 AC'!I$3:I$254) -> 0 | BH51: =SUMIF('2026 AC'!$B$3:$B$254,"*"&$D51&"*",'2026 AC'!J$3:J$254) -> 0 | ... BL51: =SUMIF('2026 AC'!$B$3:$B$254,"*"&$D51&"*",'2026 AC'!N$3:N$254) -> 0 | BM51: =SUM(BA51:BL51) -> 0 | BN51: =SUM(BA51:BC51) -> 0 | BO51: =SUM(BD51:BF51) -> 0 | BP51: =SUM(BG51:BI51) -> 0 | BQ51: =SUM(BJ51:BL51) -> 0 | BR51: =SUM(BN51:BQ51) -> 0
A52: CAR PARK | B52: 500-4000 | C52: CARPARK | D52: 500-4000 | E52: =SUMIF($BA$6:$BL$6,$E$6,$BA52:$BL52) -> 3860.37 | F52: =SUMIF($AH$6:$AS$6,$F$6,$AH52:$AS52) -> 5330.2 | G52: =(E52-F52)/F52 -> -0.27575513 | H52: =SUMIF($BN$6:$BR$6,$H$6,$BN52:$BR52) -> 18484.89 | I52: =SUMIF($AU$6:$AY$6,$I$6,$AU52:$AY52) -> 21460.01 | J52: =(H52-I52)/I52 -> -0.13863554 | K52: =BM52 -> 36421.66 | L52: =SUM(AH52:AM52) -> 39577.95 | M52: =(K52-L52)/L52 -> -0.079748698 | O52: =SUMIF('2024 AC'!$B$3:$B$250,"*"&$D52&"*",'2024 AC'!C$3:C$250) -> 6601.88 | P52: =SUMIF('2024 AC'!$B$3:$B$250,"*"&$D52&"*",'2024 AC'!D$3:D$250) -> 5480.2 | Q52: =SUMIF('2024 AC'!$B$3:$B$250,"*"&$D52&"*",'2024 AC'!E$3:E$250) -> 5224.53 | R52: =SUMIF('2024 AC'!$B$3:$B$250,"*"&$D52&"*",'2024 AC'!F$3:F$250) -> 5225.47 | S52: =SUMIF('2024 AC'!$B$3:$B$250,"*"&$D52&"*",'2024 AC'!G$3:G$250) -> 10327.37 | T52: =SUMIF('2024 AC'!$B$3:$B$250,"*"&$D52&"*",'2024 AC'!H$3:H$250) -> 4571.7 | U52: =SUMIF('2024 AC'!$B$3:$B$250,"*"&$D52&"*",'2024 AC'!I$3:I$250) -> 5440.58 | V52: =SUMIF('2024 AC'!$B$3:$B$250,"*"&$D52&"*",'2024 AC'!J$3:J$250) -> 4824.53 | ... Z52: =SUMIF('2024 AC'!$B$3:$B$250,"*"&$D52&"*",'2024 AC'!N$3:N$250) -> 9457.56 | AA52: =SUM(O52:Z52) -> 72117.97 | AB52: =SUM(O52:Q52) -> 17306.61 | AC52: =SUM(R52:T52) -> 20124.54 | AD52: =SUM(U52:W52) -> 16119.83 | AE52: =SUM(X52:Z52) -> 18566.99 | AF52: =SUM(AB52:AE52) -> 72117.97 | AH52: =SUMIF('2025 AC'!$B$3:$B$250,"*"&$D52&"*",'2025 AC'!C$3:C$250) -> 7011.33 | AI52: =SUMIF('2025 AC'!$B$3:$B$250,"*"&$D52&"*",'2025 AC'!D$3:D$250) -> 6865.1 | AJ52: =SUMIF('2025 AC'!$B$3:$B$250,"*"&$D52&"*",'2025 AC'!E$3:E$250) -> 4241.51 | AK52: =SUMIF('2025 AC'!$B$3:$B$250,"*"&$D52&"*",'2025 AC'!F$3:F$250) -> 6443 | AL52: =SUMIF('2025 AC'!$B$3:$B$250,"*"&$D52&"*",'2025 AC'!G$3:G$250) -> 9686.81 | AM52: =SUMIF('2025 AC'!$B$3:$B$250,"*"&$D52&"*",'2025 AC'!H$3:H$250) -> 5330.2 | AN52: =SUMIF('2025 AC'!$B$3:$B$250,"*"&$D52&"*",'2025 AC'!I$3:I$250) -> 4754.67 | AO52: =SUMIF('2025 AC'!$B$3:$B$250,"*"&$D52&"*",'2025 AC'!J$3:J$250) -> 4735.23 | ... AS52: =SUMIF('2025 AC'!$B$3:$B$250,"*"&$D52&"*",'2025 AC'!N$3:N$250) -> 4830.18 | AT52: =SUM(AH52:AS52) -> 68801.92 | AU52: =SUM(AH52:AJ52) -> 18117.94 | AV52: =SUM(AK52:AM52) -> 21460.01 | AW52: =SUM(AN52:AP52) -> 13885.32 | AX52: =SUM(AQ52:AS52) -> 15338.65 | AY52: =SUM(AU52:AX52) -> 68801.92 | BA52: =SUMIF('2026 AC'!$B$3:$B$254,"*"&$D52&"*",'2026 AC'!C$3:C$254) -> 8556.6 | BB52: =SUMIF('2026 AC'!$B$3:$B$254,"*"&$D52&"*",'2026 AC'!D$3:D$254) -> 4878.29 | BC52: =SUMIF('2026 AC'!$B$3:$B$254,"*"&$D52&"*",'2026 AC'!E$3:E$254) -> 4501.88 | BD52: =SUMIF('2026 AC'!$B$3:$B$254,"*"&$D52&"*",'2026 AC'!F$3:F$254) -> 8695.28 | BE52: =SUMIF('2026 AC'!$B$3:$B$254,"*"&$D52&"*",'2026 AC'!G$3:G$254) -> 5929.24 | BF52: =SUMIF('2026 AC'!$B$3:$B$254,"*"&$D52&"*",'2026 AC'!H$3:H$254) -> 3860.37 | BG52: =SUMIF('2026 AC'!$B$3:$B$254,"*"&$D52&"*",'2026 AC'!I$3:I$254) -> 0 | BH52: =SUMIF('2026 AC'!$B$3:$B$254,"*"&$D52&"*",'2026 AC'!J$3:J$254) -> 0 | ... BL52: =SUMIF('2026 AC'!$B$3:$B$254,"*"&$D52&"*",'2026 AC'!N$3:N$254) -> 0 | BM52: =SUM(BA52:BL52) -> 36421.66 | BN52: =SUM(BA52:BC52) -> 17936.77 | BO52: =SUM(BD52:BF52) -> 18484.89 | BP52: =SUM(BG52:BI52) -> 0 | BQ52: =SUM(BJ52:BL52) -> 0 | BR52: =SUM(BN52:BQ52) -> 36421.66
A53: CAR PARK | B53: 500-4000 | C53: CAR PARK | D53: 500-CP01 | E53: =SUMIF($BA$6:$BL$6,$E$6,$BA53:$BL53) -> 3860.37 | F53: =SUMIF($AH$6:$AS$6,$F$6,$AH53:$AS53) -> 5330.2 | G53: =(E53-F53)/F53 -> -0.27575513 | H53: =SUMIF($BN$6:$BR$6,$H$6,$BN53:$BR53) -> 18484.89 | I53: =SUMIF($AU$6:$AY$6,$I$6,$AU53:$AY53) -> 21460.01 | J53: =(H53-I53)/I53 -> -0.13863554 | K53: =BM53 -> 36421.66 | L53: =SUM(AH53:AM53) -> 39577.95 | M53: =(K53-L53)/L53 -> -0.079748698 | O53: =SUMIF('2024 AC'!$B$3:$B$250,"*"&$D53&"*",'2024 AC'!C$3:C$250) -> 6601.88 | P53: =SUMIF('2024 AC'!$B$3:$B$250,"*"&$D53&"*",'2024 AC'!D$3:D$250) -> 5480.2 | Q53: =SUMIF('2024 AC'!$B$3:$B$250,"*"&$D53&"*",'2024 AC'!E$3:E$250) -> 5224.53 | R53: =SUMIF('2024 AC'!$B$3:$B$250,"*"&$D53&"*",'2024 AC'!F$3:F$250) -> 5225.47 | S53: =SUMIF('2024 AC'!$B$3:$B$250,"*"&$D53&"*",'2024 AC'!G$3:G$250) -> 10327.37 | T53: =SUMIF('2024 AC'!$B$3:$B$250,"*"&$D53&"*",'2024 AC'!H$3:H$250) -> 4571.7 | U53: =SUMIF('2024 AC'!$B$3:$B$250,"*"&$D53&"*",'2024 AC'!I$3:I$250) -> 5440.58 | V53: =SUMIF('2024 AC'!$B$3:$B$250,"*"&$D53&"*",'2024 AC'!J$3:J$250) -> 4824.53 | ... Z53: =SUMIF('2024 AC'!$B$3:$B$250,"*"&$D53&"*",'2024 AC'!N$3:N$250) -> 9457.56 | AA53: =SUM(O53:Z53) -> 72117.97 | AB53: =SUM(O53:Q53) -> 17306.61 | AC53: =SUM(R53:T53) -> 20124.54 | AD53: =SUM(U53:W53) -> 16119.83 | AE53: =SUM(X53:Z53) -> 18566.99 | AF53: =SUM(AB53:AE53) -> 72117.97 | AH53: =SUMIF('2025 AC'!$B$3:$B$250,"*"&$D53&"*",'2025 AC'!C$3:C$250) -> 7011.33 | AI53: =SUMIF('2025 AC'!$B$3:$B$250,"*"&$D53&"*",'2025 AC'!D$3:D$250) -> 6865.1 | AJ53: =SUMIF('2025 AC'!$B$3:$B$250,"*"&$D53&"*",'2025 AC'!E$3:E$250) -> 4241.51 | AK53: =SUMIF('2025 AC'!$B$3:$B$250,"*"&$D53&"*",'2025 AC'!F$3:F$250) -> 6443 | AL53: =SUMIF('2025 AC'!$B$3:$B$250,"*"&$D53&"*",'2025 AC'!G$3:G$250) -> 9686.81 | AM53: =SUMIF('2025 AC'!$B$3:$B$250,"*"&$D53&"*",'2025 AC'!H$3:H$250) -> 5330.2 | AN53: =SUMIF('2025 AC'!$B$3:$B$250,"*"&$D53&"*",'2025 AC'!I$3:I$250) -> 4754.67 | AO53: =SUMIF('2025 AC'!$B$3:$B$250,"*"&$D53&"*",'2025 AC'!J$3:J$250) -> 4735.23 | ... AS53: =SUMIF('2025 AC'!$B$3:$B$250,"*"&$D53&"*",'2025 AC'!N$3:N$250) -> 4830.18 | AT53: =SUM(AH53:AS53) -> 68801.92 | AU53: =SUM(AH53:AJ53) -> 18117.94 | AV53: =SUM(AK53:AM53) -> 21460.01 | AW53: =SUM(AN53:AP53) -> 13885.32 | AX53: =SUM(AQ53:AS53) -> 15338.65 | AY53: =SUM(AU53:AX53) -> 68801.92 | BA53: =SUMIF('2026 AC'!$B$3:$B$254,"*"&$D53&"*",'2026 AC'!C$3:C$254) -> 8556.6 | BB53: =SUMIF('2026 AC'!$B$3:$B$254,"*"&$D53&"*",'2026 AC'!D$3:D$254) -> 4878.29 | BC53: =SUMIF('2026 AC'!$B$3:$B$254,"*"&$D53&"*",'2026 AC'!E$3:E$254) -> 4501.88 | BD53: =SUMIF('2026 AC'!$B$3:$B$254,"*"&$D53&"*",'2026 AC'!F$3:F$254) -> 8695.28 | BE53: =SUMIF('2026 AC'!$B$3:$B$254,"*"&$D53&"*",'2026 AC'!G$3:G$254) -> 5929.24 | BF53: =SUMIF('2026 AC'!$B$3:$B$254,"*"&$D53&"*",'2026 AC'!H$3:H$254) -> 3860.37 | BG53: =SUMIF('2026 AC'!$B$3:$B$254,"*"&$D53&"*",'2026 AC'!I$3:I$254) -> 0 | BH53: =SUMIF('2026 AC'!$B$3:$B$254,"*"&$D53&"*",'2026 AC'!J$3:J$254) -> 0 | ... BL53: =SUMIF('2026 AC'!$B$3:$B$254,"*"&$D53&"*",'2026 AC'!N$3:N$254) -> 0 | BM53: =SUM(BA53:BL53) -> 36421.66 | BN53: =SUM(BA53:BC53) -> 17936.77 | BO53: =SUM(BD53:BF53) -> 18484.89 | BP53: =SUM(BG53:BI53) -> 0 | BQ53: =SUM(BJ53:BL53) -> 0 | BR53: =SUM(BN53:BQ53) -> 36421.66
A54: CAR PARK | B54: 500-4000 | C54: CAR PARK SERVICE CHARGE | D54: 500-CPSC | E54: =SUMIF($BA$6:$BL$6,$E$6,$BA54:$BL54) -> 0 | F54: =SUMIF($AH$6:$AS$6,$F$6,$AH54:$AS54) -> 0 | G54: =IFERROR((E54-F54)/F54,0) -> 0 | H54: =SUMIF($BN$6:$BR$6,$H$6,$BN54:$BR54) -> 0 | I54: =SUMIF($AU$6:$AY$6,$I$6,$AU54:$AY54) -> 0 | J54: =IFERROR((H54-I54)/I54,0) -> 0 | K54: =BM54 -> 0 | L54: =SUM(AH54:AM54) -> 0 | M54: =IFERROR((K54-L54)/L54,0) -> 0 | O54: =SUMIF('2024 AC'!$B$3:$B$250,"*"&$D54&"*",'2024 AC'!C$3:C$250) -> 0 | P54: =SUMIF('2024 AC'!$B$3:$B$250,"*"&$D54&"*",'2024 AC'!D$3:D$250) -> 0 | Q54: =SUMIF('2024 AC'!$B$3:$B$250,"*"&$D54&"*",'2024 AC'!E$3:E$250) -> 0 | R54: =SUMIF('2024 AC'!$B$3:$B$250,"*"&$D54&"*",'2024 AC'!F$3:F$250) -> 0 | S54: =SUMIF('2024 AC'!$B$3:$B$250,"*"&$D54&"*",'2024 AC'!G$3:G$250) -> 0 | T54: =SUMIF('2024 AC'!$B$3:$B$250,"*"&$D54&"*",'2024 AC'!H$3:H$250) -> 0 | U54: =SUMIF('2024 AC'!$B$3:$B$250,"*"&$D54&"*",'2024 AC'!I$3:I$250) -> 0 | V54: =SUMIF('2024 AC'!$B$3:$B$250,"*"&$D54&"*",'2024 AC'!J$3:J$250) -> 0 | ... Z54: =SUMIF('2024 AC'!$B$3:$B$250,"*"&$D54&"*",'2024 AC'!N$3:N$250) -> 0 | AA54: =SUM(O54:Z54) -> 0 | AB54: =SUM(O54:Q54) -> 0 | AC54: =SUM(R54:T54) -> 0 | AD54: =SUM(U54:W54) -> 0 | AE54: =SUM(X54:Z54) -> 0 | AF54: =SUM(AB54:AE54) -> 0 | AH54: =SUMIF('2025 AC'!$B$3:$B$250,"*"&$D54&"*",'2025 AC'!C$3:C$250) -> 0 | AI54: =SUMIF('2025 AC'!$B$3:$B$250,"*"&$D54&"*",'2025 AC'!D$3:D$250) -> 0 | AJ54: =SUMIF('2025 AC'!$B$3:$B$250,"*"&$D54&"*",'2025 AC'!E$3:E$250) -> 0 | AK54: =SUMIF('2025 AC'!$B$3:$B$250,"*"&$D54&"*",'2025 AC'!F$3:F$250) -> 0 | AL54: =SUMIF('2025 AC'!$B$3:$B$250,"*"&$D54&"*",'2025 AC'!G$3:G$250) -> 0 | AM54: =SUMIF('2025 AC'!$B$3:$B$250,"*"&$D54&"*",'2025 AC'!H$3:H$250) -> 0 | AN54: =SUMIF('2025 AC'!$B$3:$B$250,"*"&$D54&"*",'2025 AC'!I$3:I$250) -> 0 | AO54: =SUMIF('2025 AC'!$B$3:$B$250,"*"&$D54&"*",'2025 AC'!J$3:J$250) -> 0 | ... AS54: =SUMIF('2025 AC'!$B$3:$B$250,"*"&$D54&"*",'2025 AC'!N$3:N$250) -> 0 | AT54: =SUM(AH54:AS54) -> 0 | AU54: =SUM(AH54:AJ54) -> 0 | AV54: =SUM(AK54:AM54) -> 0 | AW54: =SUM(AN54:AP54) -> 0 | AX54: =SUM(AQ54:AS54) -> 0 | AY54: =SUM(AU54:AX54) -> 0 | BA54: =SUMIF('2026 AC'!$B$3:$B$254,"*"&$D54&"*",'2026 AC'!C$3:C$254) -> 0 | BB54: =SUMIF('2026 AC'!$B$3:$B$254,"*"&$D54&"*",'2026 AC'!D$3:D$254) -> 0 | BC54: =SUMIF('2026 AC'!$B$3:$B$254,"*"&$D54&"*",'2026 AC'!E$3:E$254) -> 0 | BD54: =SUMIF('2026 AC'!$B$3:$B$254,"*"&$D54&"*",'2026 AC'!F$3:F$254) -> 0 | BE54: =SUMIF('2026 AC'!$B$3:$B$254,"*"&$D54&"*",'2026 AC'!G$3:G$254) -> 0 | BF54: =SUMIF('2026 AC'!$B$3:$B$254,"*"&$D54&"*",'2026 AC'!H$3:H$254) -> 0 | BG54: =SUMIF('2026 AC'!$B$3:$B$254,"*"&$D54&"*",'2026 AC'!I$3:I$254) -> 0 | BH54: =SUMIF('2026 AC'!$B$3:$B$254,"*"&$D54&"*",'2026 AC'!J$3:J$254) -> 0 | ... BL54: =SUMIF('2026 AC'!$B$3:$B$254,"*"&$D54&"*",'2026 AC'!N$3:N$254) -> 0 | BM54: =SUM(BA54:BL54) -> 0 | BN54: =SUM(BA54:BC54) -> 0 | BO54: =SUM(BD54:BF54) -> 0 | BP54: =SUM(BG54:BI54) -> 0 | BQ54: =SUM(BJ54:BL54) -> 0 | BR54: =SUM(BN54:BQ54) -> 0
A55: CAR PARK | B55: 500-CP01 | C55: CLEANING SERVICE REVENUE | D55: 500-5000 | E55: =SUMIF($BA$6:$BL$6,$E$6,$BA55:$BL55) -> 1000 | F55: =SUMIF($AH$6:$AS$6,$F$6,$AH55:$AS55) -> 0 | G55: =IFERROR((E55-F55)/F55,1) -> 1 | H55: =SUMIF($BN$6:$BR$6,$H$6,$BN55:$BR55) -> 3000 | I55: =SUMIF($AU$6:$AY$6,$I$6,$AU55:$AY55) -> 0 | J55: =(H55-I55)/I55 -> #DIV/0! | K55: =BM55 -> 6000 | L55: =SUM(AH55:AM55) -> 259.26 | M55: =(K55-L55)/L55 -> 22.142791 | O55: =SUMIF('2024 AC'!$B$3:$B$250,"*"&$D55&"*",'2024 AC'!C$3:C$250) -> 2599.06 | P55: =SUMIF('2024 AC'!$B$3:$B$250,"*"&$D55&"*",'2024 AC'!D$3:D$250) -> 715.81 | Q55: =SUMIF('2024 AC'!$B$3:$B$250,"*"&$D55&"*",'2024 AC'!E$3:E$250) -> 129.63 | R55: =SUMIF('2024 AC'!$B$3:$B$250,"*"&$D55&"*",'2024 AC'!F$3:F$250) -> 0 | S55: =SUMIF('2024 AC'!$B$3:$B$250,"*"&$D55&"*",'2024 AC'!G$3:G$250) -> 0 | T55: =SUMIF('2024 AC'!$B$3:$B$250,"*"&$D55&"*",'2024 AC'!H$3:H$250) -> 0 | U55: =SUMIF('2024 AC'!$B$3:$B$250,"*"&$D55&"*",'2024 AC'!I$3:I$250) -> 0 | V55: =SUMIF('2024 AC'!$B$3:$B$250,"*"&$D55&"*",'2024 AC'!J$3:J$250) -> 0 | ... Z55: =SUMIF('2024 AC'!$B$3:$B$250,"*"&$D55&"*",'2024 AC'!N$3:N$250) -> 0 | AA55: =SUM(O55:Z55) -> 3703.76 | AB55: =SUM(O55:Q55) -> 3444.5 | AC55: =SUM(R55:T55) -> 0 | AD55: =SUM(U55:W55) -> 259.26 | AE55: =SUM(X55:Z55) -> 0 | AF55: =SUM(AB55:AE55) -> 3703.76 | AH55: =SUMIF('2025 AC'!$B$3:$B$250,"*"&$D55&"*",'2025 AC'!C$3:C$250) -> 259.26 | AI55: =SUMIF('2025 AC'!$B$3:$B$250,"*"&$D55&"*",'2025 AC'!D$3:D$250) -> 0 | AJ55: =SUMIF('2025 AC'!$B$3:$B$250,"*"&$D55&"*",'2025 AC'!E$3:E$250) -> 0 | AK55: =SUMIF('2025 AC'!$B$3:$B$250,"*"&$D55&"*",'2025 AC'!F$3:F$250) -> 0 | AL55: =SUMIF('2025 AC'!$B$3:$B$250,"*"&$D55&"*",'2025 AC'!G$3:G$250) -> 0 | AM55: =SUMIF('2025 AC'!$B$3:$B$250,"*"&$D55&"*",'2025 AC'!H$3:H$250) -> 0 | AN55: =SUMIF('2025 AC'!$B$3:$B$250,"*"&$D55&"*",'2025 AC'!I$3:I$250) -> 259.26 | AO55: =SUMIF('2025 AC'!$B$3:$B$250,"*"&$D55&"*",'2025 AC'!J$3:J$250) -> 0 | ... AS55: =SUMIF('2025 AC'!$B$3:$B$250,"*"&$D55&"*",'2025 AC'!N$3:N$250) -> 45270 | AT55: =SUM(AH55:AS55) -> 45788.52 | AU55: =SUM(AH55:AJ55) -> 259.26 | AV55: =SUM(AK55:AM55) -> 0 | AW55: =SUM(AN55:AP55) -> 259.26 | AX55: =SUM(AQ55:AS55) -> 45270 | AY55: =SUM(AU55:AX55) -> 45788.52 | BA55: =SUMIF('2026 AC'!$B$3:$B$254,"*"&$D55&"*",'2026 AC'!C$3:C$254) -> 1000 | BB55: =SUMIF('2026 AC'!$B$3:$B$254,"*"&$D55&"*",'2026 AC'!D$3:D$254) -> 1000 | BC55: =SUMIF('2026 AC'!$B$3:$B$254,"*"&$D55&"*",'2026 AC'!E$3:E$254) -> 1000 | BD55: =SUMIF('2026 AC'!$B$3:$B$254,"*"&$D55&"*",'2026 AC'!F$3:F$254) -> 1000 | BE55: =SUMIF('2026 AC'!$B$3:$B$254,"*"&$D55&"*",'2026 AC'!G$3:G$254) -> 1000 | BF55: =SUMIF('2026 AC'!$B$3:$B$254,"*"&$D55&"*",'2026 AC'!H$3:H$254) -> 1000 | BG55: =SUMIF('2026 AC'!$B$3:$B$254,"*"&$D55&"*",'2026 AC'!I$3:I$254) -> 0 | BH55: =SUMIF('2026 AC'!$B$3:$B$254,"*"&$D55&"*",'2026 AC'!J$3:J$254) -> 0 | ... BL55: =SUMIF('2026 AC'!$B$3:$B$254,"*"&$D55&"*",'2026 AC'!N$3:N$254) -> 0 | BM55: =SUM(BA55:BL55) -> 6000 | BN55: =SUM(BA55:BC55) -> 3000 | BO55: =SUM(BD55:BF55) -> 3000 | BP55: =SUM(BG55:BI55) -> 0 | BQ55: =SUM(BJ55:BL55) -> 0 | BR55: =SUM(BN55:BQ55) -> 6000
A56: CLEANING SERVICE REVENUE | B56: 500-CL01 | C56: CLEANING SERVICE REVENUE | D56: 500-CL01 | E56: =SUMIF($BA$6:$BL$6,$E$6,$BA56:$BL56) -> 1000 | F56: =SUMIF($AH$6:$AS$6,$F$6,$AH56:$AS56) -> 0 | G56: =IFERROR((E56-F56)/F56,1) -> 1 | H56: =SUMIF($BN$6:$BR$6,$H$6,$BN56:$BR56) -> 3000 | I56: =SUMIF($AU$6:$AY$6,$I$6,$AU56:$AY56) -> 0 | J56: =(H56-I56)/I56 -> #DIV/0! | K56: =BM56 -> 6000 | L56: =SUM(AH56:AM56) -> 259.26 | M56: =(K56-L56)/L56 -> 22.142791 | O56: =SUMIF('2024 AC'!$B$3:$B$250,"*"&$D56&"*",'2024 AC'!C$3:C$250) -> 2599.06 | P56: =SUMIF('2024 AC'!$B$3:$B$250,"*"&$D56&"*",'2024 AC'!D$3:D$250) -> 715.81 | Q56: =SUMIF('2024 AC'!$B$3:$B$250,"*"&$D56&"*",'2024 AC'!E$3:E$250) -> 129.63 | R56: =SUMIF('2024 AC'!$B$3:$B$250,"*"&$D56&"*",'2024 AC'!F$3:F$250) -> 0 | S56: =SUMIF('2024 AC'!$B$3:$B$250,"*"&$D56&"*",'2024 AC'!G$3:G$250) -> 0 | T56: =SUMIF('2024 AC'!$B$3:$B$250,"*"&$D56&"*",'2024 AC'!H$3:H$250) -> 0 | U56: =SUMIF('2024 AC'!$B$3:$B$250,"*"&$D56&"*",'2024 AC'!I$3:I$250) -> 0 | V56: =SUMIF('2024 AC'!$B$3:$B$250,"*"&$D56&"*",'2024 AC'!J$3:J$250) -> 0 | ... Z56: =SUMIF('2024 AC'!$B$3:$B$250,"*"&$D56&"*",'2024 AC'!N$3:N$250) -> 0 | AA56: =SUM(O56:Z56) -> 3703.76 | AB56: =SUM(O56:Q56) -> 3444.5 | AC56: =SUM(R56:T56) -> 0 | AD56: =SUM(U56:W56) -> 259.26 | AE56: =SUM(X56:Z56) -> 0 | AF56: =SUM(AB56:AE56) -> 3703.76 | AH56: =SUMIF('2025 AC'!$B$3:$B$250,"*"&$D56&"*",'2025 AC'!C$3:C$250) -> 259.26 | AI56: =SUMIF('2025 AC'!$B$3:$B$250,"*"&$D56&"*",'2025 AC'!D$3:D$250) -> 0 | AJ56: =SUMIF('2025 AC'!$B$3:$B$250,"*"&$D56&"*",'2025 AC'!E$3:E$250) -> 0 | AK56: =SUMIF('2025 AC'!$B$3:$B$250,"*"&$D56&"*",'2025 AC'!F$3:F$250) -> 0 | AL56: =SUMIF('2025 AC'!$B$3:$B$250,"*"&$D56&"*",'2025 AC'!G$3:G$250) -> 0 | AM56: =SUMIF('2025 AC'!$B$3:$B$250,"*"&$D56&"*",'2025 AC'!H$3:H$250) -> 0 | AN56: =SUMIF('2025 AC'!$B$3:$B$250,"*"&$D56&"*",'2025 AC'!I$3:I$250) -> 259.26 | AO56: =SUMIF('2025 AC'!$B$3:$B$250,"*"&$D56&"*",'2025 AC'!J$3:J$250) -> 0 | ... AS56: =SUMIF('2025 AC'!$B$3:$B$250,"*"&$D56&"*",'2025 AC'!N$3:N$250) -> 45270 | AT56: =SUM(AH56:AS56) -> 45788.52 | AU56: =SUM(AH56:AJ56) -> 259.26 | AV56: =SUM(AK56:AM56) -> 0 | AW56: =SUM(AN56:AP56) -> 259.26 | AX56: =SUM(AQ56:AS56) -> 45270 | AY56: =SUM(AU56:AX56) -> 45788.52 | BA56: =SUMIF('2026 AC'!$B$3:$B$254,"*"&$D56&"*",'2026 AC'!C$3:C$254) -> 1000 | BB56: =SUMIF('2026 AC'!$B$3:$B$254,"*"&$D56&"*",'2026 AC'!D$3:D$254) -> 1000 | BC56: =SUMIF('2026 AC'!$B$3:$B$254,"*"&$D56&"*",'2026 AC'!E$3:E$254) -> 1000 | BD56: =SUMIF('2026 AC'!$B$3:$B$254,"*"&$D56&"*",'2026 AC'!F$3:F$254) -> 1000 | BE56: =SUMIF('2026 AC'!$B$3:$B$254,"*"&$D56&"*",'2026 AC'!G$3:G$254) -> 1000 | BF56: =SUMIF('2026 AC'!$B$3:$B$254,"*"&$D56&"*",'2026 AC'!H$3:H$254) -> 1000 | BG56: =SUMIF('2026 AC'!$B$3:$B$254,"*"&$D56&"*",'2026 AC'!I$3:I$254) -> 0 | BH56: =SUMIF('2026 AC'!$B$3:$B$254,"*"&$D56&"*",'2026 AC'!J$3:J$254) -> 0 | ... BL56: =SUMIF('2026 AC'!$B$3:$B$254,"*"&$D56&"*",'2026 AC'!N$3:N$254) -> 0 | BM56: =SUM(BA56:BL56) -> 6000 | BN56: =SUM(BA56:BC56) -> 3000 | BO56: =SUM(BD56:BF56) -> 3000 | BP56: =SUM(BG56:BI56) -> 0 | BQ56: =SUM(BJ56:BL56) -> 0 | BR56: =SUM(BN56:BQ56) -> 6000
A57: CLEANING SERVICE REVENUE | B57: 500-5000 | C57: MISCELLANEOUS CHARGE | D57: 500-6000 | E57: =SUMIF($BA$6:$BL$6,$E$6,$BA57:$BL57) -> 0 | F57: =SUMIF($AH$6:$AS$6,$F$6,$AH57:$AS57) -> 0 | G57: =E57-F57 -> 0 | H57: =SUMIF($BN$6:$BR$6,$H$6,$BN57:$BR57) -> 0 | I57: =SUMIF($AU$6:$AY$6,$I$6,$AU57:$AY57) -> 150 | J57: =H57-I57 -> -150 | K57: =BM57 -> 45 | L57: =SUM(AH57:AM57) -> 150 | M57: =K57-L57 -> -105 | O57: =SUMIF('2024 AC'!$B$3:$B$250,"*"&$D57&"*",'2024 AC'!C$3:C$250) -> 1335.6 | P57: =SUMIF('2024 AC'!$B$3:$B$250,"*"&$D57&"*",'2024 AC'!D$3:D$250) -> 349.06 | Q57: =SUMIF('2024 AC'!$B$3:$B$250,"*"&$D57&"*",'2024 AC'!E$3:E$250) -> 381.36 | R57: =SUMIF('2024 AC'!$B$3:$B$250,"*"&$D57&"*",'2024 AC'!F$3:F$250) -> 0 | S57: =SUMIF('2024 AC'!$B$3:$B$250,"*"&$D57&"*",'2024 AC'!G$3:G$250) -> 0 | T57: =SUMIF('2024 AC'!$B$3:$B$250,"*"&$D57&"*",'2024 AC'!H$3:H$250) -> 0 | U57: =SUMIF('2024 AC'!$B$3:$B$250,"*"&$D57&"*",'2024 AC'!I$3:I$250) -> 0 | V57: =SUMIF('2024 AC'!$B$3:$B$250,"*"&$D57&"*",'2024 AC'!J$3:J$250) -> 0 | ... Z57: =SUMIF('2024 AC'!$B$3:$B$250,"*"&$D57&"*",'2024 AC'!N$3:N$250) -> 30 | AA57: =SUM(O57:Z57) -> 2456.02 | AB57: =SUM(O57:Q57) -> 2066.02 | AC57: =SUM(R57:T57) -> 0 | AD57: =SUM(U57:W57) -> 0 | AE57: =SUM(X57:Z57) -> 390 | AF57: =SUM(AB57:AE57) -> 2456.02 | AH57: =SUMIF('2025 AC'!$B$3:$B$250,"*"&$D57&"*",'2025 AC'!C$3:C$250) -> 0 | AI57: =SUMIF('2025 AC'!$B$3:$B$250,"*"&$D57&"*",'2025 AC'!D$3:D$250) -> 0 | AJ57: =SUMIF('2025 AC'!$B$3:$B$250,"*"&$D57&"*",'2025 AC'!E$3:E$250) -> 0 | AK57: =SUMIF('2025 AC'!$B$3:$B$250,"*"&$D57&"*",'2025 AC'!F$3:F$250) -> 120 | AL57: =SUMIF('2025 AC'!$B$3:$B$250,"*"&$D57&"*",'2025 AC'!G$3:G$250) -> 30 | AM57: =SUMIF('2025 AC'!$B$3:$B$250,"*"&$D57&"*",'2025 AC'!H$3:H$250) -> 0 | AN57: =SUMIF('2025 AC'!$B$3:$B$250,"*"&$D57&"*",'2025 AC'!I$3:I$250) -> 30 | AO57: =SUMIF('2025 AC'!$B$3:$B$250,"*"&$D57&"*",'2025 AC'!J$3:J$250) -> 0 | ... AS57: =SUMIF('2025 AC'!$B$3:$B$250,"*"&$D57&"*",'2025 AC'!N$3:N$250) -> 0 | AT57: =SUM(AH57:AS57) -> 210 | AU57: =SUM(AH57:AJ57) -> 0 | AV57: =SUM(AK57:AM57) -> 150 | AW57: =SUM(AN57:AP57) -> 30 | AX57: =SUM(AQ57:AS57) -> 30 | AY57: =SUM(AU57:AX57) -> 210 | BA57: =SUMIF('2026 AC'!$B$3:$B$254,"*"&$D57&"*",'2026 AC'!C$3:C$254) -> 15 | BB57: =SUMIF('2026 AC'!$B$3:$B$254,"*"&$D57&"*",'2026 AC'!D$3:D$254) -> 0 | BC57: =SUMIF('2026 AC'!$B$3:$B$254,"*"&$D57&"*",'2026 AC'!E$3:E$254) -> 30 | BD57: =SUMIF('2026 AC'!$B$3:$B$254,"*"&$D57&"*",'2026 AC'!F$3:F$254) -> 0 | BE57: =SUMIF('2026 AC'!$B$3:$B$254,"*"&$D57&"*",'2026 AC'!G$3:G$254) -> 0 | BF57: =SUMIF('2026 AC'!$B$3:$B$254,"*"&$D57&"*",'2026 AC'!H$3:H$254) -> 0 | BG57: =SUMIF('2026 AC'!$B$3:$B$254,"*"&$D57&"*",'2026 AC'!I$3:I$254) -> 0 | BH57: =SUMIF('2026 AC'!$B$3:$B$254,"*"&$D57&"*",'2026 AC'!J$3:J$254) -> 0 | ... BL57: =SUMIF('2026 AC'!$B$3:$B$254,"*"&$D57&"*",'2026 AC'!N$3:N$254) -> 0 | BM57: =SUM(BA57:BL57) -> 45 | BN57: =SUM(BA57:BC57) -> 45 | BO57: =SUM(BD57:BF57) -> 0 | BP57: =SUM(BG57:BI57) -> 0 | BQ57: =SUM(BJ57:BL57) -> 0 | BR57: =SUM(BN57:BQ57) -> 45
A58: SUPPLY LABOUR CHARGE | B58: 500-L001 | C58: SUPPLY LABOUR CHARGE | D58: 500-L001 | E58: =SUMIF($BA$6:$BL$6,$E$6,$BA58:$BL58) -> 0 | F58: =SUMIF($AH$6:$AS$6,$F$6,$AH58:$AS58) -> 0 | G58: =IFERROR((E58-F58)/F58,0) -> 0 | H58: =SUMIF($BN$6:$BR$6,$H$6,$BN58:$BR58) -> 0 | I58: =SUMIF($AU$6:$AY$6,$I$6,$AU58:$AY58) -> 0 | J58: =IFERROR((H58-I58)/I58,0) -> 0 | K58: =BM58 -> 0 | L58: =SUM(AH58:AM58) -> 0 | M58: =IFERROR((K58-L58)/L58,0) -> 0 | O58: =SUMIF('2024 AC'!$B$3:$B$250,"*"&$D58&"*",'2024 AC'!C$3:C$250) -> 1335.6 | P58: =SUMIF('2024 AC'!$B$3:$B$250,"*"&$D58&"*",'2024 AC'!D$3:D$250) -> 349.06 | Q58: =SUMIF('2024 AC'!$B$3:$B$250,"*"&$D58&"*",'2024 AC'!E$3:E$250) -> 0 | R58: =SUMIF('2024 AC'!$B$3:$B$250,"*"&$D58&"*",'2024 AC'!F$3:F$250) -> 0 | S58: =SUMIF('2024 AC'!$B$3:$B$250,"*"&$D58&"*",'2024 AC'!G$3:G$250) -> 0 | T58: =SUMIF('2024 AC'!$B$3:$B$250,"*"&$D58&"*",'2024 AC'!H$3:H$250) -> 0 | U58: =SUMIF('2024 AC'!$B$3:$B$250,"*"&$D58&"*",'2024 AC'!I$3:I$250) -> 0 | V58: =SUMIF('2024 AC'!$B$3:$B$250,"*"&$D58&"*",'2024 AC'!J$3:J$250) -> 0 | ... Z58: =SUMIF('2024 AC'!$B$3:$B$250,"*"&$D58&"*",'2024 AC'!N$3:N$250) -> 0 | AA58: =SUM(O58:Z58) -> 1684.66 | AB58: =SUM(O58:Q58) -> 1684.66 | AC58: =SUM(R58:T58) -> 0 | AD58: =SUM(U58:W58) -> 0 | AE58: =SUM(X58:Z58) -> 0 | AF58: =SUM(AB58:AE58) -> 1684.66 | AH58: =SUMIF('2025 AC'!$B$3:$B$250,"*"&$D58&"*",'2025 AC'!C$3:C$250) -> 0 | AI58: =SUMIF('2025 AC'!$B$3:$B$250,"*"&$D58&"*",'2025 AC'!D$3:D$250) -> 0 | AJ58: =SUMIF('2025 AC'!$B$3:$B$250,"*"&$D58&"*",'2025 AC'!E$3:E$250) -> 0 | AK58: =SUMIF('2025 AC'!$B$3:$B$250,"*"&$D58&"*",'2025 AC'!F$3:F$250) -> 0 | AL58: =SUMIF('2025 AC'!$B$3:$B$250,"*"&$D58&"*",'2025 AC'!G$3:G$250) -> 0 | AM58: =SUMIF('2025 AC'!$B$3:$B$250,"*"&$D58&"*",'2025 AC'!H$3:H$250) -> 0 | AN58: =SUMIF('2025 AC'!$B$3:$B$250,"*"&$D58&"*",'2025 AC'!I$3:I$250) -> 0 | AO58: =SUMIF('2025 AC'!$B$3:$B$250,"*"&$D58&"*",'2025 AC'!J$3:J$250) -> 0 | ... AS58: =SUMIF('2025 AC'!$B$3:$B$250,"*"&$D58&"*",'2025 AC'!N$3:N$250) -> 0 | AT58: =SUM(AH58:AS58) -> 0 | AU58: =SUM(AH58:AJ58) -> 0 | AV58: =SUM(AK58:AM58) -> 0 | AW58: =SUM(AN58:AP58) -> 0 | AX58: =SUM(AQ58:AS58) -> 0 | AY58: =SUM(AU58:AX58) -> 0 | BA58: =SUMIF('2026 AC'!$B$3:$B$254,"*"&$D58&"*",'2026 AC'!C$3:C$254) -> 0 | BB58: =SUMIF('2026 AC'!$B$3:$B$254,"*"&$D58&"*",'2026 AC'!D$3:D$254) -> 0 | BC58: =SUMIF('2026 AC'!$B$3:$B$254,"*"&$D58&"*",'2026 AC'!E$3:E$254) -> 0 | BD58: =SUMIF('2026 AC'!$B$3:$B$254,"*"&$D58&"*",'2026 AC'!F$3:F$254) -> 0 | BE58: =SUMIF('2026 AC'!$B$3:$B$254,"*"&$D58&"*",'2026 AC'!G$3:G$254) -> 0 | BF58: =SUMIF('2026 AC'!$B$3:$B$254,"*"&$D58&"*",'2026 AC'!H$3:H$254) -> 0 | BG58: =SUMIF('2026 AC'!$B$3:$B$254,"*"&$D58&"*",'2026 AC'!I$3:I$254) -> 0 | BH58: =SUMIF('2026 AC'!$B$3:$B$254,"*"&$D58&"*",'2026 AC'!J$3:J$254) -> 0 | ... BL58: =SUMIF('2026 AC'!$B$3:$B$254,"*"&$D58&"*",'2026 AC'!N$3:N$254) -> 0 | BM58: =SUM(BA58:BL58) -> 0 | BN58: =SUM(BA58:BC58) -> 0 | BO58: =SUM(BD58:BF58) -> 0 | BP58: =SUM(BG58:BI58) -> 0 | BQ58: =SUM(BJ58:BL58) -> 0 | BR58: =SUM(BN58:BQ58) -> 0
A59: SWIMMING POOL CHARGE | B59: 500-SP01 | C59: SWIMMING POOL CHARGE | D59: 500-SP01 | E59: =SUMIF($BA$6:$BL$6,$E$6,$BA59:$BL59) -> 0 | F59: =SUMIF($AH$6:$AS$6,$F$6,$AH59:$AS59) -> 0 | G59: =IFERROR((E59-F59)/F59,1) -> 1 | H59: =SUMIF($BN$6:$BR$6,$H$6,$BN59:$BR59) -> 0 | I59: =SUMIF($AU$6:$AY$6,$I$6,$AU59:$AY59) -> 150 | J59: =IFERROR((H59-I59)/I59,1) -> -1 | K59: =BM59 -> 45 | L59: =SUM(AH59:AM59) -> 150 | M59: =IFERROR((K59-L59)/L59,1) -> -0.7 | O59: =SUMIF('2024 AC'!$B$3:$B$250,"*"&$D59&"*",'2024 AC'!C$3:C$250) -> 0 | P59: =SUMIF('2024 AC'!$B$3:$B$250,"*"&$D59&"*",'2024 AC'!D$3:D$250) -> 0 | Q59: =SUMIF('2024 AC'!$B$3:$B$250,"*"&$D59&"*",'2024 AC'!E$3:E$250) -> 381.36 | R59: =SUMIF('2024 AC'!$B$3:$B$250,"*"&$D59&"*",'2024 AC'!F$3:F$250) -> 0 | S59: =SUMIF('2024 AC'!$B$3:$B$250,"*"&$D59&"*",'2024 AC'!G$3:G$250) -> 0 | T59: =SUMIF('2024 AC'!$B$3:$B$250,"*"&$D59&"*",'2024 AC'!H$3:H$250) -> 0 | U59: =SUMIF('2024 AC'!$B$3:$B$250,"*"&$D59&"*",'2024 AC'!I$3:I$250) -> 0 | V59: =SUMIF('2024 AC'!$B$3:$B$250,"*"&$D59&"*",'2024 AC'!J$3:J$250) -> 0 | ... Z59: =SUMIF('2024 AC'!$B$3:$B$250,"*"&$D59&"*",'2024 AC'!N$3:N$250) -> 30 | AA59: =SUM(O59:Z59) -> 771.36 | AB59: =SUM(O59:Q59) -> 381.36 | AC59: =SUM(R59:T59) -> 0 | AD59: =SUM(U59:W59) -> 0 | AE59: =SUM(X59:Z59) -> 390 | AF59: =SUM(AB59:AE59) -> 771.36 | AH59: =SUMIF('2025 AC'!$B$3:$B$250,"*"&$D59&"*",'2025 AC'!C$3:C$250) -> 0 | AI59: =SUMIF('2025 AC'!$B$3:$B$250,"*"&$D59&"*",'2025 AC'!D$3:D$250) -> 0 | AJ59: =SUMIF('2025 AC'!$B$3:$B$250,"*"&$D59&"*",'2025 AC'!E$3:E$250) -> 0 | AK59: =SUMIF('2025 AC'!$B$3:$B$250,"*"&$D59&"*",'2025 AC'!F$3:F$250) -> 120 | AL59: =SUMIF('2025 AC'!$B$3:$B$250,"*"&$D59&"*",'2025 AC'!G$3:G$250) -> 30 | AM59: =SUMIF('2025 AC'!$B$3:$B$250,"*"&$D59&"*",'2025 AC'!H$3:H$250) -> 0 | AN59: =SUMIF('2025 AC'!$B$3:$B$250,"*"&$D59&"*",'2025 AC'!I$3:I$250) -> 30 | AO59: =SUMIF('2025 AC'!$B$3:$B$250,"*"&$D59&"*",'2025 AC'!J$3:J$250) -> 0 | ... AS59: =SUMIF('2025 AC'!$B$3:$B$250,"*"&$D59&"*",'2025 AC'!N$3:N$250) -> 0 | AT59: =SUM(AH59:AS59) -> 210 | AU59: =SUM(AH59:AJ59) -> 0 | AV59: =SUM(AK59:AM59) -> 150 | AW59: =SUM(AN59:AP59) -> 30 | AX59: =SUM(AQ59:AS59) -> 30 | AY59: =SUM(AU59:AX59) -> 210 | BA59: =SUMIF('2026 AC'!$B$3:$B$254,"*"&$D59&"*",'2026 AC'!C$3:C$254) -> 15 | BB59: =SUMIF('2026 AC'!$B$3:$B$254,"*"&$D59&"*",'2026 AC'!D$3:D$254) -> 0 | BC59: =SUMIF('2026 AC'!$B$3:$B$254,"*"&$D59&"*",'2026 AC'!E$3:E$254) -> 30 | BD59: =SUMIF('2026 AC'!$B$3:$B$254,"*"&$D59&"*",'2026 AC'!F$3:F$254) -> 0 | BE59: =SUMIF('2026 AC'!$B$3:$B$254,"*"&$D59&"*",'2026 AC'!G$3:G$254) -> 0 | BF59: =SUMIF('2026 AC'!$B$3:$B$254,"*"&$D59&"*",'2026 AC'!H$3:H$254) -> 0 | BG59: =SUMIF('2026 AC'!$B$3:$B$254,"*"&$D59&"*",'2026 AC'!I$3:I$254) -> 0 | BH59: =SUMIF('2026 AC'!$B$3:$B$254,"*"&$D59&"*",'2026 AC'!J$3:J$254) -> 0 | ... BL59: =SUMIF('2026 AC'!$B$3:$B$254,"*"&$D59&"*",'2026 AC'!N$3:N$254) -> 0 | BM59: =SUM(BA59:BL59) -> 45 | BN59: =SUM(BA59:BC59) -> 45 | BO59: =SUM(BD59:BF59) -> 0 | BP59: =SUM(BG59:BI59) -> 0 | BQ59: =SUM(BJ59:BL59) -> 0 | BR59: =SUM(BN59:BQ59) -> 45
A60: CLEANING SERVICE REVENUE | B60: 500-5000 | C60: OTHER INCOME | D60: 540-0000 | E60: =SUMIF($BA$6:$BL$6,$E$6,$BA60:$BL60) -> 2500 | F60: =SUMIF($AH$6:$AS$6,$F$6,$AH60:$AS60) -> 0 | G60: =IFERROR((E60-F60)/F60,1) -> 1 | H60: =SUMIF($BN$6:$BR$6,$H$6,$BN60:$BR60) -> 7500 | I60: =SUMIF($AU$6:$AY$6,$I$6,$AU60:$AY60) -> 0 | J60: =IFERROR((H60-I60)/I60,1) -> 1 | K60: =BM60 -> 15000 | L60: =SUM(AH60:AM60) -> 0 | M60: =IFERROR((K60-L60)/L60,1) -> 1 | O60: =SUMIF('2024 AC'!$B$3:$B$250,"*"&$D60&"*",'2024 AC'!C$3:C$250) -> 0 | P60: =SUMIF('2024 AC'!$B$3:$B$250,"*"&$D60&"*",'2024 AC'!D$3:D$250) -> 0 | Q60: =SUMIF('2024 AC'!$B$3:$B$250,"*"&$D60&"*",'2024 AC'!E$3:E$250) -> 0 | R60: =SUMIF('2024 AC'!$B$3:$B$250,"*"&$D60&"*",'2024 AC'!F$3:F$250) -> 0 | S60: =SUMIF('2024 AC'!$B$3:$B$250,"*"&$D60&"*",'2024 AC'!G$3:G$250) -> 0 | T60: =SUMIF('2024 AC'!$B$3:$B$250,"*"&$D60&"*",'2024 AC'!H$3:H$250) -> 0 | U60: =SUMIF('2024 AC'!$B$3:$B$250,"*"&$D60&"*",'2024 AC'!I$3:I$250) -> 0 | V60: =SUMIF('2024 AC'!$B$3:$B$250,"*"&$D60&"*",'2024 AC'!J$3:J$250) -> 0 | ... Z60: =SUMIF('2024 AC'!$B$3:$B$250,"*"&$D60&"*",'2024 AC'!N$3:N$250) -> 0 | AA60: =SUM(O60:Z60) -> 0 | AB60: =SUM(O60:Q60) -> 0 | AC60: =SUM(R60:T60) -> 0 | AD60: =SUM(U60:W60) -> 0 | AE60: =SUM(X60:Z60) -> 0 | AF60: =SUM(AB60:AE60) -> 0 | AH60: =SUMIF('2025 AC'!$B$3:$B$250,"*"&$D60&"*",'2025 AC'!C$3:C$250) -> 0 | AI60: =SUMIF('2025 AC'!$B$3:$B$250,"*"&$D60&"*",'2025 AC'!D$3:D$250) -> 0 | AJ60: =SUMIF('2025 AC'!$B$3:$B$250,"*"&$D60&"*",'2025 AC'!E$3:E$250) -> 0 | AK60: =SUMIF('2025 AC'!$B$3:$B$250,"*"&$D60&"*",'2025 AC'!F$3:F$250) -> 0 | AL60: =SUMIF('2025 AC'!$B$3:$B$250,"*"&$D60&"*",'2025 AC'!G$3:G$250) -> 0 | AM60: =SUMIF('2025 AC'!$B$3:$B$250,"*"&$D60&"*",'2025 AC'!H$3:H$250) -> 0 | AN60: =SUMIF('2025 AC'!$B$3:$B$250,"*"&$D60&"*",'2025 AC'!I$3:I$250) -> 0 | AO60: =SUMIF('2025 AC'!$B$3:$B$250,"*"&$D60&"*",'2025 AC'!J$3:J$250) -> 0 | ... AS60: =SUMIF('2025 AC'!$B$3:$B$250,"*"&$D60&"*",'2025 AC'!N$3:N$250) -> 22500 | AT60: =SUM(AH60:AS60) -> 22500 | AU60: =SUM(AH60:AJ60) -> 0 | AV60: =SUM(AK60:AM60) -> 0 | AW60: =SUM(AN60:AP60) -> 0 | AX60: =SUM(AQ60:AS60) -> 22500 | AY60: =SUM(AU60:AX60) -> 22500 | BA60: =SUMIF('2026 AC'!$B$3:$B$254,"*"&$D60&"*",'2026 AC'!C$3:C$254) -> 2500 | BB60: =SUMIF('2026 AC'!$B$3:$B$254,"*"&$D60&"*",'2026 AC'!D$3:D$254) -> 2500 | BC60: =SUMIF('2026 AC'!$B$3:$B$254,"*"&$D60&"*",'2026 AC'!E$3:E$254) -> 2500 | BD60: =SUMIF('2026 AC'!$B$3:$B$254,"*"&$D60&"*",'2026 AC'!F$3:F$254) -> 2500 | BE60: =SUMIF('2026 AC'!$B$3:$B$254,"*"&$D60&"*",'2026 AC'!G$3:G$254) -> 2500 | BF60: =SUMIF('2026 AC'!$B$3:$B$254,"*"&$D60&"*",'2026 AC'!H$3:H$254) -> 2500 | BG60: =SUMIF('2026 AC'!$B$3:$B$254,"*"&$D60&"*",'2026 AC'!I$3:I$254) -> 0 | BH60: =SUMIF('2026 AC'!$B$3:$B$254,"*"&$D60&"*",'2026 AC'!J$3:J$254) -> 0 | ... BL60: =SUMIF('2026 AC'!$B$3:$B$254,"*"&$D60&"*",'2026 AC'!N$3:N$254) -> 0 | BM60: =SUM(BA60:BL60) -> 15000 | BN60: =SUM(BA60:BC60) -> 7500 | BO60: =SUM(BD60:BF60) -> 7500 | BP60: =SUM(BG60:BI60) -> 0 | BQ60: =SUM(BJ60:BL60) -> 0 | BR60: =SUM(BN60:BQ60) -> 15000
C61: OUTSOURCED GAJAH3 CAFE RENTAL | D61: 540-1000 | E61: =SUMIF($BA$6:$BL$6,$E$6,$BA61:$BL61) -> 2500 | F61: =SUMIF($AH$6:$AS$6,$F$6,$AH61:$AS61) -> 0 | G61: =IFERROR((E61-F61)/F61,1) -> 1 | H61: =SUMIF($BN$6:$BR$6,$H$6,$BN61:$BR61) -> 7500 | I61: =SUMIF($AU$6:$AY$6,$I$6,$AU61:$AY61) -> 0 | J61: =IFERROR((H61-I61)/I61,1) -> 1 | K61: =BM61 -> 15000 | L61: =SUM(AH61:AM61) -> 0 | M61: =IFERROR((K61-L61)/L61,1) -> 1 | O61: =SUMIF('2024 AC'!$B$3:$B$250,"*"&$D61&"*",'2024 AC'!C$3:C$250) -> 0 | P61: =SUMIF('2024 AC'!$B$3:$B$250,"*"&$D61&"*",'2024 AC'!D$3:D$250) -> 0 | Q61: =SUMIF('2024 AC'!$B$3:$B$250,"*"&$D61&"*",'2024 AC'!E$3:E$250) -> 0 | R61: =SUMIF('2024 AC'!$B$3:$B$250,"*"&$D61&"*",'2024 AC'!F$3:F$250) -> 0 | S61: =SUMIF('2024 AC'!$B$3:$B$250,"*"&$D61&"*",'2024 AC'!G$3:G$250) -> 0 | T61: =SUMIF('2024 AC'!$B$3:$B$250,"*"&$D61&"*",'2024 AC'!H$3:H$250) -> 0 | U61: =SUMIF('2024 AC'!$B$3:$B$250,"*"&$D61&"*",'2024 AC'!I$3:I$250) -> 0 | V61: =SUMIF('2024 AC'!$B$3:$B$250,"*"&$D61&"*",'2024 AC'!J$3:J$250) -> 0 | ... Z61: =SUMIF('2024 AC'!$B$3:$B$250,"*"&$D61&"*",'2024 AC'!N$3:N$250) -> 0 | AA61: =SUM(O61:Z61) -> 0 | AB61: =SUM(O61:Q61) -> 0 | AC61: =SUM(R61:T61) -> 0 | AD61: =SUM(U61:W61) -> 0 | AE61: =SUM(X61:Z61) -> 0 | AF61: =SUM(AB61:AE61) -> 0 | AH61: =SUMIF('2025 AC'!$B$3:$B$250,"*"&$D61&"*",'2025 AC'!C$3:C$250) -> 0 | AI61: =SUMIF('2025 AC'!$B$3:$B$250,"*"&$D61&"*",'2025 AC'!D$3:D$250) -> 0 | AJ61: =SUMIF('2025 AC'!$B$3:$B$250,"*"&$D61&"*",'2025 AC'!E$3:E$250) -> 0 | AK61: =SUMIF('2025 AC'!$B$3:$B$250,"*"&$D61&"*",'2025 AC'!F$3:F$250) -> 0 | AL61: =SUMIF('2025 AC'!$B$3:$B$250,"*"&$D61&"*",'2025 AC'!G$3:G$250) -> 0 | AM61: =SUMIF('2025 AC'!$B$3:$B$250,"*"&$D61&"*",'2025 AC'!H$3:H$250) -> 0 | AN61: =SUMIF('2025 AC'!$B$3:$B$250,"*"&$D61&"*",'2025 AC'!I$3:I$250) -> 0 | AO61: =SUMIF('2025 AC'!$B$3:$B$250,"*"&$D61&"*",'2025 AC'!J$3:J$250) -> 0 | ... AS61: =SUMIF('2025 AC'!$B$3:$B$250,"*"&$D61&"*",'2025 AC'!N$3:N$250) -> 22500 | AT61: =SUM(AH61:AS61) -> 22500 | AU61: =SUM(AH61:AJ61) -> 0 | AV61: =SUM(AK61:AM61) -> 0 | AW61: =SUM(AN61:AP61) -> 0 | AX61: =SUM(AQ61:AS61) -> 22500 | AY61: =SUM(AU61:AX61) -> 22500 | BA61: =SUMIF('2026 AC'!$B$3:$B$254,"*"&$D61&"*",'2026 AC'!C$3:C$254) -> 2500 | BB61: =SUMIF('2026 AC'!$B$3:$B$254,"*"&$D61&"*",'2026 AC'!D$3:D$254) -> 2500 | BC61: =SUMIF('2026 AC'!$B$3:$B$254,"*"&$D61&"*",'2026 AC'!E$3:E$254) -> 2500 | BD61: =SUMIF('2026 AC'!$B$3:$B$254,"*"&$D61&"*",'2026 AC'!F$3:F$254) -> 2500 | BE61: =SUMIF('2026 AC'!$B$3:$B$254,"*"&$D61&"*",'2026 AC'!G$3:G$254) -> 2500 | BF61: =SUMIF('2026 AC'!$B$3:$B$254,"*"&$D61&"*",'2026 AC'!H$3:H$254) -> 2500 | BG61: =SUMIF('2026 AC'!$B$3:$B$254,"*"&$D61&"*",'2026 AC'!I$3:I$254) -> 0 | BH61: =SUMIF('2026 AC'!$B$3:$B$254,"*"&$D61&"*",'2026 AC'!J$3:J$254) -> 0 | ... BL61: =SUMIF('2026 AC'!$B$3:$B$254,"*"&$D61&"*",'2026 AC'!N$3:N$254) -> 0 | BM61: =SUM(BA61:BL61) -> 15000 | BN61: =SUM(BA61:BC61) -> 7500 | BO61: =SUM(BD61:BF61) -> 7500 | BP61: =SUM(BG61:BI61) -> 0 | BQ61: =SUM(BJ61:BL61) -> 0 | BR61: =SUM(BN61:BQ61) -> 15000
E62: =SUMIF($BA$6:$BL$6,$E$6,$BA62:$BL62) -> 0 | F62: =SUMIF($AH$6:$AS$6,$F$6,$AH62:$AS62) -> 0 | H62: =SUMIF($BN$6:$BR$6,$H$6,$BN62:$BR62) -> 0 | I62: =SUMIF($AU$6:$AY$6,$I$6,$AU62:$AY62) -> 0 | K62: =BM62 -> 0 | L62: =SUM(AH62:AM62) -> 0 | AA62: =SUM(O62:Z62) -> 0 | AB62: =SUM(O62:Q62) -> 0 | AC62: =SUM(R62:T62) -> 0 | AD62: =SUM(U62:W62) -> 0 | AE62: =SUM(X62:Z62) -> 0 | AF62: =SUM(AB62:AE62) -> 0 | AU62: =SUM(AH62:AJ62) -> 0 | AV62: =SUM(AK62:AM62) -> 0 | AW62: =SUM(AN62:AP62) -> 0 | AX62: =SUM(AQ62:AS62) -> 0 | AY62: =SUM(AU62:AX62) -> 0 | BN62: =SUM(BA62:BC62) -> 0 | BO62: =SUM(BD62:BF62) -> 0 | BP62: =SUM(BG62:BI62) -> 0 | BQ62: =SUM(BJ62:BL62) -> 0 | BR62: =SUM(BN62:BQ62) -> 0
C63: SALES ADJUSTMENTS | E63: =SUMIF($BA$6:$BL$6,$E$6,$BA63:$BL63) -> 0 | F63: =SUMIF($AH$6:$AS$6,$F$6,$AH63:$AS63) -> 0 | H63: =SUMIF($BN$6:$BR$6,$H$6,$BN63:$BR63) -> 0 | I63: =SUMIF($AU$6:$AY$6,$I$6,$AU63:$AY63) -> 0 | K63: =BM63 -> 0 | L63: =SUM(AH63:AM63) -> 0 | AA63: =SUM(O63:Z63) -> 0 | AB63: =SUM(O63:Q63) -> 0 | AC63: =SUM(R63:T63) -> 0 | AD63: =SUM(U63:W63) -> 0 | AE63: =SUM(X63:Z63) -> 0 | AF63: =SUM(AB63:AE63) -> 0 | AU63: =SUM(AH63:AJ63) -> 0 | AV63: =SUM(AK63:AM63) -> 0 | AW63: =SUM(AN63:AP63) -> 0 | AX63: =SUM(AQ63:AS63) -> 0 | AY63: =SUM(AU63:AX63) -> 0 | BN63: =SUM(BA63:BC63) -> 0 | BO63: =SUM(BD63:BF63) -> 0 | BP63: =SUM(BG63:BI63) -> 0 | BQ63: =SUM(BJ63:BL63) -> 0 | BR63: =SUM(BN63:BQ63) -> 0
E64: =SUMIF($BA$6:$BL$6,$E$6,$BA64:$BL64) -> 0 | F64: =SUMIF($AH$6:$AS$6,$F$6,$AH64:$AS64) -> 0 | H64: =SUMIF($BN$6:$BR$6,$H$6,$BN64:$BR64) -> 0 | I64: =SUMIF($AU$6:$AY$6,$I$6,$AU64:$AY64) -> 0 | K64: =BM64 -> 0 | L64: =SUM(AH64:AM64) -> 0 | AA64: =SUM(O64:Z64) -> 0 | AB64: =SUM(O64:Q64) -> 0 | AC64: =SUM(R64:T64) -> 0 | AD64: =SUM(U64:W64) -> 0 | AE64: =SUM(X64:Z64) -> 0 | AF64: =SUM(AB64:AE64) -> 0 | AU64: =SUM(AH64:AJ64) -> 0 | AV64: =SUM(AK64:AM64) -> 0 | AW64: =SUM(AN64:AP64) -> 0 | AX64: =SUM(AQ64:AS64) -> 0 | AY64: =SUM(AU64:AX64) -> 0 | BN64: =SUM(BA64:BC64) -> 0 | BO64: =SUM(BD64:BF64) -> 0 | BP64: =SUM(BG64:BI64) -> 0 | BQ64: =SUM(BJ64:BL64) -> 0 | BR64: =SUM(BN64:BQ64) -> 0
C65: SALE INWARDS | D65: 510-0000 | E65: =SUMIF($BA$6:$BL$6,$E$6,$BA65:$BL65) -> 0 | F65: =SUMIF($AH$6:$AS$6,$F$6,$AH65:$AS65) -> 0 | G65: =IFERROR((E65-F65)/F65,0) -> 0 | H65: =SUMIF($BN$6:$BR$6,$H$6,$BN65:$BR65) -> 0 | I65: =SUMIF($AU$6:$AY$6,$I$6,$AU65:$AY65) -> 0 | J65: =IFERROR((H65-I65)/I65,0) -> 0 | K65: =BM65 -> 0 | L65: =SUM(AH65:AM65) -> 0 | M65: =IFERROR((K65-L65)/L65,0) -> 0 | O65: =SUMIF('2024 AC'!$B$3:$B$250,"*"&$D65&"*",'2024 AC'!C$3:C$250) -> 0 | P65: =SUMIF('2024 AC'!$B$3:$B$250,"*"&$D65&"*",'2024 AC'!D$3:D$250) -> 0 | Q65: =SUMIF('2024 AC'!$B$3:$B$250,"*"&$D65&"*",'2024 AC'!E$3:E$250) -> 0 | R65: =SUMIF('2024 AC'!$B$3:$B$250,"*"&$D65&"*",'2024 AC'!F$3:F$250) -> 0 | S65: =SUMIF('2024 AC'!$B$3:$B$250,"*"&$D65&"*",'2024 AC'!G$3:G$250) -> 0 | T65: =SUMIF('2024 AC'!$B$3:$B$250,"*"&$D65&"*",'2024 AC'!H$3:H$250) -> 0 | U65: =SUMIF('2024 AC'!$B$3:$B$250,"*"&$D65&"*",'2024 AC'!I$3:I$250) -> 0 | V65: =SUMIF('2024 AC'!$B$3:$B$250,"*"&$D65&"*",'2024 AC'!J$3:J$250) -> 0 | ... Z65: =SUMIF('2024 AC'!$B$3:$B$250,"*"&$D65&"*",'2024 AC'!N$3:N$250) -> 0 | AA65: =SUM(O65:Z65) -> 0 | AB65: =SUM(O65:Q65) -> 0 | AC65: =SUM(R65:T65) -> 0 | AD65: =SUM(U65:W65) -> 0 | AE65: =SUM(X65:Z65) -> 0 | AF65: =SUM(AB65:AE65) -> 0 | AH65: =SUMIF('2025 AC'!$B$3:$B$250,"*"&$D65&"*",'2025 AC'!C$3:C$250) -> 0 | AI65: =SUMIF('2025 AC'!$B$3:$B$250,"*"&$D65&"*",'2025 AC'!D$3:D$250) -> 0 | AJ65: =SUMIF('2025 AC'!$B$3:$B$250,"*"&$D65&"*",'2025 AC'!E$3:E$250) -> 0 | AK65: =SUMIF('2025 AC'!$B$3:$B$250,"*"&$D65&"*",'2025 AC'!F$3:F$250) -> 0 | AL65: =SUMIF('2025 AC'!$B$3:$B$250,"*"&$D65&"*",'2025 AC'!G$3:G$250) -> 0 | AM65: =SUMIF('2025 AC'!$B$3:$B$250,"*"&$D65&"*",'2025 AC'!H$3:H$250) -> 0 | AN65: =SUMIF('2025 AC'!$B$3:$B$250,"*"&$D65&"*",'2025 AC'!I$3:I$250) -> 0 | AO65: =SUMIF('2025 AC'!$B$3:$B$250,"*"&$D65&"*",'2025 AC'!J$3:J$250) -> 0 | ... AS65: =SUMIF('2025 AC'!$B$3:$B$250,"*"&$D65&"*",'2025 AC'!N$3:N$250) -> 0 | AT65: =SUM(AH65:AS65) -> 0 | AU65: =SUM(AH65:AJ65) -> 0 | AV65: =SUM(AK65:AM65) -> 0 | AW65: =SUM(AN65:AP65) -> 0 | AX65: =SUM(AQ65:AS65) -> 0 | AY65: =SUM(AU65:AX65) -> 0 | BA65: =SUMIF('2026 AC'!$B$3:$B$254,"*"&$D65&"*",'2026 AC'!C$3:C$254) -> 0 | BB65: =SUMIF('2026 AC'!$B$3:$B$254,"*"&$D65&"*",'2026 AC'!D$3:D$254) -> 0 | BC65: =SUMIF('2026 AC'!$B$3:$B$254,"*"&$D65&"*",'2026 AC'!E$3:E$254) -> 0 | BD65: =SUMIF('2026 AC'!$B$3:$B$254,"*"&$D65&"*",'2026 AC'!F$3:F$254) -> 0 | BE65: =SUMIF('2026 AC'!$B$3:$B$254,"*"&$D65&"*",'2026 AC'!G$3:G$254) -> 0 | BF65: =SUMIF('2026 AC'!$B$3:$B$254,"*"&$D65&"*",'2026 AC'!H$3:H$254) -> 0 | BG65: =SUMIF('2026 AC'!$B$3:$B$254,"*"&$D65&"*",'2026 AC'!I$3:I$254) -> 0 | BH65: =SUMIF('2026 AC'!$B$3:$B$254,"*"&$D65&"*",'2026 AC'!J$3:J$254) -> 0 | ... BL65: =SUMIF('2026 AC'!$B$3:$B$254,"*"&$D65&"*",'2026 AC'!N$3:N$254) -> 0 | BM65: =SUM(BA65:BL65) -> 0 | BN65: =SUM(BA65:BC65) -> 0 | BO65: =SUM(BD65:BF65) -> 0 | BP65: =SUM(BG65:BI65) -> 0 | BQ65: =SUM(BJ65:BL65) -> 0 | BR65: =SUM(BN65:BQ65) -> 0
C66: REVENUE ADJUSTMENT | D66: 520-0000 | E66: =SUMIF($BA$6:$BL$6,$E$6,$BA66:$BL66) -> 0 | F66: =SUMIF($AH$6:$AS$6,$F$6,$AH66:$AS66) -> 0 | G66: =IFERROR((E66-F66)/F66,0) -> 0 | H66: =SUMIF($BN$6:$BR$6,$H$6,$BN66:$BR66) -> 0 | I66: =SUMIF($AU$6:$AY$6,$I$6,$AU66:$AY66) -> 0 | J66: =IFERROR((H66-I66)/I66,0) -> 0 | K66: =BM66 -> 0 | L66: =SUM(AH66:AM66) -> 0 | M66: =IFERROR((K66-L66)/L66,0) -> 0 | O66: =SUMIF('2024 AC'!$B$3:$B$250,"*"&$D66&"*",'2024 AC'!C$3:C$250) -> 0 | P66: =SUMIF('2024 AC'!$B$3:$B$250,"*"&$D66&"*",'2024 AC'!D$3:D$250) -> 0 | Q66: =SUMIF('2024 AC'!$B$3:$B$250,"*"&$D66&"*",'2024 AC'!E$3:E$250) -> 0 | R66: =SUMIF('2024 AC'!$B$3:$B$250,"*"&$D66&"*",'2024 AC'!F$3:F$250) -> 0 | S66: =SUMIF('2024 AC'!$B$3:$B$250,"*"&$D66&"*",'2024 AC'!G$3:G$250) -> 0 | T66: =SUMIF('2024 AC'!$B$3:$B$250,"*"&$D66&"*",'2024 AC'!H$3:H$250) -> 0 | U66: =SUMIF('2024 AC'!$B$3:$B$250,"*"&$D66&"*",'2024 AC'!I$3:I$250) -> 0 | V66: =SUMIF('2024 AC'!$B$3:$B$250,"*"&$D66&"*",'2024 AC'!J$3:J$250) -> 0 | ... Z66: =SUMIF('2024 AC'!$B$3:$B$250,"*"&$D66&"*",'2024 AC'!N$3:N$250) -> 0 | AA66: =SUM(O66:Z66) -> 0 | AB66: =SUM(O66:Q66) -> 0 | AC66: =SUM(R66:T66) -> 0 | AD66: =SUM(U66:W66) -> 0 | AE66: =SUM(X66:Z66) -> 0 | AF66: =SUM(AB66:AE66) -> 0 | AH66: =SUMIF('2025 AC'!$B$3:$B$250,"*"&$D66&"*",'2025 AC'!C$3:C$250) -> 0 | AI66: =SUMIF('2025 AC'!$B$3:$B$250,"*"&$D66&"*",'2025 AC'!D$3:D$250) -> 0 | AJ66: =SUMIF('2025 AC'!$B$3:$B$250,"*"&$D66&"*",'2025 AC'!E$3:E$250) -> 0 | AK66: =SUMIF('2025 AC'!$B$3:$B$250,"*"&$D66&"*",'2025 AC'!F$3:F$250) -> 0 | AL66: =SUMIF('2025 AC'!$B$3:$B$250,"*"&$D66&"*",'2025 AC'!G$3:G$250) -> 0 | AM66: =SUMIF('2025 AC'!$B$3:$B$250,"*"&$D66&"*",'2025 AC'!H$3:H$250) -> 0 | AN66: =SUMIF('2025 AC'!$B$3:$B$250,"*"&$D66&"*",'2025 AC'!I$3:I$250) -> 0 | AO66: =SUMIF('2025 AC'!$B$3:$B$250,"*"&$D66&"*",'2025 AC'!J$3:J$250) -> 0 | ... AS66: =SUMIF('2025 AC'!$B$3:$B$250,"*"&$D66&"*",'2025 AC'!N$3:N$250) -> 0 | AT66: =SUM(AH66:AS66) -> 0 | AU66: =SUM(AH66:AJ66) -> 0 | AV66: =SUM(AK66:AM66) -> 0 | AW66: =SUM(AN66:AP66) -> 0 | AX66: =SUM(AQ66:AS66) -> 0 | AY66: =SUM(AU66:AX66) -> 0 | BA66: =SUMIF('2026 AC'!$B$3:$B$254,"*"&$D66&"*",'2026 AC'!C$3:C$254) -> 0 | BB66: =SUMIF('2026 AC'!$B$3:$B$254,"*"&$D66&"*",'2026 AC'!D$3:D$254) -> 0 | BC66: =SUMIF('2026 AC'!$B$3:$B$254,"*"&$D66&"*",'2026 AC'!E$3:E$254) -> 0 | BD66: =SUMIF('2026 AC'!$B$3:$B$254,"*"&$D66&"*",'2026 AC'!F$3:F$254) -> 0 | BE66: =SUMIF('2026 AC'!$B$3:$B$254,"*"&$D66&"*",'2026 AC'!G$3:G$254) -> 0 | BF66: =SUMIF('2026 AC'!$B$3:$B$254,"*"&$D66&"*",'2026 AC'!H$3:H$254) -> 0 | BG66: =SUMIF('2026 AC'!$B$3:$B$254,"*"&$D66&"*",'2026 AC'!I$3:I$254) -> 0 | BH66: =SUMIF('2026 AC'!$B$3:$B$254,"*"&$D66&"*",'2026 AC'!J$3:J$254) -> 0 | ... BL66: =SUMIF('2026 AC'!$B$3:$B$254,"*"&$D66&"*",'2026 AC'!N$3:N$254) -> 0 | BM66: =SUM(BA66:BL66) -> 0 | BN66: =SUM(BA66:BC66) -> 0 | BO66: =SUM(BD66:BF66) -> 0 | BP66: =SUM(BG66:BI66) -> 0 | BQ66: =SUM(BJ66:BL66) -> 0 | BR66: =SUM(BN66:BQ66) -> 0
C67: ROOM ADJUSTMENT | D67: 520-1001 | E67: =SUMIF($BA$6:$BL$6,$E$6,$BA67:$BL67) -> 0 | F67: =SUMIF($AH$6:$AS$6,$F$6,$AH67:$AS67) -> 0 | G67: =IFERROR((E67-F67)/F67,0) -> 0 | H67: =SUMIF($BN$6:$BR$6,$H$6,$BN67:$BR67) -> 0 | I67: =SUMIF($AU$6:$AY$6,$I$6,$AU67:$AY67) -> 0 | J67: =IFERROR((H67-I67)/I67,0) -> 0 | K67: =BM67 -> 0 | L67: =SUM(AH67:AM67) -> 0 | M67: =IFERROR((K67-L67)/L67,0) -> 0 | O67: =SUMIF('2024 AC'!$B$3:$B$250,"*"&$D67&"*",'2024 AC'!C$3:C$250) -> 0 | P67: =SUMIF('2024 AC'!$B$3:$B$250,"*"&$D67&"*",'2024 AC'!D$3:D$250) -> 0 | Q67: =SUMIF('2024 AC'!$B$3:$B$250,"*"&$D67&"*",'2024 AC'!E$3:E$250) -> 0 | R67: =SUMIF('2024 AC'!$B$3:$B$250,"*"&$D67&"*",'2024 AC'!F$3:F$250) -> 0 | S67: =SUMIF('2024 AC'!$B$3:$B$250,"*"&$D67&"*",'2024 AC'!G$3:G$250) -> 0 | T67: =SUMIF('2024 AC'!$B$3:$B$250,"*"&$D67&"*",'2024 AC'!H$3:H$250) -> 0 | U67: =SUMIF('2024 AC'!$B$3:$B$250,"*"&$D67&"*",'2024 AC'!I$3:I$250) -> 0 | V67: =SUMIF('2024 AC'!$B$3:$B$250,"*"&$D67&"*",'2024 AC'!J$3:J$250) -> 0 | ... Z67: =SUMIF('2024 AC'!$B$3:$B$250,"*"&$D67&"*",'2024 AC'!N$3:N$250) -> 0 | AA67: =SUM(O67:Z67) -> 0 | AB67: =SUM(O67:Q67) -> 0 | AC67: =SUM(R67:T67) -> 0 | AD67: =SUM(U67:W67) -> 0 | AE67: =SUM(X67:Z67) -> 0 | AF67: =SUM(AB67:AE67) -> 0 | AH67: =SUMIF('2025 AC'!$B$3:$B$250,"*"&$D67&"*",'2025 AC'!C$3:C$250) -> 0 | AI67: =SUMIF('2025 AC'!$B$3:$B$250,"*"&$D67&"*",'2025 AC'!D$3:D$250) -> 0 | AJ67: =SUMIF('2025 AC'!$B$3:$B$250,"*"&$D67&"*",'2025 AC'!E$3:E$250) -> 0 | AK67: =SUMIF('2025 AC'!$B$3:$B$250,"*"&$D67&"*",'2025 AC'!F$3:F$250) -> 0 | AL67: =SUMIF('2025 AC'!$B$3:$B$250,"*"&$D67&"*",'2025 AC'!G$3:G$250) -> 0 | AM67: =SUMIF('2025 AC'!$B$3:$B$250,"*"&$D67&"*",'2025 AC'!H$3:H$250) -> 0 | AN67: =SUMIF('2025 AC'!$B$3:$B$250,"*"&$D67&"*",'2025 AC'!I$3:I$250) -> 0 | AO67: =SUMIF('2025 AC'!$B$3:$B$250,"*"&$D67&"*",'2025 AC'!J$3:J$250) -> 0 | ... AS67: =SUMIF('2025 AC'!$B$3:$B$250,"*"&$D67&"*",'2025 AC'!N$3:N$250) -> 0 | AT67: =SUM(AH67:AS67) -> 0 | AU67: =SUM(AH67:AJ67) -> 0 | AV67: =SUM(AK67:AM67) -> 0 | AW67: =SUM(AN67:AP67) -> 0 | AX67: =SUM(AQ67:AS67) -> 0 | AY67: =SUM(AU67:AX67) -> 0 | BA67: =SUMIF('2026 AC'!$B$3:$B$254,"*"&$D67&"*",'2026 AC'!C$3:C$254) -> 0 | BB67: =SUMIF('2026 AC'!$B$3:$B$254,"*"&$D67&"*",'2026 AC'!D$3:D$254) -> 0 | BC67: =SUMIF('2026 AC'!$B$3:$B$254,"*"&$D67&"*",'2026 AC'!E$3:E$254) -> 0 | BD67: =SUMIF('2026 AC'!$B$3:$B$254,"*"&$D67&"*",'2026 AC'!F$3:F$254) -> 0 | BE67: =SUMIF('2026 AC'!$B$3:$B$254,"*"&$D67&"*",'2026 AC'!G$3:G$254) -> 0 | BF67: =SUMIF('2026 AC'!$B$3:$B$254,"*"&$D67&"*",'2026 AC'!H$3:H$254) -> 0 | BG67: =SUMIF('2026 AC'!$B$3:$B$254,"*"&$D67&"*",'2026 AC'!I$3:I$254) -> 0 | BH67: =SUMIF('2026 AC'!$B$3:$B$254,"*"&$D67&"*",'2026 AC'!J$3:J$254) -> 0 | ... BL67: =SUMIF('2026 AC'!$B$3:$B$254,"*"&$D67&"*",'2026 AC'!N$3:N$254) -> 0 | BM67: =SUM(BA67:BL67) -> 0 | BN67: =SUM(BA67:BC67) -> 0 | BO67: =SUM(BD67:BF67) -> 0 | BP67: =SUM(BG67:BI67) -> 0 | BQ67: =SUM(BJ67:BL67) -> 0 | BR67: =SUM(BN67:BQ67) -> 0
C68: BREAKFAST ADJUSTMENT | D68: 520-1003 | E68: =SUMIF($BA$6:$BL$6,$E$6,$BA68:$BL68) -> 0 | F68: =SUMIF($AH$6:$AS$6,$F$6,$AH68:$AS68) -> 0 | G68: =IFERROR((E68-F68)/F68,0) -> 0 | H68: =SUMIF($BN$6:$BR$6,$H$6,$BN68:$BR68) -> 0 | I68: =SUMIF($AU$6:$AY$6,$I$6,$AU68:$AY68) -> 0 | J68: =IFERROR((H68-I68)/I68,0) -> 0 | K68: =BM68 -> 0 | L68: =SUM(AH68:AM68) -> 0 | M68: =IFERROR((K68-L68)/L68,0) -> 0 | O68: =SUMIF('2024 AC'!$B$3:$B$250,"*"&$D68&"*",'2024 AC'!C$3:C$250) -> 0 | P68: =SUMIF('2024 AC'!$B$3:$B$250,"*"&$D68&"*",'2024 AC'!D$3:D$250) -> 0 | Q68: =SUMIF('2024 AC'!$B$3:$B$250,"*"&$D68&"*",'2024 AC'!E$3:E$250) -> 0 | R68: =SUMIF('2024 AC'!$B$3:$B$250,"*"&$D68&"*",'2024 AC'!F$3:F$250) -> 0 | S68: =SUMIF('2024 AC'!$B$3:$B$250,"*"&$D68&"*",'2024 AC'!G$3:G$250) -> 0 | T68: =SUMIF('2024 AC'!$B$3:$B$250,"*"&$D68&"*",'2024 AC'!H$3:H$250) -> 0 | U68: =SUMIF('2024 AC'!$B$3:$B$250,"*"&$D68&"*",'2024 AC'!I$3:I$250) -> 0 | V68: =SUMIF('2024 AC'!$B$3:$B$250,"*"&$D68&"*",'2024 AC'!J$3:J$250) -> 0 | ... Z68: =SUMIF('2024 AC'!$B$3:$B$250,"*"&$D68&"*",'2024 AC'!N$3:N$250) -> 0 | AA68: =SUM(O68:Z68) -> 0 | AB68: =SUM(O68:Q68) -> 0 | AC68: =SUM(R68:T68) -> 0 | AD68: =SUM(U68:W68) -> 0 | AE68: =SUM(X68:Z68) -> 0 | AF68: =SUM(AB68:AE68) -> 0 | AH68: =SUMIF('2025 AC'!$B$3:$B$250,"*"&$D68&"*",'2025 AC'!C$3:C$250) -> 0 | AI68: =SUMIF('2025 AC'!$B$3:$B$250,"*"&$D68&"*",'2025 AC'!D$3:D$250) -> 0 | AJ68: =SUMIF('2025 AC'!$B$3:$B$250,"*"&$D68&"*",'2025 AC'!E$3:E$250) -> 0 | AK68: =SUMIF('2025 AC'!$B$3:$B$250,"*"&$D68&"*",'2025 AC'!F$3:F$250) -> 0 | AL68: =SUMIF('2025 AC'!$B$3:$B$250,"*"&$D68&"*",'2025 AC'!G$3:G$250) -> 0 | AM68: =SUMIF('2025 AC'!$B$3:$B$250,"*"&$D68&"*",'2025 AC'!H$3:H$250) -> 0 | AN68: =SUMIF('2025 AC'!$B$3:$B$250,"*"&$D68&"*",'2025 AC'!I$3:I$250) -> 0 | AO68: =SUMIF('2025 AC'!$B$3:$B$250,"*"&$D68&"*",'2025 AC'!J$3:J$250) -> 0 | ... AS68: =SUMIF('2025 AC'!$B$3:$B$250,"*"&$D68&"*",'2025 AC'!N$3:N$250) -> 0 | AT68: =SUM(AH68:AS68) -> 0 | AU68: =SUM(AH68:AJ68) -> 0 | AV68: =SUM(AK68:AM68) -> 0 | AW68: =SUM(AN68:AP68) -> 0 | AX68: =SUM(AQ68:AS68) -> 0 | AY68: =SUM(AU68:AX68) -> 0 | BA68: =SUMIF('2026 AC'!$B$3:$B$254,"*"&$D68&"*",'2026 AC'!C$3:C$254) -> 0 | BB68: =SUMIF('2026 AC'!$B$3:$B$254,"*"&$D68&"*",'2026 AC'!D$3:D$254) -> 0 | BC68: =SUMIF('2026 AC'!$B$3:$B$254,"*"&$D68&"*",'2026 AC'!E$3:E$254) -> 0 | BD68: =SUMIF('2026 AC'!$B$3:$B$254,"*"&$D68&"*",'2026 AC'!F$3:F$254) -> 0 | BE68: =SUMIF('2026 AC'!$B$3:$B$254,"*"&$D68&"*",'2026 AC'!G$3:G$254) -> 0 | BF68: =SUMIF('2026 AC'!$B$3:$B$254,"*"&$D68&"*",'2026 AC'!H$3:H$254) -> 0 | BG68: =SUMIF('2026 AC'!$B$3:$B$254,"*"&$D68&"*",'2026 AC'!I$3:I$254) -> 0 | BH68: =SUMIF('2026 AC'!$B$3:$B$254,"*"&$D68&"*",'2026 AC'!J$3:J$254) -> 0 | ... BL68: =SUMIF('2026 AC'!$B$3:$B$254,"*"&$D68&"*",'2026 AC'!N$3:N$254) -> 0 | BM68: =SUM(BA68:BL68) -> 0 | BN68: =SUM(BA68:BC68) -> 0 | BO68: =SUM(BD68:BF68) -> 0 | BP68: =SUM(BG68:BI68) -> 0 | BQ68: =SUM(BJ68:BL68) -> 0 | BR68: =SUM(BN68:BQ68) -> 0
A69: OUTSOURCED GAJAH3 CAFE RENTAL | B69: 540-1000 | E69: =SUMIF($BA$6:$BL$6,$E$6,$BA69:$BL69) -> 0 | F69: =SUMIF($AH$6:$AS$6,$F$6,$AH69:$AS69) -> 0 | H69: =SUMIF($BN$6:$BR$6,$H$6,$BN69:$BR69) -> 0 | I69: =SUMIF($AU$6:$AY$6,$I$6,$AU69:$AY69) -> 0 | K69: =BM69 -> 0 | L69: =SUM(AH69:AM69) -> 0 | AB69: =SUM(O69:Q69) -> 0 | AC69: =SUM(R69:T69) -> 0 | AD69: =SUM(U69:W69) -> 0 | AE69: =SUM(X69:Z69) -> 0 | AF69: =SUM(AB69:AE69) -> 0 | AU69: =SUM(AH69:AJ69) -> 0 | AV69: =SUM(AK69:AM69) -> 0 | AW69: =SUM(AN69:AP69) -> 0 | AX69: =SUM(AQ69:AS69) -> 0 | AY69: =SUM(AU69:AX69) -> 0 | BB69: 0 | BC69: 0 | BD69: 0 | BE69: 0 | BF69: 0 | BG69: 0 | BH69: 0 | BI69: 0 | BJ69: 0 | BK69: 0 | BL69: 0 | BN69: =SUM(BA69:BC69) -> 0 | BO69: =SUM(BD69:BF69) -> 0 | BP69: =SUM(BG69:BI69) -> 0 | BQ69: =SUM(BJ69:BL69) -> 0 | BR69: =SUM(BN69:BQ69) -> 0
C70: TOTAL REVENUE | E70: =SUMIF($BA$6:$BL$6,$E$6,$BA70:$BL70) -> 462999.09 | F70: =SUMIF($AH$6:$AS$6,$F$6,$AH70:$AS70) -> 427388.51 | G70: =(E70-F70)/F70 -> 0.083321332 | H70: =SUMIF($BN$6:$BR$6,$H$6,$BN70:$BR70) -> 1408509 | I70: =SUMIF($AU$6:$AY$6,$I$6,$AU70:$AY70) -> 1328734.6 | J70: =(H70-I70)/I70 -> 0.060037866 | K70: =BM70 -> 2879557.5 | L70: =SUM(AH70:AM70) -> 2673732 | M70: =(K70-L70)/L70 -> 0.076980629 | O70: =O27+O38+O45+O52+O55+O57+O60+O65+O66 -> 322969.51 | P70: =P27+P38+P45+P52+P55+P57+P60+P65+P66 -> 452835.44 | Q70: =Q27+Q38+Q45+Q52+Q55+Q57+Q60+Q65+Q66 -> 403986.76 | R70: =R27+R38+R45+R52+R55+R57+R60+R65+R66 -> 374464.84 | S70: =S27+S38+S45+S52+S55+S57+S60+S65+S66 -> 512364.24 | T70: =T27+T38+T45+T52+T55+T57+T60+T65+T66 -> 441953.8 | U70: =U27+U38+U45+U52+U55+U57+U60+U65+U66 -> 520540.69 | V70: =V27+V38+V45+V52+V55+V57+V60+V65+V66 -> 636102.51 | ... Z70: =Z27+Z38+Z45+Z52+Z55+Z57+Z60+Z65+Z66 -> 563250.71 | AA70: =SUM(O70:Z70) -> 5658580 | AB70: =SUM(O70:Q70) -> 1179791.7 | AC70: =SUM(R70:T70) -> 1328782.9 | AD70: =SUM(U70:W70) -> 1618108.1 | AE70: =SUM(X70:Z70) -> 1531897.3 | AF70: =SUM(AB70:AE70) -> 5658580 | AH70: =AH27+AH38+AH45+AH52+AH55+AH57+AH60+AH65+AH66 -> 470439.94 | AI70: =AI27+AI38+AI45+AI52+AI55+AI57+AI60+AI65+AI66 -> 432995.46 | AJ70: =AJ27+AJ38+AJ45+AJ52+AJ55+AJ57+AJ60+AJ65+AJ66 -> 441561.98 | AK70: =AK27+AK38+AK45+AK52+AK55+AK57+AK60+AK65+AK66 -> 405954.77 | AL70: =AL27+AL38+AL45+AL52+AL55+AL57+AL60+AL65+AL66 -> 495391.32 | AM70: =AM27+AM38+AM45+AM52+AM55+AM57+AM60+AM65+AM66 -> 427388.51 | AN70: =AN27+AN38+AN45+AN52+AN55+AN57+AN60+AN65+AN66 -> 433310.17 | AO70: =AO27+AO38+AO45+AO52+AO55+AO57+AO60+AO65+AO66 -> 479592.42 | ... AS70: =AS27+AS38+AS45+AS52+AS55+AS57+AS60+AS65+AS66 -> 630066.9 | AT70: =SUM(AH70:AS70) -> 5446792.7 | AU70: =SUM(AH70:AJ70) -> 1344997.4 | AV70: =SUM(AK70:AM70) -> 1328734.6 | AW70: =SUM(AN70:AP70) -> 1409325.8 | AX70: =SUM(AQ70:AS70) -> 1363734.9 | AY70: =SUM(AU70:AX70) -> 5446792.7 | BA70: =BA27+BA38+BA45+BA52+BA55+BA57+BA60+BA65+BA66 -> 512157.74 | BB70: =BB27+BB38+BB45+BB52+BB55+BB57+BB60+BB65+BB66 -> 459676.64 | BC70: =BC27+BC38+BC45+BC52+BC55+BC57+BC60+BC65+BC66 -> 499214.18 | BD70: =BD27+BD38+BD45+BD52+BD55+BD57+BD60+BD65+BD66 -> 487372.42 | BE70: =BE27+BE38+BE45+BE52+BE55+BE57+BE60+BE65+BE66 -> 458137.48 | BF70: =BF27+BF38+BF45+BF52+BF55+BF57+BF60+BF65+BF66 -> 462999.09 | BG70: =BG27+BG38+BG45+BG52+BG55+BG57+BG60+BG65+BG66 -> 0 | BH70: =BH27+BH38+BH45+BH52+BH55+BH57+BH60+BH65+BH66 -> 0 | ... BL70: =BL27+BL38+BL45+BL52+BL55+BL57+BL60+BL65+BL66 -> 0 | BM70: =SUM(BA70:BL70) -> 2879557.5 | BN70: =SUM(BA70:BC70) -> 1471048.6 | BO70: =SUM(BD70:BF70) -> 1408509 | BP70: =SUM(BG70:BI70) -> 0 | BQ70: =SUM(BJ70:BL70) -> 0 | BR70: =SUM(BN70:BQ70) -> 2879557.5
A71: SALES ADJUSTMENTS | E71: =SUMIF($BA$6:$BL$6,$E$6,$BA71:$BL71) -> 0 | F71: =SUMIF($AH$6:$AS$6,$F$6,$AH71:$AS71) -> 0 | H71: =SUMIF($BN$6:$BR$6,$H$6,$BN71:$BR71) -> 0 | I71: =SUMIF($AU$6:$AY$6,$I$6,$AU71:$AY71) -> 0 | K71: =BM71 -> 0 | L71: =SUM(AH71:AM71) -> 0 | AB71: =SUM(O71:Q71) -> 0 | AC71: =SUM(R71:T71) -> 0 | AD71: =SUM(U71:W71) -> 0 | AE71: =SUM(X71:Z71) -> 0 | AF71: =SUM(AB71:AE71) -> 0 | AU71: =SUM(AH71:AJ71) -> 0 | AV71: =SUM(AK71:AM71) -> 0 | AW71: =SUM(AN71:AP71) -> 0 | AX71: =SUM(AQ71:AS71) -> 0 | AY71: =SUM(AU71:AX71) -> 0 | BN71: =SUM(BA71:BC71) -> 0 | BO71: =SUM(BD71:BF71) -> 0 | BP71: =SUM(BG71:BI71) -> 0 | BQ71: =SUM(BJ71:BL71) -> 0 | BR71: =SUM(BN71:BQ71) -> 0
A72: COST OF GOODS SOLD | C72: COST OF SALES | E72: =SUMIF($BA$6:$BL$6,$E$6,$BA72:$BL72) -> 0 | F72: =SUMIF($AH$6:$AS$6,$F$6,$AH72:$AS72) -> 0 | H72: =SUMIF($BN$6:$BR$6,$H$6,$BN72:$BR72) -> 0 | I72: =SUMIF($AU$6:$AY$6,$I$6,$AU72:$AY72) -> 0 | K72: =BM72 -> 0 | L72: =SUM(AH72:AM72) -> 0 | AB72: =SUM(O72:Q72) -> 0 | AC72: =SUM(R72:T72) -> 0 | AD72: =SUM(U72:W72) -> 0 | AE72: =SUM(X72:Z72) -> 0 | AF72: =SUM(AB72:AE72) -> 0 | AU72: =SUM(AH72:AJ72) -> 0 | AV72: =SUM(AK72:AM72) -> 0 | AW72: =SUM(AN72:AP72) -> 0 | AX72: =SUM(AQ72:AS72) -> 0 | AY72: =SUM(AU72:AX72) -> 0 | BB72: 0 | BC72: 0 | BD72: 0 | BE72: 0 | BF72: 0 | BG72: 0 | BH72: 0 | BI72: 0 | BJ72: 0 | BK72: 0 | BL72: 0 | BN72: =SUM(BA72:BC72) -> 0 | BO72: =SUM(BD72:BF72) -> 0 | BP72: =SUM(BG72:BI72) -> 0 | BQ72: =SUM(BJ72:BL72) -> 0 | BR72: =SUM(BN72:BQ72) -> 0
E73: =SUMIF($BA$6:$BL$6,$E$6,$BA73:$BL73) -> 0 | F73: =SUMIF($AH$6:$AS$6,$F$6,$AH73:$AS73) -> 0 | H73: =SUMIF($BN$6:$BR$6,$H$6,$BN73:$BR73) -> 0 | I73: =SUMIF($AU$6:$AY$6,$I$6,$AU73:$AY73) -> 0 | K73: =BM73 -> 0 | L73: =SUM(AH73:AM73) -> 0 | AB73: =SUM(O73:Q73) -> 0 | AC73: =SUM(R73:T73) -> 0 | AD73: =SUM(U73:W73) -> 0 | AE73: =SUM(X73:Z73) -> 0 | AF73: =SUM(AB73:AE73) -> 0 | AU73: =SUM(AH73:AJ73) -> 0 | AV73: =SUM(AK73:AM73) -> 0 | AW73: =SUM(AN73:AP73) -> 0 | AX73: =SUM(AQ73:AS73) -> 0 | AY73: =SUM(AU73:AX73) -> 0 | BN73: =SUM(BA73:BC73) -> 0 | BO73: =SUM(BD73:BF73) -> 0 | BP73: =SUM(BG73:BI73) -> 0 | BQ73: =SUM(BJ73:BL73) -> 0 | BR73: =SUM(BN73:BQ73) -> 0
A74: STOCKS AT THE BEGINNING OF YEAR | B74: 600-0000 | C74: STOCKS AT THE BEGINNING OF YEAR | D74: 600-0000 | E74: =SUMIF($BA$6:$BL$6,$E$6,$BA74:$BL74) -> 36922.05 | F74: =SUMIF($AH$6:$AS$6,$F$6,$AH74:$AS74) -> 0 | G74: =IFERROR((E74-F74)/F74,1) -> 1 | H74: =SUMIF($BN$6:$BR$6,$H$6,$BN74:$BR74) -> 114931.47 | I74: =SUMIF($AU$6:$AY$6,$I$6,$AU74:$AY74) -> 0 | J74: =(H74-I74)/I74 -> #DIV/0! | K74: =BM74 -> 240745.56 | L74: =SUM(AH74:AM74) -> 30020.35 | M74: =(K74-L74)/L74 -> 7.0194122 | O74: =SUMIF('2024 AC'!$B$3:$B$250,"*"&$D74&"*",'2024 AC'!C$3:C$250) -> 23438.06 | P74: =SUMIF('2024 AC'!$B$3:$B$250,"*"&$D74&"*",'2024 AC'!D$3:D$250) -> 0 | Q74: =SUMIF('2024 AC'!$B$3:$B$250,"*"&$D74&"*",'2024 AC'!E$3:E$250) -> 0 | R74: =SUMIF('2024 AC'!$B$3:$B$250,"*"&$D74&"*",'2024 AC'!F$3:F$250) -> 0 | S74: =SUMIF('2024 AC'!$B$3:$B$250,"*"&$D74&"*",'2024 AC'!G$3:G$250) -> 0 | T74: =SUMIF('2024 AC'!$B$3:$B$250,"*"&$D74&"*",'2024 AC'!H$3:H$250) -> 0 | U74: =SUMIF('2024 AC'!$B$3:$B$250,"*"&$D74&"*",'2024 AC'!I$3:I$250) -> 0 | V74: =SUMIF('2024 AC'!$B$3:$B$250,"*"&$D74&"*",'2024 AC'!J$3:J$250) -> 0 | ... Z74: =SUMIF('2024 AC'!$B$3:$B$250,"*"&$D74&"*",'2024 AC'!N$3:N$250) -> 0 | AA74: =SUM(O74:Z74) -> 23438.06 | AB74: =SUM(O74:Q74) -> 23438.06 | AC74: =SUM(R74:T74) -> 0 | AD74: =SUM(U74:W74) -> 0 | AE74: =SUM(X74:Z74) -> 0 | AF74: =SUM(AB74:AE74) -> 23438.06 | AH74: =SUMIF('2025 AC'!$B$3:$B$250,"*"&$D74&"*",'2025 AC'!C$3:C$250) -> 30020.35 | AI74: =SUMIF('2025 AC'!$B$3:$B$250,"*"&$D74&"*",'2025 AC'!D$3:D$250) -> 0 | AJ74: =SUMIF('2025 AC'!$B$3:$B$250,"*"&$D74&"*",'2025 AC'!E$3:E$250) -> 0 | AK74: =SUMIF('2025 AC'!$B$3:$B$250,"*"&$D74&"*",'2025 AC'!F$3:F$250) -> 0 | AL74: =SUMIF('2025 AC'!$B$3:$B$250,"*"&$D74&"*",'2025 AC'!G$3:G$250) -> 0 | AM74: =SUMIF('2025 AC'!$B$3:$B$250,"*"&$D74&"*",'2025 AC'!H$3:H$250) -> 0 | AN74: =SUMIF('2025 AC'!$B$3:$B$250,"*"&$D74&"*",'2025 AC'!I$3:I$250) -> 0 | AO74: =SUMIF('2025 AC'!$B$3:$B$250,"*"&$D74&"*",'2025 AC'!J$3:J$250) -> 0 | ... AS74: =SUMIF('2025 AC'!$B$3:$B$250,"*"&$D74&"*",'2025 AC'!N$3:N$250) -> 0 | AT74: =SUM(AH74:AS74) -> 30020.35 | AU74: =SUM(AH74:AJ74) -> 30020.35 | AV74: =SUM(AK74:AM74) -> 0 | AW74: =SUM(AN74:AP74) -> 0 | AX74: =SUM(AQ74:AS74) -> 0 | AY74: =SUM(AU74:AX74) -> 30020.35 | BA74: =SUMIF('2026 AC'!$B$3:$B$254,"*"&$D74&"*",'2026 AC'!C$3:C$254) -> 41167.7 | BB74: =SUMIF('2026 AC'!$B$3:$B$254,"*"&$D74&"*",'2026 AC'!D$3:D$254) -> 40202.1 | BC74: =SUMIF('2026 AC'!$B$3:$B$254,"*"&$D74&"*",'2026 AC'!E$3:E$254) -> 44444.29 | BD74: =SUMIF('2026 AC'!$B$3:$B$254,"*"&$D74&"*",'2026 AC'!F$3:F$254) -> 38689.93 | BE74: =SUMIF('2026 AC'!$B$3:$B$254,"*"&$D74&"*",'2026 AC'!G$3:G$254) -> 39319.49 | BF74: =SUMIF('2026 AC'!$B$3:$B$254,"*"&$D74&"*",'2026 AC'!H$3:H$254) -> 36922.05 | BG74: =SUMIF('2026 AC'!$B$3:$B$254,"*"&$D74&"*",'2026 AC'!I$3:I$254) -> 0 | BH74: =SUMIF('2026 AC'!$B$3:$B$254,"*"&$D74&"*",'2026 AC'!J$3:J$254) -> 0 | ... BL74: =SUMIF('2026 AC'!$B$3:$B$254,"*"&$D74&"*",'2026 AC'!N$3:N$254) -> 0 | BM74: =SUM(BA74:BL74) -> 240745.56 | BN74: =SUM(BA74:BC74) -> 125814.09 | BO74: =SUM(BD74:BF74) -> 114931.47 | BP74: =SUM(BG74:BI74) -> 0 | BQ74: =SUM(BJ74:BL74) -> 0 | BR74: =SUM(BN74:BQ74) -> 240745.56
A75: COST - GUEST ROOM | B75: 610-0001 | C75: COST - GUEST ROOM | D75: 610-0001 | E75: =SUMIF($BA$6:$BL$6,$E$6,$BA75:$BL75) -> 39470.19 | F75: =SUMIF($AH$6:$AS$6,$F$6,$AH75:$AS75) -> 35070.41 | G75: =(E75-F75)/F75 -> 0.12545562 | H75: =SUMIF($BN$6:$BR$6,$H$6,$BN75:$BR75) -> 108614.57 | I75: =SUMIF($AU$6:$AY$6,$I$6,$AU75:$AY75) -> 106925.99 | J75: =(H75-I75)/I75 -> 0.015792045 | K75: =BM75 -> 240693.82 | L75: =SUM(AH75:AM75) -> 220149.35 | M75: =(K75-L75)/L75 -> 0.093320603 | O75: =SUM(O76:O81) -> 36471.73 | P75: =SUM(P76:P81) -> 36113.49 | Q75: =SUM(Q76:Q81) -> 39425.47 | R75: =SUM(R76:R81) -> 20218.33 | S75: =SUM(S76:S81) -> 34110.27 | T75: =SUM(T76:T81) -> 50931.21 | U75: =SUM(U76:U81) -> 49620.32 | V75: =SUM(V76:V81) -> 64184.35 | ... Z75: =SUM(Z76:Z81) -> 47440.65 | AA75: =SUM(O75:Z75) -> 492217.47 | AB75: =SUM(O75:Q75) -> 112010.69 | AC75: =SUM(R75:T75) -> 105259.81 | AD75: =SUM(U75:W75) -> 150908.41 | AE75: =SUM(X75:Z75) -> 124038.56 | AF75: =SUM(AB75:AE75) -> 492217.47 | AH75: =SUMIF('2025 AC'!$B$3:$B$250,"*"&$D75&"*",'2025 AC'!C$3:C$250) -> 46246.85 | AI75: =SUMIF('2025 AC'!$B$3:$B$250,"*"&$D75&"*",'2025 AC'!D$3:D$250) -> 45368.6 | AJ75: =SUMIF('2025 AC'!$B$3:$B$250,"*"&$D75&"*",'2025 AC'!E$3:E$250) -> 21607.91 | AK75: =SUMIF('2025 AC'!$B$3:$B$250,"*"&$D75&"*",'2025 AC'!F$3:F$250) -> 33942.41 | AL75: =SUMIF('2025 AC'!$B$3:$B$250,"*"&$D75&"*",'2025 AC'!G$3:G$250) -> 37913.17 | AM75: =SUMIF('2025 AC'!$B$3:$B$250,"*"&$D75&"*",'2025 AC'!H$3:H$250) -> 35070.41 | AN75: =SUMIF('2025 AC'!$B$3:$B$250,"*"&$D75&"*",'2025 AC'!I$3:I$250) -> 9277.62 | AO75: =SUMIF('2025 AC'!$B$3:$B$250,"*"&$D75&"*",'2025 AC'!J$3:J$250) -> 48246.31 | ... AS75: =SUMIF('2025 AC'!$B$3:$B$250,"*"&$D75&"*",'2025 AC'!N$3:N$250) -> 63364.55 | AT75: =SUM(AH75:AS75) -> 462814.02 | AU75: =SUM(AH75:AJ75) -> 113223.36 | AV75: =SUM(AK75:AM75) -> 106925.99 | AW75: =SUM(AN75:AP75) -> 94497.66 | AX75: =SUM(AQ75:AS75) -> 148167.01 | AY75: =SUM(AU75:AX75) -> 462814.02 | BA75: =SUMIF('2026 AC'!$B$3:$B$254,"*"&$D75&"*",'2026 AC'!C$3:C$254) -> 54076.44 | BB75: =SUMIF('2026 AC'!$B$3:$B$254,"*"&$D75&"*",'2026 AC'!D$3:D$254) -> 40039.14 | BC75: =SUMIF('2026 AC'!$B$3:$B$254,"*"&$D75&"*",'2026 AC'!E$3:E$254) -> 37963.67 | BD75: =SUMIF('2026 AC'!$B$3:$B$254,"*"&$D75&"*",'2026 AC'!F$3:F$254) -> 31837.16 | BE75: =SUMIF('2026 AC'!$B$3:$B$254,"*"&$D75&"*",'2026 AC'!G$3:G$254) -> 37307.22 | BF75: =SUMIF('2026 AC'!$B$3:$B$254,"*"&$D75&"*",'2026 AC'!H$3:H$254) -> 39470.19 | BG75: =SUMIF('2026 AC'!$B$3:$B$254,"*"&$D75&"*",'2026 AC'!I$3:I$254) -> 0 | BH75: =SUMIF('2026 AC'!$B$3:$B$254,"*"&$D75&"*",'2026 AC'!J$3:J$254) -> 0 | ... BL75: =SUMIF('2026 AC'!$B$3:$B$254,"*"&$D75&"*",'2026 AC'!N$3:N$254) -> 0 | BM75: =SUM(BA75:BL75) -> 240693.82 | BN75: =SUM(BA75:BC75) -> 132079.25 | BO75: =SUM(BD75:BF75) -> 108614.57 | BP75: =SUM(BG75:BI75) -> 0 | BQ75: =SUM(BJ75:BL75) -> 0 | BR75: =SUM(BN75:BQ75) -> 240693.82
A76: COST - GUEST ROOM SUPPLIES | B76: 610-1000 | C76: GUEST ROOM SUPPLIES | D76: 610-1000 | E76: =SUMIF($BA$6:$BL$6,$E$6,$BA76:$BL76) -> 10342 | F76: =SUMIF($AH$6:$AS$6,$F$6,$AH76:$AS76) -> 8080 | G76: =(E76-F76)/F76 -> 0.2799505 | H76: =SUMIF($BN$6:$BR$6,$H$6,$BN76:$BR76) -> 30144 | I76: =SUMIF($AU$6:$AY$6,$I$6,$AU76:$AY76) -> 31334 | J76: =(H76-I76)/I76 -> -0.037977915 | K76: =BM76 -> 84862 | L76: =SUM(AH76:AM76) -> 66538.91 | M76: =(K76-L76)/L76 -> 0.27537406 | O76: =SUMIF('2024 AC'!$B$3:$B$250,"*"&$D76&"*",'2024 AC'!C$3:C$250) -> 18604 | P76: =SUMIF('2024 AC'!$B$3:$B$250,"*"&$D76&"*",'2024 AC'!D$3:D$250) -> 13245 | Q76: =SUMIF('2024 AC'!$B$3:$B$250,"*"&$D76&"*",'2024 AC'!E$3:E$250) -> 17212 | R76: =SUMIF('2024 AC'!$B$3:$B$250,"*"&$D76&"*",'2024 AC'!F$3:F$250) -> 2805 | S76: =SUMIF('2024 AC'!$B$3:$B$250,"*"&$D76&"*",'2024 AC'!G$3:G$250) -> 9347 | T76: =SUMIF('2024 AC'!$B$3:$B$250,"*"&$D76&"*",'2024 AC'!H$3:H$250) -> 22737 | U76: =SUMIF('2024 AC'!$B$3:$B$250,"*"&$D76&"*",'2024 AC'!I$3:I$250) -> 11924 | V76: =SUMIF('2024 AC'!$B$3:$B$250,"*"&$D76&"*",'2024 AC'!J$3:J$250) -> 29110 | ... Z76: =SUMIF('2024 AC'!$B$3:$B$250,"*"&$D76&"*",'2024 AC'!N$3:N$250) -> 12398 | AA76: =SUM(O76:Z76) -> 160714 | AB76: =SUM(O76:Q76) -> 49061 | AC76: =SUM(R76:T76) -> 34889 | AD76: =SUM(U76:W76) -> 45231 | AE76: =SUM(X76:Z76) -> 31533 | AF76: =SUM(AB76:AE76) -> 160714 | AH76: =SUMIF('2025 AC'!$B$3:$B$250,"*"&$D76&"*",'2025 AC'!C$3:C$250) -> 16906.86 | AI76: =SUMIF('2025 AC'!$B$3:$B$250,"*"&$D76&"*",'2025 AC'!D$3:D$250) -> 15678.05 | AJ76: =SUMIF('2025 AC'!$B$3:$B$250,"*"&$D76&"*",'2025 AC'!E$3:E$250) -> 2620 | AK76: =SUMIF('2025 AC'!$B$3:$B$250,"*"&$D76&"*",'2025 AC'!F$3:F$250) -> 9013 | AL76: =SUMIF('2025 AC'!$B$3:$B$250,"*"&$D76&"*",'2025 AC'!G$3:G$250) -> 14241 | AM76: =SUMIF('2025 AC'!$B$3:$B$250,"*"&$D76&"*",'2025 AC'!H$3:H$250) -> 8080 | AN76: =SUMIF('2025 AC'!$B$3:$B$250,"*"&$D76&"*",'2025 AC'!I$3:I$250) -> 9677.62 | AO76: =SUMIF('2025 AC'!$B$3:$B$250,"*"&$D76&"*",'2025 AC'!J$3:J$250) -> 23300.98 | ... AS76: =SUMIF('2025 AC'!$B$3:$B$250,"*"&$D76&"*",'2025 AC'!N$3:N$250) -> 11569 | AT76: =SUM(AH76:AS76) -> 159557.51 | AU76: =SUM(AH76:AJ76) -> 35204.91 | AV76: =SUM(AK76:AM76) -> 31334 | AW76: =SUM(AN76:AP76) -> 44826.6 | AX76: =SUM(AQ76:AS76) -> 48192 | AY76: =SUM(AU76:AX76) -> 159557.51 | BA76: =SUMIF('2026 AC'!$B$3:$B$254,"*"&$D76&"*",'2026 AC'!C$3:C$254) -> 25601 | BB76: =SUMIF('2026 AC'!$B$3:$B$254,"*"&$D76&"*",'2026 AC'!D$3:D$254) -> 13590 | BC76: =SUMIF('2026 AC'!$B$3:$B$254,"*"&$D76&"*",'2026 AC'!E$3:E$254) -> 15527 | BD76: =SUMIF('2026 AC'!$B$3:$B$254,"*"&$D76&"*",'2026 AC'!F$3:F$254) -> 7622 | BE76: =SUMIF('2026 AC'!$B$3:$B$254,"*"&$D76&"*",'2026 AC'!G$3:G$254) -> 12180 | BF76: =SUMIF('2026 AC'!$B$3:$B$254,"*"&$D76&"*",'2026 AC'!H$3:H$254) -> 10342 | BG76: =SUMIF('2026 AC'!$B$3:$B$254,"*"&$D76&"*",'2026 AC'!I$3:I$254) -> 0 | BH76: =SUMIF('2026 AC'!$B$3:$B$254,"*"&$D76&"*",'2026 AC'!J$3:J$254) -> 0 | ... BL76: =SUMIF('2026 AC'!$B$3:$B$254,"*"&$D76&"*",'2026 AC'!N$3:N$254) -> 0 | BM76: =SUM(BA76:BL76) -> 84862 | BN76: =SUM(BA76:BC76) -> 54718 | BO76: =SUM(BD76:BF76) -> 30144 | BP76: =SUM(BG76:BI76) -> 0 | BQ76: =SUM(BJ76:BL76) -> 0 | BR76: =SUM(BN76:BQ76) -> 84862
A77: COST - GUEST SERVICES LAUNDRY | B77: 610-1004 | C77: COST - GUEST SERVICES LAUNDRY | D77: 610-1004 | E77: =SUMIF($BA$6:$BL$6,$E$6,$BA77:$BL77) -> 0 | F77: =SUMIF($AH$6:$AS$6,$F$6,$AH77:$AS77) -> 0 | G77: =IFERROR((E77-F77)/F77,0) -> 0 | H77: =SUMIF($BN$6:$BR$6,$H$6,$BN77:$BR77) -> 0 | I77: =SUMIF($AU$6:$AY$6,$I$6,$AU77:$AY77) -> 0 | J77: =IFERROR((H77-I77)/I77,0) -> 0 | K77: =BM77 -> 0 | L77: =SUM(AH77:AM77) -> 0 | M77: =IFERROR((K77-L77)/L77,0) -> 0 | O77: =SUMIF('2024 AC'!$B$3:$B$250,"*"&$D77&"*",'2024 AC'!C$3:C$250) -> 0 | P77: =SUMIF('2024 AC'!$B$3:$B$250,"*"&$D77&"*",'2024 AC'!D$3:D$250) -> 0 | Q77: =SUMIF('2024 AC'!$B$3:$B$250,"*"&$D77&"*",'2024 AC'!E$3:E$250) -> 0 | R77: =SUMIF('2024 AC'!$B$3:$B$250,"*"&$D77&"*",'2024 AC'!F$3:F$250) -> 0 | S77: =SUMIF('2024 AC'!$B$3:$B$250,"*"&$D77&"*",'2024 AC'!G$3:G$250) -> 0 | T77: =SUMIF('2024 AC'!$B$3:$B$250,"*"&$D77&"*",'2024 AC'!H$3:H$250) -> 0 | U77: =SUMIF('2024 AC'!$B$3:$B$250,"*"&$D77&"*",'2024 AC'!I$3:I$250) -> 0 | V77: =SUMIF('2024 AC'!$B$3:$B$250,"*"&$D77&"*",'2024 AC'!J$3:J$250) -> 0 | ... Z77: =SUMIF('2024 AC'!$B$3:$B$250,"*"&$D77&"*",'2024 AC'!N$3:N$250) -> 0 | AA77: =SUM(O77:Z77) -> 0 | AB77: =SUM(O77:Q77) -> 0 | AC77: =SUM(R77:T77) -> 0 | AD77: =SUM(U77:W77) -> 0 | AE77: =SUM(X77:Z77) -> 0 | AF77: =SUM(AB77:AE77) -> 0 | AH77: =SUMIF('2025 AC'!$B$3:$B$250,"*"&$D77&"*",'2025 AC'!C$3:C$250) -> 0 | AI77: =SUMIF('2025 AC'!$B$3:$B$250,"*"&$D77&"*",'2025 AC'!D$3:D$250) -> 0 | AJ77: =SUMIF('2025 AC'!$B$3:$B$250,"*"&$D77&"*",'2025 AC'!E$3:E$250) -> 0 | AK77: =SUMIF('2025 AC'!$B$3:$B$250,"*"&$D77&"*",'2025 AC'!F$3:F$250) -> 0 | AL77: =SUMIF('2025 AC'!$B$3:$B$250,"*"&$D77&"*",'2025 AC'!G$3:G$250) -> 0 | AM77: =SUMIF('2025 AC'!$B$3:$B$250,"*"&$D77&"*",'2025 AC'!H$3:H$250) -> 0 | AN77: =SUMIF('2025 AC'!$B$3:$B$250,"*"&$D77&"*",'2025 AC'!I$3:I$250) -> 0 | AO77: =SUMIF('2025 AC'!$B$3:$B$250,"*"&$D77&"*",'2025 AC'!J$3:J$250) -> 0 | ... AS77: =SUMIF('2025 AC'!$B$3:$B$250,"*"&$D77&"*",'2025 AC'!N$3:N$250) -> 0 | AT77: =SUM(AH77:AS77) -> 0 | AU77: =SUM(AH77:AJ77) -> 0 | AV77: =SUM(AK77:AM77) -> 0 | AW77: =SUM(AN77:AP77) -> 0 | AX77: =SUM(AQ77:AS77) -> 0 | AY77: =SUM(AU77:AX77) -> 0 | BA77: =SUMIF('2026 AC'!$B$3:$B$254,"*"&$D77&"*",'2026 AC'!C$3:C$254) -> 0 | BB77: =SUMIF('2026 AC'!$B$3:$B$254,"*"&$D77&"*",'2026 AC'!D$3:D$254) -> 0 | BC77: =SUMIF('2026 AC'!$B$3:$B$254,"*"&$D77&"*",'2026 AC'!E$3:E$254) -> 0 | BD77: =SUMIF('2026 AC'!$B$3:$B$254,"*"&$D77&"*",'2026 AC'!F$3:F$254) -> 0 | BE77: =SUMIF('2026 AC'!$B$3:$B$254,"*"&$D77&"*",'2026 AC'!G$3:G$254) -> 0 | BF77: =SUMIF('2026 AC'!$B$3:$B$254,"*"&$D77&"*",'2026 AC'!H$3:H$254) -> 0 | BG77: =SUMIF('2026 AC'!$B$3:$B$254,"*"&$D77&"*",'2026 AC'!I$3:I$254) -> 0 | BH77: =SUMIF('2026 AC'!$B$3:$B$254,"*"&$D77&"*",'2026 AC'!J$3:J$254) -> 0 | ... BL77: =SUMIF('2026 AC'!$B$3:$B$254,"*"&$D77&"*",'2026 AC'!N$3:N$254) -> 0 | BM77: =SUM(BA77:BL77) -> 0 | BN77: =SUM(BA77:BC77) -> 0 | BO77: =SUM(BD77:BF77) -> 0 | BP77: =SUM(BG77:BI77) -> 0 | BQ77: =SUM(BJ77:BL77) -> 0 | BR77: =SUM(BN77:BQ77) -> 0
A78: COST - GUEST SERVICES C.STORE/SOUVENIER | B78: 610-1005 | C78: COST - GUEST SERVICES C.STORE/SOUVENIER | D78: 610-1005 | E78: =SUMIF($BA$6:$BL$6,$E$6,$BA78:$BL78) -> 0 | F78: =SUMIF($AH$6:$AS$6,$F$6,$AH78:$AS78) -> 0 | G78: =IFERROR((E78-F78)/F78,0) -> 0 | H78: =SUMIF($BN$6:$BR$6,$H$6,$BN78:$BR78) -> 0 | I78: =SUMIF($AU$6:$AY$6,$I$6,$AU78:$AY78) -> 0 | J78: =IFERROR((H78-I78)/I78,0) -> 0 | K78: =BM78 -> 0 | L78: =SUM(AH78:AM78) -> 0 | M78: =IFERROR((K78-L78)/L78,0) -> 0 | O78: =SUMIF('2024 AC'!$B$3:$B$250,"*"&$D78&"*",'2024 AC'!C$3:C$250) -> 0 | P78: =SUMIF('2024 AC'!$B$3:$B$250,"*"&$D78&"*",'2024 AC'!D$3:D$250) -> 0 | Q78: =SUMIF('2024 AC'!$B$3:$B$250,"*"&$D78&"*",'2024 AC'!E$3:E$250) -> 0 | R78: =SUMIF('2024 AC'!$B$3:$B$250,"*"&$D78&"*",'2024 AC'!F$3:F$250) -> 0 | S78: =SUMIF('2024 AC'!$B$3:$B$250,"*"&$D78&"*",'2024 AC'!G$3:G$250) -> 0 | T78: =SUMIF('2024 AC'!$B$3:$B$250,"*"&$D78&"*",'2024 AC'!H$3:H$250) -> 0 | U78: =SUMIF('2024 AC'!$B$3:$B$250,"*"&$D78&"*",'2024 AC'!I$3:I$250) -> 0 | V78: =SUMIF('2024 AC'!$B$3:$B$250,"*"&$D78&"*",'2024 AC'!J$3:J$250) -> 0 | ... Z78: =SUMIF('2024 AC'!$B$3:$B$250,"*"&$D78&"*",'2024 AC'!N$3:N$250) -> 0 | AA78: =SUM(O78:Z78) -> 0 | AB78: =SUM(O78:Q78) -> 0 | AC78: =SUM(R78:T78) -> 0 | AD78: =SUM(U78:W78) -> 0 | AE78: =SUM(X78:Z78) -> 0 | AF78: =SUM(AB78:AE78) -> 0 | AH78: =SUMIF('2025 AC'!$B$3:$B$250,"*"&$D78&"*",'2025 AC'!C$3:C$250) -> 0 | AI78: =SUMIF('2025 AC'!$B$3:$B$250,"*"&$D78&"*",'2025 AC'!D$3:D$250) -> 0 | AJ78: =SUMIF('2025 AC'!$B$3:$B$250,"*"&$D78&"*",'2025 AC'!E$3:E$250) -> 0 | AK78: =SUMIF('2025 AC'!$B$3:$B$250,"*"&$D78&"*",'2025 AC'!F$3:F$250) -> 0 | AL78: =SUMIF('2025 AC'!$B$3:$B$250,"*"&$D78&"*",'2025 AC'!G$3:G$250) -> 0 | AM78: =SUMIF('2025 AC'!$B$3:$B$250,"*"&$D78&"*",'2025 AC'!H$3:H$250) -> 0 | AN78: =SUMIF('2025 AC'!$B$3:$B$250,"*"&$D78&"*",'2025 AC'!I$3:I$250) -> 0 | AO78: =SUMIF('2025 AC'!$B$3:$B$250,"*"&$D78&"*",'2025 AC'!J$3:J$250) -> 0 | ... AS78: =SUMIF('2025 AC'!$B$3:$B$250,"*"&$D78&"*",'2025 AC'!N$3:N$250) -> 0 | AT78: =SUM(AH78:AS78) -> 0 | AU78: =SUM(AH78:AJ78) -> 0 | AV78: =SUM(AK78:AM78) -> 0 | AW78: =SUM(AN78:AP78) -> 0 | AX78: =SUM(AQ78:AS78) -> 0 | AY78: =SUM(AU78:AX78) -> 0 | BA78: =SUMIF('2026 AC'!$B$3:$B$254,"*"&$D78&"*",'2026 AC'!C$3:C$254) -> 0 | BB78: =SUMIF('2026 AC'!$B$3:$B$254,"*"&$D78&"*",'2026 AC'!D$3:D$254) -> 0 | BC78: =SUMIF('2026 AC'!$B$3:$B$254,"*"&$D78&"*",'2026 AC'!E$3:E$254) -> 0 | BD78: =SUMIF('2026 AC'!$B$3:$B$254,"*"&$D78&"*",'2026 AC'!F$3:F$254) -> 0 | BE78: =SUMIF('2026 AC'!$B$3:$B$254,"*"&$D78&"*",'2026 AC'!G$3:G$254) -> 0 | BF78: =SUMIF('2026 AC'!$B$3:$B$254,"*"&$D78&"*",'2026 AC'!H$3:H$254) -> 0 | BG78: =SUMIF('2026 AC'!$B$3:$B$254,"*"&$D78&"*",'2026 AC'!I$3:I$254) -> 0 | BH78: =SUMIF('2026 AC'!$B$3:$B$254,"*"&$D78&"*",'2026 AC'!J$3:J$254) -> 0 | ... BL78: =SUMIF('2026 AC'!$B$3:$B$254,"*"&$D78&"*",'2026 AC'!N$3:N$254) -> 0 | BM78: =SUM(BA78:BL78) -> 0 | BN78: =SUM(BA78:BC78) -> 0 | BO78: =SUM(BD78:BF78) -> 0 | BP78: =SUM(BG78:BI78) -> 0 | BQ78: =SUM(BJ78:BL78) -> 0 | BR78: =SUM(BN78:BQ78) -> 0
A79: COST - GUEST SERVICES FLOWER / DECORATIONS | B79: 610-1006 | C79: COST - GUEST SERVICES FLOWER / DECORATIONS | D79: 610-1006 | E79: =SUMIF($BA$6:$BL$6,$E$6,$BA79:$BL79) -> 0 | F79: =SUMIF($AH$6:$AS$6,$F$6,$AH79:$AS79) -> 0 | G79: =IFERROR((E79-F79)/F79,0) -> 0 | H79: =SUMIF($BN$6:$BR$6,$H$6,$BN79:$BR79) -> 0 | I79: =SUMIF($AU$6:$AY$6,$I$6,$AU79:$AY79) -> 0 | J79: =IFERROR((H79-I79)/I79,0) -> 0 | K79: =BM79 -> 0 | L79: =SUM(AH79:AM79) -> 9.3 | M79: =IFERROR((K79-L79)/L79,0) -> -1 | O79: =SUMIF('2024 AC'!$B$3:$B$250,"*"&$D79&"*",'2024 AC'!C$3:C$250) -> 0 | P79: =SUMIF('2024 AC'!$B$3:$B$250,"*"&$D79&"*",'2024 AC'!D$3:D$250) -> 0 | Q79: =SUMIF('2024 AC'!$B$3:$B$250,"*"&$D79&"*",'2024 AC'!E$3:E$250) -> 107.6 | R79: =SUMIF('2024 AC'!$B$3:$B$250,"*"&$D79&"*",'2024 AC'!F$3:F$250) -> 0 | S79: =SUMIF('2024 AC'!$B$3:$B$250,"*"&$D79&"*",'2024 AC'!G$3:G$250) -> 0 | T79: =SUMIF('2024 AC'!$B$3:$B$250,"*"&$D79&"*",'2024 AC'!H$3:H$250) -> 0 | U79: =SUMIF('2024 AC'!$B$3:$B$250,"*"&$D79&"*",'2024 AC'!I$3:I$250) -> 0 | V79: =SUMIF('2024 AC'!$B$3:$B$250,"*"&$D79&"*",'2024 AC'!J$3:J$250) -> 30.4 | ... Z79: =SUMIF('2024 AC'!$B$3:$B$250,"*"&$D79&"*",'2024 AC'!N$3:N$250) -> 0 | AA79: =SUM(O79:Z79) -> 138 | AB79: =SUM(O79:Q79) -> 107.6 | AC79: =SUM(R79:T79) -> 0 | AD79: =SUM(U79:W79) -> 30.4 | AE79: =SUM(X79:Z79) -> 0 | AF79: =SUM(AB79:AE79) -> 138 | AH79: =SUMIF('2025 AC'!$B$3:$B$250,"*"&$D79&"*",'2025 AC'!C$3:C$250) -> 9.3 | AI79: =SUMIF('2025 AC'!$B$3:$B$250,"*"&$D79&"*",'2025 AC'!D$3:D$250) -> 0 | AJ79: =SUMIF('2025 AC'!$B$3:$B$250,"*"&$D79&"*",'2025 AC'!E$3:E$250) -> 0 | AK79: =SUMIF('2025 AC'!$B$3:$B$250,"*"&$D79&"*",'2025 AC'!F$3:F$250) -> 0 | AL79: =SUMIF('2025 AC'!$B$3:$B$250,"*"&$D79&"*",'2025 AC'!G$3:G$250) -> 0 | AM79: =SUMIF('2025 AC'!$B$3:$B$250,"*"&$D79&"*",'2025 AC'!H$3:H$250) -> 0 | AN79: =SUMIF('2025 AC'!$B$3:$B$250,"*"&$D79&"*",'2025 AC'!I$3:I$250) -> 0 | AO79: =SUMIF('2025 AC'!$B$3:$B$250,"*"&$D79&"*",'2025 AC'!J$3:J$250) -> 0 | ... AS79: =SUMIF('2025 AC'!$B$3:$B$250,"*"&$D79&"*",'2025 AC'!N$3:N$250) -> 0 | AT79: =SUM(AH79:AS79) -> 9.3 | AU79: =SUM(AH79:AJ79) -> 9.3 | AV79: =SUM(AK79:AM79) -> 0 | AW79: =SUM(AN79:AP79) -> 0 | AX79: =SUM(AQ79:AS79) -> 0 | AY79: =SUM(AU79:AX79) -> 9.3 | BA79: =SUMIF('2026 AC'!$B$3:$B$254,"*"&$D79&"*",'2026 AC'!C$3:C$254) -> 0 | BB79: =SUMIF('2026 AC'!$B$3:$B$254,"*"&$D79&"*",'2026 AC'!D$3:D$254) -> 0 | BC79: =SUMIF('2026 AC'!$B$3:$B$254,"*"&$D79&"*",'2026 AC'!E$3:E$254) -> 0 | BD79: =SUMIF('2026 AC'!$B$3:$B$254,"*"&$D79&"*",'2026 AC'!F$3:F$254) -> 0 | BE79: =SUMIF('2026 AC'!$B$3:$B$254,"*"&$D79&"*",'2026 AC'!G$3:G$254) -> 0 | BF79: =SUMIF('2026 AC'!$B$3:$B$254,"*"&$D79&"*",'2026 AC'!H$3:H$254) -> 0 | BG79: =SUMIF('2026 AC'!$B$3:$B$254,"*"&$D79&"*",'2026 AC'!I$3:I$254) -> 0 | BH79: =SUMIF('2026 AC'!$B$3:$B$254,"*"&$D79&"*",'2026 AC'!J$3:J$254) -> 0 | ... BL79: =SUMIF('2026 AC'!$B$3:$B$254,"*"&$D79&"*",'2026 AC'!N$3:N$254) -> 0 | BM79: =SUM(BA79:BL79) -> 0 | BN79: =SUM(BA79:BC79) -> 0 | BO79: =SUM(BD79:BF79) -> 0 | BP79: =SUM(BG79:BI79) -> 0 | BQ79: =SUM(BJ79:BL79) -> 0 | BR79: =SUM(BN79:BQ79) -> 0
A80: COST - GUEST SERVICES TRANSFER | B80: 610-1008 | C80: COST - GUEST SERVICES TRANSFER | D80: 610-1008 | E80: =SUMIF($BA$6:$BL$6,$E$6,$BA80:$BL80) -> 0 | F80: =SUMIF($AH$6:$AS$6,$F$6,$AH80:$AS80) -> 0 | G80: =IFERROR((E80-F80)/F80,0) -> 0 | H80: =SUMIF($BN$6:$BR$6,$H$6,$BN80:$BR80) -> 0 | I80: =SUMIF($AU$6:$AY$6,$I$6,$AU80:$AY80) -> 0 | J80: =IFERROR((H80-I80)/I80,0) -> 0 | K80: =BM80 -> 0 | L80: =SUM(AH80:AM80) -> 0 | M80: =IFERROR((K80-L80)/L80,0) -> 0 | O80: =SUMIF('2024 AC'!$B$3:$B$250,"*"&$D80&"*",'2024 AC'!C$3:C$250) -> 0 | P80: =SUMIF('2024 AC'!$B$3:$B$250,"*"&$D80&"*",'2024 AC'!D$3:D$250) -> 0 | Q80: =SUMIF('2024 AC'!$B$3:$B$250,"*"&$D80&"*",'2024 AC'!E$3:E$250) -> 0 | R80: =SUMIF('2024 AC'!$B$3:$B$250,"*"&$D80&"*",'2024 AC'!F$3:F$250) -> 0 | S80: =SUMIF('2024 AC'!$B$3:$B$250,"*"&$D80&"*",'2024 AC'!G$3:G$250) -> 0 | T80: =SUMIF('2024 AC'!$B$3:$B$250,"*"&$D80&"*",'2024 AC'!H$3:H$250) -> 0 | U80: =SUMIF('2024 AC'!$B$3:$B$250,"*"&$D80&"*",'2024 AC'!I$3:I$250) -> 0 | V80: =SUMIF('2024 AC'!$B$3:$B$250,"*"&$D80&"*",'2024 AC'!J$3:J$250) -> 0 | ... Z80: =SUMIF('2024 AC'!$B$3:$B$250,"*"&$D80&"*",'2024 AC'!N$3:N$250) -> 0 | AA80: =SUM(O80:Z80) -> 0 | AB80: =SUM(O80:Q80) -> 0 | AC80: =SUM(R80:T80) -> 0 | AD80: =SUM(U80:W80) -> 0 | AE80: =SUM(X80:Z80) -> 0 | AF80: =SUM(AB80:AE80) -> 0 | AH80: =SUMIF('2025 AC'!$B$3:$B$250,"*"&$D80&"*",'2025 AC'!C$3:C$250) -> 0 | AI80: =SUMIF('2025 AC'!$B$3:$B$250,"*"&$D80&"*",'2025 AC'!D$3:D$250) -> 0 | AJ80: =SUMIF('2025 AC'!$B$3:$B$250,"*"&$D80&"*",'2025 AC'!E$3:E$250) -> 0 | AK80: =SUMIF('2025 AC'!$B$3:$B$250,"*"&$D80&"*",'2025 AC'!F$3:F$250) -> 0 | AL80: =SUMIF('2025 AC'!$B$3:$B$250,"*"&$D80&"*",'2025 AC'!G$3:G$250) -> 0 | AM80: =SUMIF('2025 AC'!$B$3:$B$250,"*"&$D80&"*",'2025 AC'!H$3:H$250) -> 0 | AN80: =SUMIF('2025 AC'!$B$3:$B$250,"*"&$D80&"*",'2025 AC'!I$3:I$250) -> 0 | AO80: =SUMIF('2025 AC'!$B$3:$B$250,"*"&$D80&"*",'2025 AC'!J$3:J$250) -> 0 | ... AS80: =SUMIF('2025 AC'!$B$3:$B$250,"*"&$D80&"*",'2025 AC'!N$3:N$250) -> 0 | AT80: =SUM(AH80:AS80) -> 0 | AU80: =SUM(AH80:AJ80) -> 0 | AV80: =SUM(AK80:AM80) -> 0 | AW80: =SUM(AN80:AP80) -> 0 | AX80: =SUM(AQ80:AS80) -> 0 | AY80: =SUM(AU80:AX80) -> 0 | BA80: =SUMIF('2026 AC'!$B$3:$B$254,"*"&$D80&"*",'2026 AC'!C$3:C$254) -> 0 | BB80: =SUMIF('2026 AC'!$B$3:$B$254,"*"&$D80&"*",'2026 AC'!D$3:D$254) -> 0 | BC80: =SUMIF('2026 AC'!$B$3:$B$254,"*"&$D80&"*",'2026 AC'!E$3:E$254) -> 0 | BD80: =SUMIF('2026 AC'!$B$3:$B$254,"*"&$D80&"*",'2026 AC'!F$3:F$254) -> 0 | BE80: =SUMIF('2026 AC'!$B$3:$B$254,"*"&$D80&"*",'2026 AC'!G$3:G$254) -> 0 | BF80: =SUMIF('2026 AC'!$B$3:$B$254,"*"&$D80&"*",'2026 AC'!H$3:H$254) -> 0 | BG80: =SUMIF('2026 AC'!$B$3:$B$254,"*"&$D80&"*",'2026 AC'!I$3:I$254) -> 0 | BH80: =SUMIF('2026 AC'!$B$3:$B$254,"*"&$D80&"*",'2026 AC'!J$3:J$254) -> 0 | ... BL80: =SUMIF('2026 AC'!$B$3:$B$254,"*"&$D80&"*",'2026 AC'!N$3:N$254) -> 0 | BM80: =SUM(BA80:BL80) -> 0 | BN80: =SUM(BA80:BC80) -> 0 | BO80: =SUM(BD80:BF80) -> 0 | BP80: =SUM(BG80:BI80) -> 0 | BQ80: =SUM(BJ80:BL80) -> 0 | BR80: =SUM(BN80:BQ80) -> 0
A81: COST - ROOM LAUNDRY | B81: 610-4000 | C81: COST - ROOM LAUNDRY | D81: 610-4000 | E81: =SUMIF($BA$6:$BL$6,$E$6,$BA81:$BL81) -> 29128.19 | F81: =SUMIF($AH$6:$AS$6,$F$6,$AH81:$AS81) -> 26990.41 | G81: =(E81-F81)/F81 -> 0.07920517 | H81: =SUMIF($BN$6:$BR$6,$H$6,$BN81:$BR81) -> 78470.57 | I81: =SUMIF($AU$6:$AY$6,$I$6,$AU81:$AY81) -> 75591.99 | J81: =(H81-I81)/I81 -> 0.03808049 | K81: =BM81 -> 155831.82 | L81: =SUM(AH81:AM81) -> 153601.14 | M81: =(K81-L81)/L81 -> 0.014522548 | O81: =SUMIF('2024 AC'!$B$3:$B$250,"*"&$D81&"*",'2024 AC'!C$3:C$250) -> 17867.73 | P81: =SUMIF('2024 AC'!$B$3:$B$250,"*"&$D81&"*",'2024 AC'!D$3:D$250) -> 22868.49 | Q81: =SUMIF('2024 AC'!$B$3:$B$250,"*"&$D81&"*",'2024 AC'!E$3:E$250) -> 22105.87 | R81: =SUMIF('2024 AC'!$B$3:$B$250,"*"&$D81&"*",'2024 AC'!F$3:F$250) -> 17413.33 | S81: =SUMIF('2024 AC'!$B$3:$B$250,"*"&$D81&"*",'2024 AC'!G$3:G$250) -> 24763.27 | T81: =SUMIF('2024 AC'!$B$3:$B$250,"*"&$D81&"*",'2024 AC'!H$3:H$250) -> 28194.21 | U81: =SUMIF('2024 AC'!$B$3:$B$250,"*"&$D81&"*",'2024 AC'!I$3:I$250) -> 37696.32 | V81: =SUMIF('2024 AC'!$B$3:$B$250,"*"&$D81&"*",'2024 AC'!J$3:J$250) -> 35043.95 | ... Z81: =SUMIF('2024 AC'!$B$3:$B$250,"*"&$D81&"*",'2024 AC'!N$3:N$250) -> 35042.65 | AA81: =SUM(O81:Z81) -> 331365.47 | AB81: =SUM(O81:Q81) -> 62842.09 | AC81: =SUM(R81:T81) -> 70370.81 | AD81: =SUM(U81:W81) -> 105647.01 | AE81: =SUM(X81:Z81) -> 92505.56 | AF81: =SUM(AB81:AE81) -> 331365.47 | AH81: =SUMIF('2025 AC'!$B$3:$B$250,"*"&$D81&"*",'2025 AC'!C$3:C$250) -> 29330.69 | AI81: =SUMIF('2025 AC'!$B$3:$B$250,"*"&$D81&"*",'2025 AC'!D$3:D$250) -> 29690.55 | AJ81: =SUMIF('2025 AC'!$B$3:$B$250,"*"&$D81&"*",'2025 AC'!E$3:E$250) -> 18987.91 | AK81: =SUMIF('2025 AC'!$B$3:$B$250,"*"&$D81&"*",'2025 AC'!F$3:F$250) -> 24929.41 | AL81: =SUMIF('2025 AC'!$B$3:$B$250,"*"&$D81&"*",'2025 AC'!G$3:G$250) -> 23672.17 | AM81: =SUMIF('2025 AC'!$B$3:$B$250,"*"&$D81&"*",'2025 AC'!H$3:H$250) -> 26990.41 | AN81: =SUMIF('2025 AC'!$B$3:$B$250,"*"&$D81&"*",'2025 AC'!I$3:I$250) -> -400 | AO81: =SUMIF('2025 AC'!$B$3:$B$250,"*"&$D81&"*",'2025 AC'!J$3:J$250) -> 24945.33 | ... AS81: =SUMIF('2025 AC'!$B$3:$B$250,"*"&$D81&"*",'2025 AC'!N$3:N$250) -> 51795.55 | AT81: =SUM(AH81:AS81) -> 303247.21 | AU81: =SUM(AH81:AJ81) -> 78009.15 | AV81: =SUM(AK81:AM81) -> 75591.99 | AW81: =SUM(AN81:AP81) -> 49671.06 | AX81: =SUM(AQ81:AS81) -> 99975.01 | AY81: =SUM(AU81:AX81) -> 303247.21 | BA81: =SUMIF('2026 AC'!$B$3:$B$254,"*"&$D81&"*",'2026 AC'!C$3:C$254) -> 28475.44 | BB81: =SUMIF('2026 AC'!$B$3:$B$254,"*"&$D81&"*",'2026 AC'!D$3:D$254) -> 26449.14 | BC81: =SUMIF('2026 AC'!$B$3:$B$254,"*"&$D81&"*",'2026 AC'!E$3:E$254) -> 22436.67 | BD81: =SUMIF('2026 AC'!$B$3:$B$254,"*"&$D81&"*",'2026 AC'!F$3:F$254) -> 24215.16 | BE81: =SUMIF('2026 AC'!$B$3:$B$254,"*"&$D81&"*",'2026 AC'!G$3:G$254) -> 25127.22 | BF81: =SUMIF('2026 AC'!$B$3:$B$254,"*"&$D81&"*",'2026 AC'!H$3:H$254) -> 29128.19 | BG81: =SUMIF('2026 AC'!$B$3:$B$254,"*"&$D81&"*",'2026 AC'!I$3:I$254) -> 0 | BH81: =SUMIF('2026 AC'!$B$3:$B$254,"*"&$D81&"*",'2026 AC'!J$3:J$254) -> 0 | ... BL81: =SUMIF('2026 AC'!$B$3:$B$254,"*"&$D81&"*",'2026 AC'!N$3:N$254) -> 0 | BM81: =SUM(BA81:BL81) -> 155831.82 | BN81: =SUM(BA81:BC81) -> 77361.25 | BO81: =SUM(BD81:BF81) -> 78470.57 | BP81: =SUM(BG81:BI81) -> 0 | BQ81: =SUM(BJ81:BL81) -> 0 | BR81: =SUM(BN81:BQ81) -> 155831.82
A82: COST - F&B & BANQUET | B82: 610-0002 | C82: COST - F&B & BANQUET | D82: 610-0002 | E82: =SUMIF($BA$6:$BL$6,$E$6,$BA82:$BL82) -> 28254.21 | F82: =SUMIF($AH$6:$AS$6,$F$6,$AH82:$AS82) -> 26834.04 | G82: =(E82-F82)/F82 -> 0.052924196 | H82: =SUMIF($BN$6:$BR$6,$H$6,$BN82:$BR82) -> 84029.9 | I82: =SUMIF($AU$6:$AY$6,$I$6,$AU82:$AY82) -> 110556.08 | J82: =(H82-I82)/I82 -> -0.23993416 | K82: =BM82 -> 221771.06 | L82: =SUM(AH82:AM82) -> 281117.57 | M82: =(K82-L82)/L82 -> -0.21110922 | O82: =SUM(O83:O91) -> 42651.26 | P82: =SUM(P83:P91) -> 46548.98 | Q82: =SUM(Q83:Q91) -> 80476.09 | R82: =SUM(R83:R91) -> 53120.16 | S82: =SUM(S83:S91) -> 53325.88 | T82: =SUM(T83:T91) -> 36857.89 | U82: =SUM(U83:U91) -> 36605.5 | V82: =SUM(V83:V91) -> 51141.56 | ... Z82: =SUM(Z83:Z91) -> 37793.32 | AA82: =SUM(O82:Z82) -> 574373.63 | AB82: =SUM(O82:Q82) -> 169676.33 | AC82: =SUM(R82:T82) -> 143303.93 | AD82: =SUM(U82:W82) -> 126201.49 | AE82: =SUM(X82:Z82) -> 135191.88 | AF82: =SUM(AB82:AE82) -> 574373.63 | AH82: =SUMIF('2025 AC'!$B$3:$B$250,"*"&$D82&"*",'2025 AC'!C$3:C$250) -> 53144.94 | AI82: =SUMIF('2025 AC'!$B$3:$B$250,"*"&$D82&"*",'2025 AC'!D$3:D$250) -> 32417.58 | AJ82: =SUMIF('2025 AC'!$B$3:$B$250,"*"&$D82&"*",'2025 AC'!E$3:E$250) -> 84998.97 | AK82: =SUMIF('2025 AC'!$B$3:$B$250,"*"&$D82&"*",'2025 AC'!F$3:F$250) -> 32431.83 | AL82: =SUMIF('2025 AC'!$B$3:$B$250,"*"&$D82&"*",'2025 AC'!G$3:G$250) -> 51290.21 | AM82: =SUMIF('2025 AC'!$B$3:$B$250,"*"&$D82&"*",'2025 AC'!H$3:H$250) -> 26834.04 | AN82: =SUMIF('2025 AC'!$B$3:$B$250,"*"&$D82&"*",'2025 AC'!I$3:I$250) -> 32072.54 | AO82: =SUMIF('2025 AC'!$B$3:$B$250,"*"&$D82&"*",'2025 AC'!J$3:J$250) -> 33955.25 | ... AS82: =SUMIF('2025 AC'!$B$3:$B$250,"*"&$D82&"*",'2025 AC'!N$3:N$250) -> 45608.65 | AT82: =SUM(AH82:AS82) -> 502529.36 | AU82: =SUM(AH82:AJ82) -> 170561.49 | AV82: =SUM(AK82:AM82) -> 110556.08 | AW82: =SUM(AN82:AP82) -> 107824.96 | AX82: =SUM(AQ82:AS82) -> 113586.83 | AY82: =SUM(AU82:AX82) -> 502529.36 | BA82: =SUMIF('2026 AC'!$B$3:$B$254,"*"&$D82&"*",'2026 AC'!C$3:C$254) -> 36014.3 | BB82: =SUMIF('2026 AC'!$B$3:$B$254,"*"&$D82&"*",'2026 AC'!D$3:D$254) -> 50142.15 | BC82: =SUMIF('2026 AC'!$B$3:$B$254,"*"&$D82&"*",'2026 AC'!E$3:E$254) -> 51584.71 | BD82: =SUMIF('2026 AC'!$B$3:$B$254,"*"&$D82&"*",'2026 AC'!F$3:F$254) -> 32936.58 | BE82: =SUMIF('2026 AC'!$B$3:$B$254,"*"&$D82&"*",'2026 AC'!G$3:G$254) -> 22839.11 | BF82: =SUMIF('2026 AC'!$B$3:$B$254,"*"&$D82&"*",'2026 AC'!H$3:H$254) -> 28254.21 | BG82: =SUMIF('2026 AC'!$B$3:$B$254,"*"&$D82&"*",'2026 AC'!I$3:I$254) -> 0 | BH82: =SUMIF('2026 AC'!$B$3:$B$254,"*"&$D82&"*",'2026 AC'!J$3:J$254) -> 0 | ... BL82: =SUMIF('2026 AC'!$B$3:$B$254,"*"&$D82&"*",'2026 AC'!N$3:N$254) -> 0 | BM82: =SUM(BA82:BL82) -> 221771.06 | BN82: =SUM(BA82:BC82) -> 137741.16 | BO82: =SUM(BD82:BF82) -> 84029.9 | BP82: =SUM(BG82:BI82) -> 0 | BQ82: =SUM(BJ82:BL82) -> 0 | BR82: =SUM(BN82:BQ82) -> 221771.06
A83: COST F&B - BANQUET | B83: 610-2002 | C83: COST F&B - BANQUET** | D83: 610-2002 | E83: =SUMIF($BA$6:$BL$6,$E$6,$BA83:$BL83) -> 0 | F83: =SUMIF($AH$6:$AS$6,$F$6,$AH83:$AS83) -> 0 | G83: =(E83-F83)/F83 -> #DIV/0! | H83: =SUMIF($BN$6:$BR$6,$H$6,$BN83:$BR83) -> 0 | I83: =SUMIF($AU$6:$AY$6,$I$6,$AU83:$AY83) -> 130 | J83: =(H83-I83)/I83 -> -1 | K83: =BM83 -> 0 | L83: =SUM(AH83:AM83) -> 1838.85 | M83: =(K83-L83)/L83 -> -1 | O83: =SUMIF('2024 AC'!$B$3:$B$250,"*"&$D83&"*",'2024 AC'!C$3:C$250) -> 1645 | P83: =SUMIF('2024 AC'!$B$3:$B$250,"*"&$D83&"*",'2024 AC'!D$3:D$250) -> 567 | Q83: =SUMIF('2024 AC'!$B$3:$B$250,"*"&$D83&"*",'2024 AC'!E$3:E$250) -> 2241.45 | R83: =SUMIF('2024 AC'!$B$3:$B$250,"*"&$D83&"*",'2024 AC'!F$3:F$250) -> 1691.2 | S83: =SUMIF('2024 AC'!$B$3:$B$250,"*"&$D83&"*",'2024 AC'!G$3:G$250) -> 69 | T83: =SUMIF('2024 AC'!$B$3:$B$250,"*"&$D83&"*",'2024 AC'!H$3:H$250) -> 855.6 | U83: =SUMIF('2024 AC'!$B$3:$B$250,"*"&$D83&"*",'2024 AC'!I$3:I$250) -> 82.5 | V83: =SUMIF('2024 AC'!$B$3:$B$250,"*"&$D83&"*",'2024 AC'!J$3:J$250) -> 17.2 | ... Z83: =SUMIF('2024 AC'!$B$3:$B$250,"*"&$D83&"*",'2024 AC'!N$3:N$250) -> 0 | AA83: =SUM(O83:Z83) -> 7327.15 | AB83: =SUM(O83:Q83) -> 4453.45 | AC83: =SUM(R83:T83) -> 2615.8 | AD83: =SUM(U83:W83) -> 257.9 | AE83: =SUM(X83:Z83) -> 0 | AF83: =SUM(AB83:AE83) -> 7327.15 | AH83: =SUMIF('2025 AC'!$B$3:$B$250,"*"&$D83&"*",'2025 AC'!C$3:C$250) -> 1625 | AI83: =SUMIF('2025 AC'!$B$3:$B$250,"*"&$D83&"*",'2025 AC'!D$3:D$250) -> 0 | AJ83: =SUMIF('2025 AC'!$B$3:$B$250,"*"&$D83&"*",'2025 AC'!E$3:E$250) -> 83.85 | AK83: =SUMIF('2025 AC'!$B$3:$B$250,"*"&$D83&"*",'2025 AC'!F$3:F$250) -> 0 | AL83: =SUMIF('2025 AC'!$B$3:$B$250,"*"&$D83&"*",'2025 AC'!G$3:G$250) -> 130 | AM83: =SUMIF('2025 AC'!$B$3:$B$250,"*"&$D83&"*",'2025 AC'!H$3:H$250) -> 0 | AN83: =SUMIF('2025 AC'!$B$3:$B$250,"*"&$D83&"*",'2025 AC'!I$3:I$250) -> 0 | AO83: =SUMIF('2025 AC'!$B$3:$B$250,"*"&$D83&"*",'2025 AC'!J$3:J$250) -> 0 | ... AS83: =SUMIF('2025 AC'!$B$3:$B$250,"*"&$D83&"*",'2025 AC'!N$3:N$250) -> 66 | AT83: =SUM(AH83:AS83) -> 2328.75 | AU83: =SUM(AH83:AJ83) -> 1708.85 | AV83: =SUM(AK83:AM83) -> 130 | AW83: =SUM(AN83:AP83) -> 0 | AX83: =SUM(AQ83:AS83) -> 489.9 | AY83: =SUM(AU83:AX83) -> 2328.75 | BA83: =SUMIF('2026 AC'!$B$3:$B$254,"*"&$D83&"*",'2026 AC'!C$3:C$254) -> 0 | BB83: =SUMIF('2026 AC'!$B$3:$B$254,"*"&$D83&"*",'2026 AC'!D$3:D$254) -> 0 | BC83: =SUMIF('2026 AC'!$B$3:$B$254,"*"&$D83&"*",'2026 AC'!E$3:E$254) -> 0 | BD83: =SUMIF('2026 AC'!$B$3:$B$254,"*"&$D83&"*",'2026 AC'!F$3:F$254) -> 0 | BE83: =SUMIF('2026 AC'!$B$3:$B$254,"*"&$D83&"*",'2026 AC'!G$3:G$254) -> 0 | BF83: =SUMIF('2026 AC'!$B$3:$B$254,"*"&$D83&"*",'2026 AC'!H$3:H$254) -> 0 | BG83: =SUMIF('2026 AC'!$B$3:$B$254,"*"&$D83&"*",'2026 AC'!I$3:I$254) -> 0 | BH83: =SUMIF('2026 AC'!$B$3:$B$254,"*"&$D83&"*",'2026 AC'!J$3:J$254) -> 0 | ... BL83: =SUMIF('2026 AC'!$B$3:$B$254,"*"&$D83&"*",'2026 AC'!N$3:N$254) -> 0 | BM83: =SUM(BA83:BL83) -> 0 | BN83: =SUM(BA83:BC83) -> 0 | BO83: =SUM(BD83:BF83) -> 0 | BP83: =SUM(BG83:BI83) -> 0 | BQ83: =SUM(BJ83:BL83) -> 0 | BR83: =SUM(BN83:BQ83) -> 0
A84: COST - BANQUET (NON-FOOD) | B84: 610-3000 | C84: COST - BANQUET (NON-FOOD)** | D84: 610-3000 | E84: =SUMIF($BA$6:$BL$6,$E$6,$BA84:$BL84) -> 0 | F84: =SUMIF($AH$6:$AS$6,$F$6,$AH84:$AS84) -> 600 | G84: =(E84-F84)/F84 -> -1 | H84: =SUMIF($BN$6:$BR$6,$H$6,$BN84:$BR84) -> 0 | I84: =SUMIF($AU$6:$AY$6,$I$6,$AU84:$AY84) -> 2984 | J84: =(H84-I84)/I84 -> -1 | K84: =BM84 -> 0 | L84: =SUM(AH84:AM84) -> 5627.5 | M84: =(K84-L84)/L84 -> -1 | O84: =SUMIF('2024 AC'!$B$3:$B$250,"*"&$D84&"*",'2024 AC'!C$3:C$250) -> 750 | P84: =SUMIF('2024 AC'!$B$3:$B$250,"*"&$D84&"*",'2024 AC'!D$3:D$250) -> 1155 | Q84: =SUMIF('2024 AC'!$B$3:$B$250,"*"&$D84&"*",'2024 AC'!E$3:E$250) -> 154 | R84: =SUMIF('2024 AC'!$B$3:$B$250,"*"&$D84&"*",'2024 AC'!F$3:F$250) -> 0 | S84: =SUMIF('2024 AC'!$B$3:$B$250,"*"&$D84&"*",'2024 AC'!G$3:G$250) -> 0 | T84: =SUMIF('2024 AC'!$B$3:$B$250,"*"&$D84&"*",'2024 AC'!H$3:H$250) -> 0 | U84: =SUMIF('2024 AC'!$B$3:$B$250,"*"&$D84&"*",'2024 AC'!I$3:I$250) -> 568 | V84: =SUMIF('2024 AC'!$B$3:$B$250,"*"&$D84&"*",'2024 AC'!J$3:J$250) -> 744 | ... Z84: =SUMIF('2024 AC'!$B$3:$B$250,"*"&$D84&"*",'2024 AC'!N$3:N$250) -> 127.5 | AA84: =SUM(O84:Z84) -> 12684 | AB84: =SUM(O84:Q84) -> 2059 | AC84: =SUM(R84:T84) -> 0 | AD84: =SUM(U84:W84) -> 1738 | AE84: =SUM(X84:Z84) -> 8887 | AF84: =SUM(AB84:AE84) -> 12684 | AH84: =SUMIF('2025 AC'!$B$3:$B$250,"*"&$D84&"*",'2025 AC'!C$3:C$250) -> 2141.5 | AI84: =SUMIF('2025 AC'!$B$3:$B$250,"*"&$D84&"*",'2025 AC'!D$3:D$250) -> 0 | AJ84: =SUMIF('2025 AC'!$B$3:$B$250,"*"&$D84&"*",'2025 AC'!E$3:E$250) -> 502 | AK84: =SUMIF('2025 AC'!$B$3:$B$250,"*"&$D84&"*",'2025 AC'!F$3:F$250) -> 434 | AL84: =SUMIF('2025 AC'!$B$3:$B$250,"*"&$D84&"*",'2025 AC'!G$3:G$250) -> 1950 | AM84: =SUMIF('2025 AC'!$B$3:$B$250,"*"&$D84&"*",'2025 AC'!H$3:H$250) -> 600 | AN84: =SUMIF('2025 AC'!$B$3:$B$250,"*"&$D84&"*",'2025 AC'!I$3:I$250) -> 0 | AO84: =SUMIF('2025 AC'!$B$3:$B$250,"*"&$D84&"*",'2025 AC'!J$3:J$250) -> 708 | ... AS84: =SUMIF('2025 AC'!$B$3:$B$250,"*"&$D84&"*",'2025 AC'!N$3:N$250) -> 0 | AT84: =SUM(AH84:AS84) -> 8673.5 | AU84: =SUM(AH84:AJ84) -> 2643.5 | AV84: =SUM(AK84:AM84) -> 2984 | AW84: =SUM(AN84:AP84) -> 2166 | AX84: =SUM(AQ84:AS84) -> 880 | AY84: =SUM(AU84:AX84) -> 8673.5 | BA84: =SUMIF('2026 AC'!$B$3:$B$254,"*"&$D84&"*",'2026 AC'!C$3:C$254) -> 0 | BB84: =SUMIF('2026 AC'!$B$3:$B$254,"*"&$D84&"*",'2026 AC'!D$3:D$254) -> 0 | BC84: =SUMIF('2026 AC'!$B$3:$B$254,"*"&$D84&"*",'2026 AC'!E$3:E$254) -> 0 | BD84: =SUMIF('2026 AC'!$B$3:$B$254,"*"&$D84&"*",'2026 AC'!F$3:F$254) -> 0 | BE84: =SUMIF('2026 AC'!$B$3:$B$254,"*"&$D84&"*",'2026 AC'!G$3:G$254) -> 0 | BF84: =SUMIF('2026 AC'!$B$3:$B$254,"*"&$D84&"*",'2026 AC'!H$3:H$254) -> 0 | BG84: =SUMIF('2026 AC'!$B$3:$B$254,"*"&$D84&"*",'2026 AC'!I$3:I$254) -> 0 | BH84: =SUMIF('2026 AC'!$B$3:$B$254,"*"&$D84&"*",'2026 AC'!J$3:J$254) -> 0 | ... BL84: =SUMIF('2026 AC'!$B$3:$B$254,"*"&$D84&"*",'2026 AC'!N$3:N$254) -> 0 | BM84: =SUM(BA84:BL84) -> 0 | BN84: =SUM(BA84:BC84) -> 0 | BO84: =SUM(BD84:BF84) -> 0 | BP84: =SUM(BG84:BI84) -> 0 | BQ84: =SUM(BJ84:BL84) -> 0 | BR84: =SUM(BN84:BQ84) -> 0
A85: COST - BANQUET SUPPLIES | B85: 610-3001 | C85: COST - BANQUET SUPPLIES | D85: 610-3001 | E85: =SUMIF($BA$6:$BL$6,$E$6,$BA85:$BL85) -> 0 | F85: =SUMIF($AH$6:$AS$6,$F$6,$AH85:$AS85) -> 705.6 | G85: =IFERROR((E85-F85)/F85,0) -> -1 | H85: =SUMIF($BN$6:$BR$6,$H$6,$BN85:$BR85) -> 0 | I85: =SUMIF($AU$6:$AY$6,$I$6,$AU85:$AY85) -> 705.6 | J85: =(H85-I85)/I85 -> -1 | K85: =BM85 -> 0 | L85: =SUM(AH85:AM85) -> 1582.9 | M85: =(K85-L85)/L85 -> -1 | O85: =SUMIF('2024 AC'!$B$3:$B$250,"*"&$D85&"*",'2024 AC'!C$3:C$250) -> 0 | P85: =SUMIF('2024 AC'!$B$3:$B$250,"*"&$D85&"*",'2024 AC'!D$3:D$250) -> 0 | Q85: =SUMIF('2024 AC'!$B$3:$B$250,"*"&$D85&"*",'2024 AC'!E$3:E$250) -> 0 | R85: =SUMIF('2024 AC'!$B$3:$B$250,"*"&$D85&"*",'2024 AC'!F$3:F$250) -> 0 | S85: =SUMIF('2024 AC'!$B$3:$B$250,"*"&$D85&"*",'2024 AC'!G$3:G$250) -> 0 | T85: =SUMIF('2024 AC'!$B$3:$B$250,"*"&$D85&"*",'2024 AC'!H$3:H$250) -> 0 | U85: =SUMIF('2024 AC'!$B$3:$B$250,"*"&$D85&"*",'2024 AC'!I$3:I$250) -> 0 | V85: =SUMIF('2024 AC'!$B$3:$B$250,"*"&$D85&"*",'2024 AC'!J$3:J$250) -> 705.6 | ... Z85: =SUMIF('2024 AC'!$B$3:$B$250,"*"&$D85&"*",'2024 AC'!N$3:N$250) -> 0 | AA85: =SUM(O85:Z85) -> 1411.2 | AB85: =SUM(O85:Q85) -> 0 | AC85: =SUM(R85:T85) -> 0 | AD85: =SUM(U85:W85) -> 1411.2 | AE85: =SUM(X85:Z85) -> 0 | AF85: =SUM(AB85:AE85) -> 1411.2 | AH85: =SUMIF('2025 AC'!$B$3:$B$250,"*"&$D85&"*",'2025 AC'!C$3:C$250) -> 705.6 | AI85: =SUMIF('2025 AC'!$B$3:$B$250,"*"&$D85&"*",'2025 AC'!D$3:D$250) -> 171.7 | AJ85: =SUMIF('2025 AC'!$B$3:$B$250,"*"&$D85&"*",'2025 AC'!E$3:E$250) -> 0 | AK85: =SUMIF('2025 AC'!$B$3:$B$250,"*"&$D85&"*",'2025 AC'!F$3:F$250) -> 0 | AL85: =SUMIF('2025 AC'!$B$3:$B$250,"*"&$D85&"*",'2025 AC'!G$3:G$250) -> 0 | AM85: =SUMIF('2025 AC'!$B$3:$B$250,"*"&$D85&"*",'2025 AC'!H$3:H$250) -> 705.6 | AN85: =SUMIF('2025 AC'!$B$3:$B$250,"*"&$D85&"*",'2025 AC'!I$3:I$250) -> 0 | AO85: =SUMIF('2025 AC'!$B$3:$B$250,"*"&$D85&"*",'2025 AC'!J$3:J$250) -> 0 | ... AS85: =SUMIF('2025 AC'!$B$3:$B$250,"*"&$D85&"*",'2025 AC'!N$3:N$250) -> 705.6 | AT85: =SUM(AH85:AS85) -> 2994.1 | AU85: =SUM(AH85:AJ85) -> 877.3 | AV85: =SUM(AK85:AM85) -> 705.6 | AW85: =SUM(AN85:AP85) -> 0 | AX85: =SUM(AQ85:AS85) -> 1411.2 | AY85: =SUM(AU85:AX85) -> 2994.1 | BA85: =SUMIF('2026 AC'!$B$3:$B$254,"*"&$D85&"*",'2026 AC'!C$3:C$254) -> 0 | BB85: =SUMIF('2026 AC'!$B$3:$B$254,"*"&$D85&"*",'2026 AC'!D$3:D$254) -> 0 | BC85: =SUMIF('2026 AC'!$B$3:$B$254,"*"&$D85&"*",'2026 AC'!E$3:E$254) -> 0 | BD85: =SUMIF('2026 AC'!$B$3:$B$254,"*"&$D85&"*",'2026 AC'!F$3:F$254) -> 0 | BE85: =SUMIF('2026 AC'!$B$3:$B$254,"*"&$D85&"*",'2026 AC'!G$3:G$254) -> 0 | BF85: =SUMIF('2026 AC'!$B$3:$B$254,"*"&$D85&"*",'2026 AC'!H$3:H$254) -> 0 | BG85: =SUMIF('2026 AC'!$B$3:$B$254,"*"&$D85&"*",'2026 AC'!I$3:I$254) -> 0 | BH85: =SUMIF('2026 AC'!$B$3:$B$254,"*"&$D85&"*",'2026 AC'!J$3:J$254) -> 0 | ... BL85: =SUMIF('2026 AC'!$B$3:$B$254,"*"&$D85&"*",'2026 AC'!N$3:N$254) -> 0 | BM85: =SUM(BA85:BL85) -> 0 | BN85: =SUM(BA85:BC85) -> 0 | BO85: =SUM(BD85:BF85) -> 0 | BP85: =SUM(BG85:BI85) -> 0 | BQ85: =SUM(BJ85:BL85) -> 0 | BR85: =SUM(BN85:BQ85) -> 0
A86: COST - BANQUET SETUP | B86: 610-3002 | C86: COST - BANQUET SETUP | D86: 610-3002 | E86: =SUMIF($BA$6:$BL$6,$E$6,$BA86:$BL86) -> 0 | F86: =SUMIF($AH$6:$AS$6,$F$6,$AH86:$AS86) -> 0 | G86: =IFERROR((E86-F86)/F86,0) -> 0 | H86: =SUMIF($BN$6:$BR$6,$H$6,$BN86:$BR86) -> 0 | I86: =SUMIF($AU$6:$AY$6,$I$6,$AU86:$AY86) -> 0 | J86: =IFERROR((H86-I86)/I86,0) -> 0 | K86: =BM86 -> 0 | L86: =SUM(AH86:AM86) -> 0 | M86: =IFERROR((K86-L86)/L86,0) -> 0 | O86: =SUMIF('2024 AC'!$B$3:$B$250,"*"&$D86&"*",'2024 AC'!C$3:C$250) -> 0 | P86: =SUMIF('2024 AC'!$B$3:$B$250,"*"&$D86&"*",'2024 AC'!D$3:D$250) -> 0 | Q86: =SUMIF('2024 AC'!$B$3:$B$250,"*"&$D86&"*",'2024 AC'!E$3:E$250) -> 0 | R86: =SUMIF('2024 AC'!$B$3:$B$250,"*"&$D86&"*",'2024 AC'!F$3:F$250) -> 0 | S86: =SUMIF('2024 AC'!$B$3:$B$250,"*"&$D86&"*",'2024 AC'!G$3:G$250) -> 0 | T86: =SUMIF('2024 AC'!$B$3:$B$250,"*"&$D86&"*",'2024 AC'!H$3:H$250) -> 0 | U86: =SUMIF('2024 AC'!$B$3:$B$250,"*"&$D86&"*",'2024 AC'!I$3:I$250) -> 0 | V86: =SUMIF('2024 AC'!$B$3:$B$250,"*"&$D86&"*",'2024 AC'!J$3:J$250) -> 0 | ... Z86: =SUMIF('2024 AC'!$B$3:$B$250,"*"&$D86&"*",'2024 AC'!N$3:N$250) -> 0 | AA86: =SUM(O86:Z86) -> 0 | AB86: =SUM(O86:Q86) -> 0 | AC86: =SUM(R86:T86) -> 0 | AD86: =SUM(U86:W86) -> 0 | AE86: =SUM(X86:Z86) -> 0 | AF86: =SUM(AB86:AE86) -> 0 | AH86: =SUMIF('2025 AC'!$B$3:$B$250,"*"&$D86&"*",'2025 AC'!C$3:C$250) -> 0 | AI86: =SUMIF('2025 AC'!$B$3:$B$250,"*"&$D86&"*",'2025 AC'!D$3:D$250) -> 0 | AJ86: =SUMIF('2025 AC'!$B$3:$B$250,"*"&$D86&"*",'2025 AC'!E$3:E$250) -> 0 | AK86: =SUMIF('2025 AC'!$B$3:$B$250,"*"&$D86&"*",'2025 AC'!F$3:F$250) -> 0 | AL86: =SUMIF('2025 AC'!$B$3:$B$250,"*"&$D86&"*",'2025 AC'!G$3:G$250) -> 0 | AM86: =SUMIF('2025 AC'!$B$3:$B$250,"*"&$D86&"*",'2025 AC'!H$3:H$250) -> 0 | AN86: =SUMIF('2025 AC'!$B$3:$B$250,"*"&$D86&"*",'2025 AC'!I$3:I$250) -> 0 | AO86: =SUMIF('2025 AC'!$B$3:$B$250,"*"&$D86&"*",'2025 AC'!J$3:J$250) -> 0 | ... AS86: =SUMIF('2025 AC'!$B$3:$B$250,"*"&$D86&"*",'2025 AC'!N$3:N$250) -> 0 | AT86: =SUM(AH86:AS86) -> 0 | AU86: =SUM(AH86:AJ86) -> 0 | AV86: =SUM(AK86:AM86) -> 0 | AW86: =SUM(AN86:AP86) -> 0 | AX86: =SUM(AQ86:AS86) -> 0 | AY86: =SUM(AU86:AX86) -> 0 | BA86: =SUMIF('2026 AC'!$B$3:$B$254,"*"&$D86&"*",'2026 AC'!C$3:C$254) -> 0 | BB86: =SUMIF('2026 AC'!$B$3:$B$254,"*"&$D86&"*",'2026 AC'!D$3:D$254) -> 0 | BC86: =SUMIF('2026 AC'!$B$3:$B$254,"*"&$D86&"*",'2026 AC'!E$3:E$254) -> 0 | BD86: =SUMIF('2026 AC'!$B$3:$B$254,"*"&$D86&"*",'2026 AC'!F$3:F$254) -> 0 | BE86: =SUMIF('2026 AC'!$B$3:$B$254,"*"&$D86&"*",'2026 AC'!G$3:G$254) -> 0 | BF86: =SUMIF('2026 AC'!$B$3:$B$254,"*"&$D86&"*",'2026 AC'!H$3:H$254) -> 0 | BG86: =SUMIF('2026 AC'!$B$3:$B$254,"*"&$D86&"*",'2026 AC'!I$3:I$254) -> 0 | BH86: =SUMIF('2026 AC'!$B$3:$B$254,"*"&$D86&"*",'2026 AC'!J$3:J$254) -> 0 | ... BL86: =SUMIF('2026 AC'!$B$3:$B$254,"*"&$D86&"*",'2026 AC'!N$3:N$254) -> 0 | BM86: =SUM(BA86:BL86) -> 0 | BN86: =SUM(BA86:BC86) -> 0 | BO86: =SUM(BD86:BF86) -> 0 | BP86: =SUM(BG86:BI86) -> 0 | BQ86: =SUM(BJ86:BL86) -> 0 | BR86: =SUM(BN86:BQ86) -> 0
A87: COST - BANQUET MUSICIAN FEES | B87: 610-3003 | C87: COST - BANQUET MUSICIAN FEES | D87: 610-3003 | E87: =SUMIF($BA$6:$BL$6,$E$6,$BA87:$BL87) -> 0 | F87: =SUMIF($AH$6:$AS$6,$F$6,$AH87:$AS87) -> 0 | G87: =IFERROR((E87-F87)/F87,0) -> 0 | H87: =SUMIF($BN$6:$BR$6,$H$6,$BN87:$BR87) -> 0 | I87: =SUMIF($AU$6:$AY$6,$I$6,$AU87:$AY87) -> 0 | J87: =IFERROR((H87-I87)/I87,0) -> 0 | K87: =BM87 -> 0 | L87: =SUM(AH87:AM87) -> 0 | M87: =IFERROR((K87-L87)/L87,0) -> 0 | O87: =SUMIF('2024 AC'!$B$3:$B$250,"*"&$D87&"*",'2024 AC'!C$3:C$250) -> 0 | P87: =SUMIF('2024 AC'!$B$3:$B$250,"*"&$D87&"*",'2024 AC'!D$3:D$250) -> 0 | Q87: =SUMIF('2024 AC'!$B$3:$B$250,"*"&$D87&"*",'2024 AC'!E$3:E$250) -> 0 | R87: =SUMIF('2024 AC'!$B$3:$B$250,"*"&$D87&"*",'2024 AC'!F$3:F$250) -> 0 | S87: =SUMIF('2024 AC'!$B$3:$B$250,"*"&$D87&"*",'2024 AC'!G$3:G$250) -> 0 | T87: =SUMIF('2024 AC'!$B$3:$B$250,"*"&$D87&"*",'2024 AC'!H$3:H$250) -> 0 | U87: =SUMIF('2024 AC'!$B$3:$B$250,"*"&$D87&"*",'2024 AC'!I$3:I$250) -> 0 | V87: =SUMIF('2024 AC'!$B$3:$B$250,"*"&$D87&"*",'2024 AC'!J$3:J$250) -> 0 | ... Z87: =SUMIF('2024 AC'!$B$3:$B$250,"*"&$D87&"*",'2024 AC'!N$3:N$250) -> 0 | AA87: =SUM(O87:Z87) -> 0 | AB87: =SUM(O87:Q87) -> 0 | AC87: =SUM(R87:T87) -> 0 | AD87: =SUM(U87:W87) -> 0 | AE87: =SUM(X87:Z87) -> 0 | AF87: =SUM(AB87:AE87) -> 0 | AH87: =SUMIF('2025 AC'!$B$3:$B$250,"*"&$D87&"*",'2025 AC'!C$3:C$250) -> 0 | AI87: =SUMIF('2025 AC'!$B$3:$B$250,"*"&$D87&"*",'2025 AC'!D$3:D$250) -> 0 | AJ87: =SUMIF('2025 AC'!$B$3:$B$250,"*"&$D87&"*",'2025 AC'!E$3:E$250) -> 0 | AK87: =SUMIF('2025 AC'!$B$3:$B$250,"*"&$D87&"*",'2025 AC'!F$3:F$250) -> 0 | AL87: =SUMIF('2025 AC'!$B$3:$B$250,"*"&$D87&"*",'2025 AC'!G$3:G$250) -> 0 | AM87: =SUMIF('2025 AC'!$B$3:$B$250,"*"&$D87&"*",'2025 AC'!H$3:H$250) -> 0 | AN87: =SUMIF('2025 AC'!$B$3:$B$250,"*"&$D87&"*",'2025 AC'!I$3:I$250) -> 0 | AO87: =SUMIF('2025 AC'!$B$3:$B$250,"*"&$D87&"*",'2025 AC'!J$3:J$250) -> 0 | ... AS87: =SUMIF('2025 AC'!$B$3:$B$250,"*"&$D87&"*",'2025 AC'!N$3:N$250) -> 0 | AT87: =SUM(AH87:AS87) -> 0 | AU87: =SUM(AH87:AJ87) -> 0 | AV87: =SUM(AK87:AM87) -> 0 | AW87: =SUM(AN87:AP87) -> 0 | AX87: =SUM(AQ87:AS87) -> 0 | AY87: =SUM(AU87:AX87) -> 0 | BA87: =SUMIF('2026 AC'!$B$3:$B$254,"*"&$D87&"*",'2026 AC'!C$3:C$254) -> 0 | BB87: =SUMIF('2026 AC'!$B$3:$B$254,"*"&$D87&"*",'2026 AC'!D$3:D$254) -> 0 | BC87: =SUMIF('2026 AC'!$B$3:$B$254,"*"&$D87&"*",'2026 AC'!E$3:E$254) -> 0 | BD87: =SUMIF('2026 AC'!$B$3:$B$254,"*"&$D87&"*",'2026 AC'!F$3:F$254) -> 0 | BE87: =SUMIF('2026 AC'!$B$3:$B$254,"*"&$D87&"*",'2026 AC'!G$3:G$254) -> 0 | BF87: =SUMIF('2026 AC'!$B$3:$B$254,"*"&$D87&"*",'2026 AC'!H$3:H$254) -> 0 | BG87: =SUMIF('2026 AC'!$B$3:$B$254,"*"&$D87&"*",'2026 AC'!I$3:I$254) -> 0 | BH87: =SUMIF('2026 AC'!$B$3:$B$254,"*"&$D87&"*",'2026 AC'!J$3:J$254) -> 0 | ... BL87: =SUMIF('2026 AC'!$B$3:$B$254,"*"&$D87&"*",'2026 AC'!N$3:N$254) -> 0 | BM87: =SUM(BA87:BL87) -> 0 | BN87: =SUM(BA87:BC87) -> 0 | BO87: =SUM(BD87:BF87) -> 0 | BP87: =SUM(BG87:BI87) -> 0 | BQ87: =SUM(BJ87:BL87) -> 0 | BR87: =SUM(BN87:BQ87) -> 0
A88: COST F&B | B88: 610-2000 | C88: COST F&B** | D88: 610-2000 | E88: =SUMIF($BA$6:$BL$6,$E$6,$BA88:$BL88) -> 28190.81 | F88: =SUMIF($AH$6:$AS$6,$F$6,$AH88:$AS88) -> 25438.85 | G88: =(E88-F88)/F88 -> 0.10817942 | H88: =SUMIF($BN$6:$BR$6,$H$6,$BN88:$BR88) -> 79005.26 | I88: =SUMIF($AU$6:$AY$6,$I$6,$AU88:$AY88) -> 105277.84 | J88: =(H88-I88)/I88 -> -0.2495547 | K88: =BM88 -> 206626.83 | L88: =SUM(AH88:AM88) -> 266927.18 | M88: =(K88-L88)/L88 -> -0.22590562 | O88: =SUMIF('2024 AC'!$B$3:$B$250,"*"&$D88&"*",'2024 AC'!C$3:C$250) -> 29788.53 | P88: =SUMIF('2024 AC'!$B$3:$B$250,"*"&$D88&"*",'2024 AC'!D$3:D$250) -> 29491.43 | Q88: =SUMIF('2024 AC'!$B$3:$B$250,"*"&$D88&"*",'2024 AC'!E$3:E$250) -> 55712.24 | R88: =SUMIF('2024 AC'!$B$3:$B$250,"*"&$D88&"*",'2024 AC'!F$3:F$250) -> 37724.13 | S88: =SUMIF('2024 AC'!$B$3:$B$250,"*"&$D88&"*",'2024 AC'!G$3:G$250) -> 41528.08 | T88: =SUMIF('2024 AC'!$B$3:$B$250,"*"&$D88&"*",'2024 AC'!H$3:H$250) -> 34919.51 | U88: =SUMIF('2024 AC'!$B$3:$B$250,"*"&$D88&"*",'2024 AC'!I$3:I$250) -> 34061.62 | V88: =SUMIF('2024 AC'!$B$3:$B$250,"*"&$D88&"*",'2024 AC'!J$3:J$250) -> 49193.62 | ... Z88: =SUMIF('2024 AC'!$B$3:$B$250,"*"&$D88&"*",'2024 AC'!N$3:N$250) -> 36482.51 | AA88: =SUM(O88:Z88) -> 473642.7 | AB88: =SUM(O88:Q88) -> 114992.2 | AC88: =SUM(R88:T88) -> 114171.72 | AD88: =SUM(U88:W88) -> 119889.92 | AE88: =SUM(X88:Z88) -> 124588.86 | AF88: =SUM(AB88:AE88) -> 473642.7 | AH88: =SUMIF('2025 AC'!$B$3:$B$250,"*"&$D88&"*",'2025 AC'!C$3:C$250) -> 47566.77 | AI88: =SUMIF('2025 AC'!$B$3:$B$250,"*"&$D88&"*",'2025 AC'!D$3:D$250) -> 31316.32 | AJ88: =SUMIF('2025 AC'!$B$3:$B$250,"*"&$D88&"*",'2025 AC'!E$3:E$250) -> 82766.25 | AK88: =SUMIF('2025 AC'!$B$3:$B$250,"*"&$D88&"*",'2025 AC'!F$3:F$250) -> 31736.32 | AL88: =SUMIF('2025 AC'!$B$3:$B$250,"*"&$D88&"*",'2025 AC'!G$3:G$250) -> 48102.67 | AM88: =SUMIF('2025 AC'!$B$3:$B$250,"*"&$D88&"*",'2025 AC'!H$3:H$250) -> 25438.85 | AN88: =SUMIF('2025 AC'!$B$3:$B$250,"*"&$D88&"*",'2025 AC'!I$3:I$250) -> 31307.54 | AO88: =SUMIF('2025 AC'!$B$3:$B$250,"*"&$D88&"*",'2025 AC'!J$3:J$250) -> 33134.88 | ... AS88: =SUMIF('2025 AC'!$B$3:$B$250,"*"&$D88&"*",'2025 AC'!N$3:N$250) -> 43879.58 | AT88: =SUM(AH88:AS88) -> 480062.41 | AU88: =SUM(AH88:AJ88) -> 161649.34 | AV88: =SUM(AK88:AM88) -> 105277.84 | AW88: =SUM(AN88:AP88) -> 104132.39 | AX88: =SUM(AQ88:AS88) -> 109002.84 | AY88: =SUM(AU88:AX88) -> 480062.41 | BA88: =SUMIF('2026 AC'!$B$3:$B$254,"*"&$D88&"*",'2026 AC'!C$3:C$254) -> 34428.98 | BB88: =SUMIF('2026 AC'!$B$3:$B$254,"*"&$D88&"*",'2026 AC'!D$3:D$254) -> 43138.18 | BC88: =SUMIF('2026 AC'!$B$3:$B$254,"*"&$D88&"*",'2026 AC'!E$3:E$254) -> 50054.41 | BD88: =SUMIF('2026 AC'!$B$3:$B$254,"*"&$D88&"*",'2026 AC'!F$3:F$254) -> 30865.2 | BE88: =SUMIF('2026 AC'!$B$3:$B$254,"*"&$D88&"*",'2026 AC'!G$3:G$254) -> 19949.25 | BF88: =SUMIF('2026 AC'!$B$3:$B$254,"*"&$D88&"*",'2026 AC'!H$3:H$254) -> 28190.81 | BG88: =SUMIF('2026 AC'!$B$3:$B$254,"*"&$D88&"*",'2026 AC'!I$3:I$254) -> 0 | BH88: =SUMIF('2026 AC'!$B$3:$B$254,"*"&$D88&"*",'2026 AC'!J$3:J$254) -> 0 | ... BL88: =SUMIF('2026 AC'!$B$3:$B$254,"*"&$D88&"*",'2026 AC'!N$3:N$254) -> 0 | BM88: =SUM(BA88:BL88) -> 206626.83 | BN88: =SUM(BA88:BC88) -> 127621.57 | BO88: =SUM(BD88:BF88) -> 79005.26 | BP88: =SUM(BG88:BI88) -> 0 | BQ88: =SUM(BJ88:BL88) -> 0 | BR88: =SUM(BN88:BQ88) -> 206626.83
A89: COST F&B - G3 | B89: 610-2001 | C89: COST F&B - G3** | D89: 610-2001 | E89: =SUMIF($BA$6:$BL$6,$E$6,$BA89:$BL89) -> 0 | F89: =SUMIF($AH$6:$AS$6,$F$6,$AH89:$AS89) -> 0 | G89: =IFERROR((E89-F89)/F89,0) -> 0 | H89: =SUMIF($BN$6:$BR$6,$H$6,$BN89:$BR89) -> 0 | I89: =SUMIF($AU$6:$AY$6,$I$6,$AU89:$AY89) -> 0 | J89: =IFERROR((H89-I89)/I89,0) -> 0 | K89: =BM89 -> 0 | L89: =SUM(AH89:AM89) -> 0 | M89: =IFERROR((K89-L89)/L89,0) -> 0 | O89: =SUMIF('2024 AC'!$B$3:$B$250,"*"&$D89&"*",'2024 AC'!C$3:C$250) -> 10073.78 | P89: =SUMIF('2024 AC'!$B$3:$B$250,"*"&$D89&"*",'2024 AC'!D$3:D$250) -> 15159.85 | Q89: =SUMIF('2024 AC'!$B$3:$B$250,"*"&$D89&"*",'2024 AC'!E$3:E$250) -> 21490.76 | R89: =SUMIF('2024 AC'!$B$3:$B$250,"*"&$D89&"*",'2024 AC'!F$3:F$250) -> 12407.46 | S89: =SUMIF('2024 AC'!$B$3:$B$250,"*"&$D89&"*",'2024 AC'!G$3:G$250) -> 10317.15 | T89: =SUMIF('2024 AC'!$B$3:$B$250,"*"&$D89&"*",'2024 AC'!H$3:H$250) -> 0 | U89: =SUMIF('2024 AC'!$B$3:$B$250,"*"&$D89&"*",'2024 AC'!I$3:I$250) -> 0 | V89: =SUMIF('2024 AC'!$B$3:$B$250,"*"&$D89&"*",'2024 AC'!J$3:J$250) -> 0 | ... Z89: =SUMIF('2024 AC'!$B$3:$B$250,"*"&$D89&"*",'2024 AC'!N$3:N$250) -> 0 | AA89: =SUM(O89:Z89) -> 69449 | AB89: =SUM(O89:Q89) -> 46724.39 | AC89: =SUM(R89:T89) -> 22724.61 | AD89: =SUM(U89:W89) -> 0 | AE89: =SUM(X89:Z89) -> 0 | AF89: =SUM(AB89:AE89) -> 69449 | AH89: =SUMIF('2025 AC'!$B$3:$B$250,"*"&$D89&"*",'2025 AC'!C$3:C$250) -> 0 | AI89: =SUMIF('2025 AC'!$B$3:$B$250,"*"&$D89&"*",'2025 AC'!D$3:D$250) -> 0 | AJ89: =SUMIF('2025 AC'!$B$3:$B$250,"*"&$D89&"*",'2025 AC'!E$3:E$250) -> 0 | AK89: =SUMIF('2025 AC'!$B$3:$B$250,"*"&$D89&"*",'2025 AC'!F$3:F$250) -> 0 | AL89: =SUMIF('2025 AC'!$B$3:$B$250,"*"&$D89&"*",'2025 AC'!G$3:G$250) -> 0 | AM89: =SUMIF('2025 AC'!$B$3:$B$250,"*"&$D89&"*",'2025 AC'!H$3:H$250) -> 0 | AN89: =SUMIF('2025 AC'!$B$3:$B$250,"*"&$D89&"*",'2025 AC'!I$3:I$250) -> 0 | AO89: =SUMIF('2025 AC'!$B$3:$B$250,"*"&$D89&"*",'2025 AC'!J$3:J$250) -> 0 | ... AS89: =SUMIF('2025 AC'!$B$3:$B$250,"*"&$D89&"*",'2025 AC'!N$3:N$250) -> 0 | AT89: =SUM(AH89:AS89) -> 0 | AU89: =SUM(AH89:AJ89) -> 0 | AV89: =SUM(AK89:AM89) -> 0 | AW89: =SUM(AN89:AP89) -> 0 | AX89: =SUM(AQ89:AS89) -> 0 | AY89: =SUM(AU89:AX89) -> 0 | BA89: =SUMIF('2026 AC'!$B$3:$B$254,"*"&$D89&"*",'2026 AC'!C$3:C$254) -> 0 | BB89: =SUMIF('2026 AC'!$B$3:$B$254,"*"&$D89&"*",'2026 AC'!D$3:D$254) -> 0 | BC89: =SUMIF('2026 AC'!$B$3:$B$254,"*"&$D89&"*",'2026 AC'!E$3:E$254) -> 0 | BD89: =SUMIF('2026 AC'!$B$3:$B$254,"*"&$D89&"*",'2026 AC'!F$3:F$254) -> 0 | BE89: =SUMIF('2026 AC'!$B$3:$B$254,"*"&$D89&"*",'2026 AC'!G$3:G$254) -> 0 | BF89: =SUMIF('2026 AC'!$B$3:$B$254,"*"&$D89&"*",'2026 AC'!H$3:H$254) -> 0 | BG89: =SUMIF('2026 AC'!$B$3:$B$254,"*"&$D89&"*",'2026 AC'!I$3:I$254) -> 0 | BH89: =SUMIF('2026 AC'!$B$3:$B$254,"*"&$D89&"*",'2026 AC'!J$3:J$254) -> 0 | ... BL89: =SUMIF('2026 AC'!$B$3:$B$254,"*"&$D89&"*",'2026 AC'!N$3:N$254) -> 0 | BM89: =SUM(BA89:BL89) -> 0 | BN89: =SUM(BA89:BC89) -> 0 | BO89: =SUM(BD89:BF89) -> 0 | BP89: =SUM(BG89:BI89) -> 0 | BQ89: =SUM(BJ89:BL89) -> 0 | BR89: =SUM(BN89:BQ89) -> 0
